Workbook

Sheet Total 
A1: Note: 4th week meetings, talk about accrued expenses | C1: January | D1: February | E1: March | F1: April | G1: May | H1: June | I1: July | J1: August | K1: September | L1: October | M1: November | N1: December | O1: Total | Q1: 24 vs 25 Bud Var
A2: TOTAL | B2: Actual 2024 | C2: =SUMIFS(C18:C204,$B$18:$B$204,"Actual 2024") -> 279328.95 | D2: =SUMIFS(D18:D204,$B$18:$B$204,"Actual 2024") -> 270214.24 | E2: =SUMIFS(E18:E204,$B$18:$B$204,"Actual 2024") -> 361676.73 | F2: =SUMIFS(F18:F204,$B$18:$B$204,"Actual 2024") -> 340089.85 | G2: =SUMIFS(G18:G204,$B$18:$B$204,"Actual 2024") -> 352828.34 | H2: =SUMIFS(H18:H204,$B$18:$B$204,"Actual 2024") -> 279066.85 | I2: =SUMIFS(I18:I204,$B$18:$B$204,"Actual 2024") -> 304345.61 | J2: =SUMIFS(J18:J204,$B$18:$B$204,"Actual 2024") -> 304643.71 | ... N2: =SUMIFS(N18:N204,$B$18:$B$204,"Actual 2024") -> 300395.3 | O2: =SUM(C2:N2) -> 3803746.5
B3: Estimated 2025 | C3: =SUMIFS(C18:C204,$B$18:$B$204,"Estimated") -> 386832.24 | D3: =SUMIFS(D18:D204,$B$18:$B$204,"Estimated") -> 390190.88 | E3: =SUMIFS(E18:E204,$B$18:$B$204,"Estimated") -> 370736.1 | F3: =SUMIFS(F18:F204,$B$18:$B$204,"Estimated") -> 341182.5 | G3: =SUMIFS(G18:G204,$B$18:$B$204,"Estimated") -> 361749.72 | H3: =SUMIFS(H18:H204,$B$18:$B$204,"Estimated") -> 330303.67 | I3: =SUMIFS(I18:I204,$B$18:$B$204,"Estimated") -> 298664.66 | J3: =SUMIFS(J18:J204,$B$18:$B$204,"Estimated") -> 327027.09 | ... N3: =SUMIFS(N18:N204,$B$18:$B$204,"Estimated") -> 321172.34 | O3: =SUM(C3:N3) -> 4131703.6
B4: Budget | C4: =SUMIFS(C18:C204,$B$18:$B$204,"Budget") -> 343948.15 | D4: =SUMIFS(D18:D204,$B$18:$B$204,"Budget") -> 389470.6 | E4: =SUMIFS(E18:E204,$B$18:$B$204,"Budget") -> 369659.21 | F4: =SUMIFS(F18:F204,$B$18:$B$204,"Budget") -> 337869.28 | G4: =SUMIFS(G18:G204,$B$18:$B$204,"Budget") -> 349380.65 | H4: =SUMIFS(H18:H204,$B$18:$B$204,"Budget") -> 323922 | I4: =SUMIFS(I18:I204,$B$18:$B$204,"Budget") -> 299871.66 | J4: =SUMIFS(J18:J204,$B$18:$B$204,"Budget") -> 315111.1 | ... N4: =SUMIFS(N18:N204,$B$18:$B$204,"Budget") -> 319183.58 | O4: =SUM(C4:N4) -> 4033309.9
B5: Actual | C5: =SUMIFS(C18:C204,$B$18:$B$204,"Actual") -> 356907.3 | D5: =SUMIFS(D18:D204,$B$18:$B$204,"Actual") -> 344891.48 | E5: =SUMIFS(E18:E204,$B$18:$B$204,"Actual") -> 403531.82 | F5: =SUMIFS(F18:F204,$B$18:$B$204,"Actual") -> 381063.99 | G5: =SUMIFS(G18:G204,$B$18:$B$204,"Actual") -> 408641.75 | H5: =SUMIFS(H18:H204,$B$18:$B$204,"Actual") -> 384046.39 | I5: =SUMIFS(I18:I204,$B$18:$B$204,"Actual") -> 392927.52 | J5: =SUMIFS(J18:J204,$B$18:$B$204,"Actual") -> 400678.58 | ... N5: =SUMIFS(N18:N204,$B$18:$B$204,"Actual") -> 0 | O5: =SUM(C5:N5) -> 3636337.2 | Q5: =O3-O2 -> 327957.12 | R5: Change Y/Y | S5: =Q5/O2 -> 0.0862195
B6: Budget Deficit/ Savings | C6: =C14 -> -12959.15 | D6: =D4-D5 -> 44579.12 | E6: =E4-E5 -> -33872.61 | F6: =F4-F5 -> -43194.71 | G6: =G4-G5 -> -59261.1 | H6: =H4-H5 -> -60124.39 | I6: =I4-I5 -> -93055.86 | J6: =J4-J5 -> -85567.48 | O6: =SUM(C6:N6) -> -343456.18 | Q6: =Q28 -> 65960.05 | R6: Change in Performance Based
B7: Year to Date Spend | C7: =SUM($C5:C5) -> 356907.3 | D7: =SUM($C5:D5) -> 701798.78 | E7: =SUM($C5:E5) -> 1105330.6 | F7: =SUM($C5:F5) -> 1486394.6 | G7: =SUM($C5:G5) -> 1895036.3 | H7: =SUM($C5:H5) -> 2279082.7 | I7: =SUM($C5:I5) -> 2672010.2 | J7: =SUM($C5:J5) -> 3072688.8 | O7: =O5 -> 3636337.2 | Q7: =Q5-Q6 -> 261997.07 | R7: Change in everything else | S7: =Q7/O2 -> 0.068878689
B8: YTD Excess From Budget | C8: =C4-C7 -> -12959.15 | D8: =SUM($C4:D4)-D7 -> 31619.97 | E8: =SUM($C4:E4)-E7 -> -2252.64 | F8: =SUM($C4:F4)-F7 -> -45447.35 | G8: =SUM($C4:G4)-G7 -> -104708.45 | H8: =SUM($C4:H4)-H7 -> -164832.84 | I8: =SUM($C4:I4)-I7 -> -257888.7 | J8: =SUM($C4:J4)-J7 -> -343456.18 | O8: =SUM(C8:N8) -> -899925.34
A10: Westbound | B10: Actual 2024 | C10: =SUMIFS(C18:C195,$B$18:$B$195,"Actual 2024") -> 276395.89 | D10: =SUMIFS(D18:D195,$B$18:$B$195,"Actual 2024") -> 265891.91 | E10: =SUMIFS(E18:E195,$B$18:$B$195,"Actual 2024") -> 318342.66 | F10: =SUMIFS(F18:F195,$B$18:$B$195,"Actual 2024") -> 332878.99 | G10: =SUMIFS(G18:G195,$B$18:$B$195,"Actual 2024") -> 348416.69 | H10: =SUMIFS(H18:H195,$B$18:$B$195,"Actual 2024") -> 274374.54 | I10: =SUMIFS(I18:I195,$B$18:$B$195,"Actual 2024") -> 299083.16 | J10: =SUMIFS(J18:J195,$B$18:$B$195,"Actual 2024") -> 299928.02 | ... N10: =SUMIFS(N18:N195,$B$18:$B$195,"Actual 2024") -> 295673.58 | O10: =SUM(C10:N10) -> 3703393
B11: Estimated | C11: =SUMIFS(C18:C195,$B$18:$B$195,"Estimated") -> 386832.24 | D11: =SUMIFS(D18:D195,$B$18:$B$195,"Estimated") -> 390190.88 | E11: =SUMIFS(E18:E195,$B$18:$B$195,"Estimated") -> 370736.1 | F11: =SUMIFS(F18:F195,$B$18:$B$195,"Estimated") -> 341182.5 | G11: =SUMIFS(G18:G195,$B$18:$B$195,"Estimated") -> 361749.72 | H11: =SUMIFS(H18:H195,$B$18:$B$195,"Estimated") -> 330303.67 | I11: =SUMIFS(I18:I195,$B$18:$B$195,"Estimated") -> 298664.66 | J11: =SUMIFS(J18:J195,$B$18:$B$195,"Estimated") -> 327027.09 | ... N11: =SUMIFS(N18:N195,$B$18:$B$195,"Estimated") -> 321172.34 | O11: =SUM(C11:N11) -> 4131703.6
B12: Budget | C12: =SUMIFS(C18:C195,$B$18:$B$195,"Budget") -> 343948.15 | D12: =SUMIFS(D18:D195,$B$18:$B$195,"Budget") -> 389470.6 | E12: =SUMIFS(E18:E195,$B$18:$B$195,"Budget") -> 369659.21 | F12: =SUMIFS(F18:F195,$B$18:$B$195,"Budget") -> 337869.28 | G12: =SUMIFS(G18:G195,$B$18:$B$195,"Budget") -> 349380.65 | H12: =SUMIFS(H18:H195,$B$18:$B$195,"Budget") -> 323922 | I12: =SUMIFS(I18:I195,$B$18:$B$195,"Budget") -> 299871.66 | J12: =SUMIFS(J18:J195,$B$18:$B$195,"Budget") -> 315111.1 | ... N12: =SUMIFS(N18:N195,$B$18:$B$195,"Budget") -> 319183.58 | O12: =SUM(C12:N12) -> 4033309.9
B13: Actual | C13: =SUMIFS(C18:C195,$B$18:$B$195,"Actual") -> 356907.3 | D13: =SUMIFS(D18:D195,$B$18:$B$195,"Actual") -> 344891.48 | E13: =SUMIFS(E18:E195,$B$18:$B$195,"Actual") -> 403531.82 | F13: =SUMIFS(F18:F195,$B$18:$B$195,"Actual") -> 381063.99 | G13: =SUMIFS(G18:G195,$B$18:$B$195,"Actual") -> 408641.75 | H13: =SUMIFS(H18:H195,$B$18:$B$195,"Actual") -> 384046.39 | I13: =SUMIFS(I18:I195,$B$18:$B$195,"Actual") -> 392927.52 | J13: =SUMIFS(J18:J195,$B$18:$B$195,"Actual") -> 400678.58 | ... N13: =SUMIFS(N18:N195,$B$18:$B$195,"Actual") -> 0 | O13: =SUM(C13:N13) -> 3636337.2
B14: Budget Deficit/ Savings | C14: =C12-C13 -> -12959.15 | D14: =D12-D13 -> 44579.12 | E14: =E12-E13 -> -33872.61 | F14: =F12-F13 -> -43194.71 | G14: =G12-G13 -> -59261.1 | H14: =H12-H13 -> -60124.39 | I14: =I12-I13 -> -93055.86 | J14: =J12-J13 -> -85567.48 | ... L14: =L12-L13 -> 71059.4 | O14: =SUM(C14:N14) -> -221504.76
B15: Year to Date Spend | C15: =SUM($C13:C13) -> 356907.3 | D15: =SUM($C13:D13) -> 701798.78 | E15: =SUM($C13:E13) -> 1105330.6 | F15: =SUM($C13:F13) -> 1486394.6 | G15: =SUM($C13:G13) -> 1895036.3 | H15: =SUM($C13:H13) -> 2279082.7 | I15: =SUM($C13:I13) -> 2672010.2 | J15: =SUM($C13:J13) -> 3072688.8 | ... L15: =SUM($C13:L13) -> 3629360.4 | O15: =O13 -> 3636337.2
B16: YTD Excess From Budget | C16: =SUM($C12:C12)-C15 -> -12959.15 | D16: =SUM($C12:D12)-D15 -> 31619.97 | E16: =SUM($C12:E12)-E15 -> -2252.64 | F16: =SUM($C12:F12)-F15 -> -45447.35 | G16: =SUM($C12:G12)-G15 -> -104708.45 | H16: =SUM($C12:H12)-H15 -> -164832.84 | I16: =SUM($C12:I12)-I15 -> -257888.7 | J16: =SUM($C12:J12)-J15 -> -343456.18 | ... L16: =SUM($C12:L12)-L15 -> -221504.76 | O16: =SUM(C16:N16) -> -1413994.3
A18: Individual Contractors 5024-510 | B18: Actual 2024 | C18: ='5024-510 Individual Contractors'!C3 -> 15182.75 | D18: ='5024-510 Individual Contractors'!D3 -> 14877.45 | E18: ='5024-510 Individual Contractors'!E3 -> 15152.75 | F18: ='5024-510 Individual Contractors'!F3 -> 15467 | G18: ='5024-510 Individual Contractors'!G3 -> 16872.5 | H18: ='5024-510 Individual Contractors'!H3 -> 15506.5 | I18: ='5024-510 Individual Contractors'!I3 -> 22385.5 | J18: ='5024-510 Individual Contractors'!J3 -> 23444 | ... O18: ='5024-510 Individual Contractors'!O3 -> 235250.45
B19: Estimated | C19: ='5024-510 Individual Contractors'!C4 -> 25473 | D19: ='5024-510 Individual Contractors'!D4 -> 25473 | E19: ='5024-510 Individual Contractors'!E4 -> 25473 | F19: ='5024-510 Individual Contractors'!F4 -> 25473 | G19: ='5024-510 Individual Contractors'!G4 -> 25473 | H19: ='5024-510 Individual Contractors'!H4 -> 25473 | I19: ='5024-510 Individual Contractors'!I4 -> 25473 | J19: ='5024-510 Individual Contractors'!J4 -> 25473 | ... O19: ='5024-510 Individual Contractors'!O4 -> 305676 | Q19: =O19-O18 -> 70425.55 | R19: $21K moved from General Contracted (5310-510) to this acct.
B20: Budget | C20: ='5024-510 Individual Contractors'!C5 -> 23573 | D20: ='5024-510 Individual Contractors'!D5 -> 23573 | E20: ='5024-510 Individual Contractors'!E5 -> 23573 | F20: ='5024-510 Individual Contractors'!F5 -> 23573 | G20: ='5024-510 Individual Contractors'!G5 -> 23573 | H20: ='5024-510 Individual Contractors'!H5 -> 23573 | I20: ='5024-510 Individual Contractors'!I5 -> 23573 | J20: ='5024-510 Individual Contractors'!J5 -> 23573 | ... O20: ='5024-510 Individual Contractors'!O5 -> 282876
B21: Actual | C21: ='5024-510 Individual Contractors'!C6 -> 25960.83 | D21: ='5024-510 Individual Contractors'!D6 -> 23257.83 | E21: ='5024-510 Individual Contractors'!E6 -> 26377 | F21: ='5024-510 Individual Contractors'!F6 -> 36213.01 | G21: ='5024-510 Individual Contractors'!G6 -> 66882.95 | H21: ='5024-510 Individual Contractors'!H6 -> 49229.95 | I21: ='5024-510 Individual Contractors'!I6 -> 37253.5 | J21: ='5024-510 Individual Contractors'!J6 -> 19065 | ... O21: ='5024-510 Individual Contractors'!O6 -> 315566.74 | Q21: =Q19+Q96 -> 49252.2 | R21: Actual Change
A22: Any work done by individual Contractors, regardless of the activity done. | B22: Budget Deficit/ Savings | C22: ='5024-510 Individual Contractors'!C7 -> -2387.83 | D22: ='5024-510 Individual Contractors'!D7 -> 315.17 | E22: ='5024-510 Individual Contractors'!E7 -> -2804 | F22: ='5024-510 Individual Contractors'!F7 -> -12640.01 | G22: ='5024-510 Individual Contractors'!G7 -> -43309.95 | H22: ='5024-510 Individual Contractors'!H7 -> -25656.95 | I22: ='5024-510 Individual Contractors'!I7 -> -13680.5 | J22: ='5024-510 Individual Contractors'!J7 -> 4508 | ... O22: ='5024-510 Individual Contractors'!O7 -> -32690.74 | R22: Primarily--web design, Japan & Korea support and Optimizely Testing
B23: Year to Date Spend | C23: ='5024-510 Individual Contractors'!C8 -> 25960.83 | D23: ='5024-510 Individual Contractors'!D8 -> 49218.66 | E23: ='5024-510 Individual Contractors'!E8 -> 75595.66 | F23: ='5024-510 Individual Contractors'!F8 -> 111808.67 | G23: ='5024-510 Individual Contractors'!G8 -> 178691.62 | H23: ='5024-510 Individual Contractors'!H8 -> 227921.57 | I23: ='5024-510 Individual Contractors'!I8 -> 265175.07 | J23: ='5024-510 Individual Contractors'!J8 -> 284240.07 | ... O23: ='5024-510 Individual Contractors'!O8 -> 315566.74
B24: YTD Excess From Budget | C24: ='5024-510 Individual Contractors'!C9 -> -2387.83 | D24: ='5024-510 Individual Contractors'!D9 -> -2072.66 | E24: ='5024-510 Individual Contractors'!E9 -> -4876.66 | F24: ='5024-510 Individual Contractors'!F9 -> -17516.67 | G24: ='5024-510 Individual Contractors'!G9 -> -60826.62 | H24: ='5024-510 Individual Contractors'!H9 -> -86483.57 | I24: ='5024-510 Individual Contractors'!I9 -> -100164.07 | J24: ='5024-510 Individual Contractors'!J9 -> -95656.07 | ... O24: ='5024-510 Individual Contractors'!O9 -> 0
A27: Performance based 5100-510 | B27: Actual 2024 | C27: ='5100-510 Performance based'!C3 -> 143539.3 | D27: ='5100-510 Performance based'!D3 -> 147248.13 | E27: ='5100-510 Performance based'!E3 -> 185140.97 | F27: ='5100-510 Performance based'!F3 -> 169233.26 | G27: ='5100-510 Performance based'!G3 -> 176262.06 | H27: ='5100-510 Performance based'!H3 -> 149970.94 | I27: ='5100-510 Performance based'!I3 -> 177140.26 | J27: ='5100-510 Performance based'!J3 -> 155860.75 | ... O27: ='5100-510 Performance based'!O3 -> 1976450.7
B28: Estimated | C28: ='5100-510 Performance based'!C4 -> 146953 | D28: ='5100-510 Performance based'!D4 -> 180607.9 | E28: ='5100-510 Performance based'!E4 -> 187009.76 | F28: ='5100-510 Performance based'!F4 -> 174751.99 | G28: ='5100-510 Performance based'!G4 -> 176957.38 | H28: ='5100-510 Performance based'!H4 -> 173636.33 | I28: ='5100-510 Performance based'!I4 -> 175447.32 | J28: ='5100-510 Performance based'!J4 -> 166596.13 | ... O28: ='5100-510 Performance based'!O4 -> 2042410.7 | Q28: =O28-O27 -> 65960.05
B29: Budget | C29: ='5100-510 Performance based'!C5 -> 154148.08 | D29: ='5100-510 Performance based'!D5 -> 189450.78 | E29: ='5100-510 Performance based'!E5 -> 196166.08 | F29: ='5100-510 Performance based'!F5 -> 183308.15 | G29: ='5100-510 Performance based'!G5 -> 185621.52 | H29: ='5100-510 Performance based'!H5 -> 182137.87 | I29: ='5100-510 Performance based'!I5 -> 184037.53 | J29: ='5100-510 Performance based'!J5 -> 174752.97 | ... O29: ='5100-510 Performance based'!O5 -> 2142410.7
B30: Actual | C30: ='5100-510 Performance based'!C6 -> 167533.56 | D30: ='5100-510 Performance based'!D6 -> 177155.24 | E30: ='5100-510 Performance based'!E6 -> 194641.2 | F30: ='5100-510 Performance based'!F6 -> 189109.5 | G30: ='5100-510 Performance based'!G6 -> 186083.66 | H30: ='5100-510 Performance based'!H6 -> 186467.29 | I30: ='5100-510 Performance based'!I6 -> 218352.1 | J30: ='5100-510 Performance based'!J6 -> 206940.24 | ... O30: ='5100-510 Performance based'!O6 -> 1828114.5
A31: Ad Expenses that can be tracked by their association to Rev | B31: Budget Deficit/ Savings | C31: ='5100-510 Performance based'!C7 -> -13385.48 | D31: ='5100-510 Performance based'!D7 -> 12295.54 | E31: ='5100-510 Performance based'!E7 -> 1524.88 | F31: ='5100-510 Performance based'!F7 -> -5801.35 | G31: ='5100-510 Performance based'!G7 -> -462.14 | H31: ='5100-510 Performance based'!H7 -> -4329.42 | I31: ='5100-510 Performance based'!I7 -> -34314.57 | J31: ='5100-510 Performance based'!J7 -> -32187.27 | ... O31: ='5100-510 Performance based'!O7 -> 314296.21
B32: Year to Date Spend | C32: ='5100-510 Performance based'!C8 -> 167533.56 | D32: ='5100-510 Performance based'!D8 -> 344688.8 | E32: ='5100-510 Performance based'!E8 -> 539330 | F32: ='5100-510 Performance based'!F8 -> 728439.5 | G32: ='5100-510 Performance based'!G8 -> 914523.16 | H32: ='5100-510 Performance based'!H8 -> 1100990.4 | I32: ='5100-510 Performance based'!I8 -> 1319342.6 | J32: ='5100-510 Performance based'!J8 -> 1526282.8 | ... O32: ='5100-510 Performance based'!O8 -> 1828114.5
B33: YTD Excess From Budget | C33: ='5100-510 Performance based'!C9 -> -13385.48 | D33: ='5100-510 Performance based'!D9 -> -1089.94 | E33: ='5100-510 Performance based'!E9 -> 434.94 | F33: ='5100-510 Performance based'!F9 -> -5366.41 | G33: ='5100-510 Performance based'!G9 -> -5828.55 | H33: ='5100-510 Performance based'!H9 -> -10157.97 | I33: ='5100-510 Performance based'!I9 -> -44472.54 | J33: ='5100-510 Performance based'!J9 -> -76659.81 | ... O33: ='5100-510 Performance based'!O9 -> 0
A36: Non performance based 5101-510 | B36: Actual 2024 | C36: ='5101-510 Non performance based'!C3 -> 54961.34 | D36: ='5101-510 Non performance based'!D3 -> 52303.61 | E36: ='5101-510 Non performance based'!E3 -> 53970.61 | F36: ='5101-510 Non performance based'!F3 -> 62526.2 | G36: ='5101-510 Non performance based'!G3 -> 50448.93 | H36: ='5101-510 Non performance based'!H3 -> 33734.71 | I36: ='5101-510 Non performance based'!I3 -> 36157.39 | J36: ='5101-510 Non performance based'!J3 -> 43318.85 | ... O36: ='5101-510 Non performance based'!O3 -> 579457.29
B37: Estimated | C37: ='5101-510 Non performance based'!C4 -> 73939 | D37: ='5101-510 Non performance based'!D4 -> 58654 | E37: ='5101-510 Non performance based'!E4 -> 50860 | F37: ='5101-510 Non performance based'!F4 -> 64316 | G37: ='5101-510 Non performance based'!G4 -> 47360 | H37: ='5101-510 Non performance based'!H4 -> 42133 | I37: ='5101-510 Non performance based'!I4 -> 29860 | J37: ='5101-510 Non performance based'!J4 -> 43399 | ... O37: ='5101-510 Non performance based'!O4 -> 605565 | Q37: =O37-O36 -> 26107.71 | R37: Adding Japan Marketing
B38: Budget | C38: ='5101-510 Non performance based'!C5 -> 75939 | D38: ='5101-510 Non performance based'!D5 -> 58654 | E38: ='5101-510 Non performance based'!E5 -> 50860 | F38: ='5101-510 Non performance based'!F5 -> 66316 | G38: ='5101-510 Non performance based'!G5 -> 47360 | H38: ='5101-510 Non performance based'!H5 -> 42133 | I38: ='5101-510 Non performance based'!I5 -> 31860 | J38: ='5101-510 Non performance based'!J5 -> 43399 | ... O38: ='5101-510 Non performance based'!O5 -> 613565
B39: Actual | C39: ='5101-510 Non performance based'!C6 -> 48578.52 | D39: ='5101-510 Non performance based'!D6 -> 47324.93 | E39: ='5101-510 Non performance based'!E6 -> 43482.71 | F39: ='5101-510 Non performance based'!F6 -> 73020.92 | G39: ='5101-510 Non performance based'!G6 -> 35157.55 | H39: ='5101-510 Non performance based'!H6 -> 57157.04 | I39: ='5101-510 Non performance based'!I6 -> 37818.82 | J39: ='5101-510 Non performance based'!J6 -> 50222.33 | ... O39: ='5101-510 Non performance based'!O6 -> 491972.19
A40: Other Ad Expenses | B40: Budget Deficit/ Savings | C40: ='5101-510 Non performance based'!C7 -> 27360.48 | D40: ='5101-510 Non performance based'!D7 -> 11329.07 | E40: ='5101-510 Non performance based'!E7 -> 7377.29 | F40: ='5101-510 Non performance based'!F7 -> -6704.92 | G40: ='5101-510 Non performance based'!G7 -> 12202.45 | H40: ='5101-510 Non performance based'!H7 -> -15024.04 | I40: ='5101-510 Non performance based'!I7 -> -5958.82 | J40: ='5101-510 Non performance based'!J7 -> -6823.33 | ... O40: ='5101-510 Non performance based'!O7 -> 121592.81
B41: Year to Date Spend | C41: ='5101-510 Non performance based'!C8 -> 48578.52 | D41: ='5101-510 Non performance based'!D8 -> 95903.45 | E41: ='5101-510 Non performance based'!E8 -> 139386.16 | F41: ='5101-510 Non performance based'!F8 -> 212407.08 | G41: ='5101-510 Non performance based'!G8 -> 247564.63 | H41: ='5101-510 Non performance based'!H8 -> 304721.67 | I41: ='5101-510 Non performance based'!I8 -> 342540.49 | J41: ='5101-510 Non performance based'!J8 -> 392762.82 | ... O41: ='5101-510 Non performance based'!O8 -> 491972.19
B42: YTD Excess From Budget | C42: ='5101-510 Non performance based'!C9 -> 27360.48 | D42: ='5101-510 Non performance based'!D9 -> 38689.55 | E42: ='5101-510 Non performance based'!E9 -> 46066.84 | F42: ='5101-510 Non performance based'!F9 -> 39361.92 | G42: ='5101-510 Non performance based'!G9 -> 51564.37 | H42: ='5101-510 Non performance based'!H9 -> 36540.33 | I42: ='5101-510 Non performance based'!I9 -> 30581.51 | J42: ='5101-510 Non performance based'!J9 -> 23758.18 | ... O42: ='5101-510 Non performance based'!O9 -> 0
A45: Advertising Agency Fee 5102-510 | B45: Actual 2024 | C45: ='5102-510 Advertising Agency Fee'!C3 -> 30663.22 | D45: ='5102-510 Advertising Agency Fee'!D3 -> 34061.61 | E45: ='5102-510 Advertising Agency Fee'!E3 -> 48123.82 | F45: ='5102-510 Advertising Agency Fee'!F3 -> 35442.91 | G45: ='5102-510 Advertising Agency Fee'!G3 -> 57806.73 | H45: ='5102-510 Advertising Agency Fee'!H3 -> 42091.03 | I45: ='5102-510 Advertising Agency Fee'!I3 -> 39212.95 | J45: ='5102-510 Advertising Agency Fee'!J3 -> 38385.77 | ... O45: ='5102-510 Advertising Agency Fee'!O3 -> 489117.25
B46: Estimated | C46: ='5102-510 Advertising Agency Fee'!C4 -> 67567 | D46: ='5102-510 Advertising Agency Fee'!D4 -> 97522 | E46: ='5102-510 Advertising Agency Fee'!E4 -> 58826 | F46: ='5102-510 Advertising Agency Fee'!F4 -> 51522 | G46: ='5102-510 Advertising Agency Fee'!G4 -> 65022 | H46: ='5102-510 Advertising Agency Fee'!H4 -> 49022 | I46: ='5102-510 Advertising Agency Fee'!I4 -> 47085 | J46: ='5102-510 Advertising Agency Fee'!J4 -> 47022 | ... O46: ='5102-510 Advertising Agency Fee'!O4 -> 697176 | Q46: =O46-O45 -> 208058.75 | R46: Annual Fee increases (mostly World Media)
B47: Budget | C47: ='5102-510 Advertising Agency Fee'!C5 -> 67567 | D47: ='5102-510 Advertising Agency Fee'!D5 -> 97522 | E47: ='5102-510 Advertising Agency Fee'!E5 -> 58826 | F47: ='5102-510 Advertising Agency Fee'!F5 -> 51522 | G47: ='5102-510 Advertising Agency Fee'!G5 -> 65022 | H47: ='5102-510 Advertising Agency Fee'!H5 -> 49022 | I47: ='5102-510 Advertising Agency Fee'!I5 -> 47085 | J47: ='5102-510 Advertising Agency Fee'!J5 -> 47022 | ... O47: ='5102-510 Advertising Agency Fee'!O5 -> 697176
B48: Actual | C48: ='5102-510 Advertising Agency Fee'!C6 -> 51418.5 | D48: ='5102-510 Advertising Agency Fee'!D6 -> 59616.7 | E48: ='5102-510 Advertising Agency Fee'!E6 -> 47803.15 | F48: ='5102-510 Advertising Agency Fee'!F6 -> 54958.58 | G48: ='5102-510 Advertising Agency Fee'!G6 -> 55320.83 | H48: ='5102-510 Advertising Agency Fee'!H6 -> 58388.51 | I48: ='5102-510 Advertising Agency Fee'!I6 -> 63125.88 | J48: ='5102-510 Advertising Agency Fee'!J6 -> 59393.07 | ... O48: ='5102-510 Advertising Agency Fee'!O6 -> 528819.66
A49: Retainer Fees to Ad Agencies | B49: Budget Deficit/ Savings | C49: ='5102-510 Advertising Agency Fee'!C7 -> 16148.5 | D49: ='5102-510 Advertising Agency Fee'!D7 -> 37905.3 | E49: ='5102-510 Advertising Agency Fee'!E7 -> 11022.85 | F49: ='5102-510 Advertising Agency Fee'!F7 -> -3436.58 | G49: ='5102-510 Advertising Agency Fee'!G7 -> 9701.17 | H49: ='5102-510 Advertising Agency Fee'!H7 -> -9366.51 | I49: ='5102-510 Advertising Agency Fee'!I7 -> -16040.88 | J49: ='5102-510 Advertising Agency Fee'!J7 -> -12371.07 | ... O49: ='5102-510 Advertising Agency Fee'!O7 -> 168356.34
B50: Year to Date Spend | C50: ='5102-510 Advertising Agency Fee'!C8 -> 51418.5 | D50: ='5102-510 Advertising Agency Fee'!D8 -> 111035.2 | E50: ='5102-510 Advertising Agency Fee'!E8 -> 158838.35 | F50: ='5102-510 Advertising Agency Fee'!F8 -> 213796.93 | G50: ='5102-510 Advertising Agency Fee'!G8 -> 269117.76 | H50: ='5102-510 Advertising Agency Fee'!H8 -> 327506.27 | I50: ='5102-510 Advertising Agency Fee'!I8 -> 390632.15 | J50: ='5102-510 Advertising Agency Fee'!J8 -> 450025.22 | ... O50: ='5102-510 Advertising Agency Fee'!O8 -> 528819.66
B51: YTD Excess From Budget | C51: ='5102-510 Advertising Agency Fee'!C9 -> 16148.5 | D51: ='5102-510 Advertising Agency Fee'!D9 -> 54053.8 | E51: ='5102-510 Advertising Agency Fee'!E9 -> 65076.65 | F51: ='5102-510 Advertising Agency Fee'!F9 -> 61640.07 | G51: ='5102-510 Advertising Agency Fee'!G9 -> 71341.24 | H51: ='5102-510 Advertising Agency Fee'!H9 -> 61974.73 | I51: ='5102-510 Advertising Agency Fee'!I9 -> 45933.85 | J51: ='5102-510 Advertising Agency Fee'!J9 -> 33562.78 | ... O51: ='5102-510 Advertising Agency Fee'!O9 -> 0
A53: Public Relations 5104-510 | B53: Actual 2024 | C53: ='5104-510 Public Relations'!C3 -> 8376.96 | D53: ='5104-510 Public Relations'!D3 -> 8376.96 | E53: ='5104-510 Public Relations'!E3 -> 8376.96 | F53: ='5104-510 Public Relations'!F3 -> 17177.88 | G53: ='5104-510 Public Relations'!G3 -> 23701.57 | H53: ='5104-510 Public Relations'!H3 -> 11057.63 | I53: ='5104-510 Public Relations'!I3 -> 10209.42 | J53: ='5104-510 Public Relations'!J3 -> 10209.42 | ... O53: ='5104-510 Public Relations'!O3 -> 157545.37
B54: Estimated | C54: ='5104-510 Public Relations'!C4 -> 10209.46 | D54: ='5104-510 Public Relations'!D4 -> 10209.46 | E54: ='5104-510 Public Relations'!E4 -> 21832.46 | F54: ='5104-510 Public Relations'!F4 -> 10209.46 | G54: ='5104-510 Public Relations'!G4 -> 16832.46 | H54: ='5104-510 Public Relations'!H4 -> 10209.46 | I54: ='5104-510 Public Relations'!I4 -> 10209.46 | J54: ='5104-510 Public Relations'!J4 -> 10209.46 | ... O54: ='5104-510 Public Relations'!O4 -> 152382.52 | Q54: =O54-O53 -> -5162.85
B55: Budget | C55: ='5104-510 Public Relations'!C5 -> 10209.46 | D55: ='5104-510 Public Relations'!D5 -> 10209.46 | E55: ='5104-510 Public Relations'!E5 -> 21832.46 | F55: ='5104-510 Public Relations'!F5 -> 10209.46 | G55: ='5104-510 Public Relations'!G5 -> 16832.46 | H55: ='5104-510 Public Relations'!H5 -> 10209.46 | I55: ='5104-510 Public Relations'!I5 -> 10209.46 | J55: ='5104-510 Public Relations'!J5 -> 10209.46 | ... O55: ='5104-510 Public Relations'!O5 -> 152382.52
B56: Actual | C56: ='5104-510 Public Relations'!C6 -> 10467.72 | D56: ='5104-510 Public Relations'!D6 -> 12294.22 | E56: ='5104-510 Public Relations'!E6 -> 10209.42 | F56: ='5104-510 Public Relations'!F6 -> 9126.96 | G56: ='5104-510 Public Relations'!G6 -> 21267.29 | H56: ='5104-510 Public Relations'!H6 -> 13282.01 | I56: ='5104-510 Public Relations'!I6 -> 8376.96 | J56: ='5104-510 Public Relations'!J6 -> 8376.96 | ... O56: ='5104-510 Public Relations'!O6 -> 103610.96
A57: Any PR Expenses (Giveaways, PR agencies) | B57: Budget Deficit/ Savings | C57: ='5104-510 Public Relations'!C7 -> -258.26 | D57: ='5104-510 Public Relations'!D7 -> -2084.76 | E57: ='5104-510 Public Relations'!E7 -> 11623.04 | F57: ='5104-510 Public Relations'!F7 -> 1082.5 | G57: ='5104-510 Public Relations'!G7 -> -4434.83 | H57: ='5104-510 Public Relations'!H7 -> -3072.55 | I57: ='5104-510 Public Relations'!I7 -> 1832.5 | J57: ='5104-510 Public Relations'!J7 -> 1832.5 | ... O57: ='5104-510 Public Relations'!O7 -> 48771.56
B58: Year to Date Spend | C58: ='5104-510 Public Relations'!C8 -> 10467.72 | D58: ='5104-510 Public Relations'!D8 -> 22761.94 | E58: ='5104-510 Public Relations'!E8 -> 32971.36 | F58: ='5104-510 Public Relations'!F8 -> 42098.32 | G58: ='5104-510 Public Relations'!G8 -> 63365.61 | H58: ='5104-510 Public Relations'!H8 -> 76647.62 | I58: ='5104-510 Public Relations'!I8 -> 85024.58 | J58: ='5104-510 Public Relations'!J8 -> 93401.54 | ... O58: ='5104-510 Public Relations'!O8 -> 103610.96
B59: YTD Excess From Budget | C59: ='5104-510 Public Relations'!C9 -> -258.26 | D59: ='5104-510 Public Relations'!D9 -> -2343.02 | E59: ='5104-510 Public Relations'!E9 -> 9280.02 | F59: ='5104-510 Public Relations'!F9 -> 10362.52 | G59: ='5104-510 Public Relations'!G9 -> 5927.69 | H59: ='5104-510 Public Relations'!H9 -> 2855.14 | I59: ='5104-510 Public Relations'!I9 -> 4687.64 | J59: ='5104-510 Public Relations'!J9 -> 6520.14 | ... O59: ='5104-510 Public Relations'!O9 -> 0
A61: Promotional Events 5105-510 | B61: Actual 2024 | C61: ='5105-510 Promotional Events'!C3 -> 0 | D61: ='5105-510 Promotional Events'!D3 -> 0 | E61: ='5105-510 Promotional Events'!E3 -> 0 | F61: ='5105-510 Promotional Events'!F3 -> 0 | G61: ='5105-510 Promotional Events'!G3 -> 0 | H61: ='5105-510 Promotional Events'!H3 -> 0 | I61: ='5105-510 Promotional Events'!I3 -> 0 | J61: ='5105-510 Promotional Events'!J3 -> 0 | ... O61: ='5105-510 Promotional Events'!O3 -> 0
B62: Estimated | C62: ='5105-510 Promotional Events'!C4 -> 0 | D62: ='5105-510 Promotional Events'!D4 -> 0 | E62: ='5105-510 Promotional Events'!E4 -> 0 | F62: ='5105-510 Promotional Events'!F4 -> 0 | G62: ='5105-510 Promotional Events'!G4 -> 0 | H62: ='5105-510 Promotional Events'!H4 -> 0 | I62: ='5105-510 Promotional Events'!I4 -> 0 | J62: ='5105-510 Promotional Events'!J4 -> 0 | ... O62: ='5105-510 Promotional Events'!O4 -> 0
B63: Budget | C63: ='5105-510 Promotional Events'!C5 -> 0 | D63: ='5105-510 Promotional Events'!D5 -> 0 | E63: ='5105-510 Promotional Events'!E5 -> 0 | F63: ='5105-510 Promotional Events'!F5 -> 0 | G63: ='5105-510 Promotional Events'!G5 -> 0 | H63: ='5105-510 Promotional Events'!H5 -> 0 | I63: ='5105-510 Promotional Events'!I5 -> 0 | J63: ='5105-510 Promotional Events'!J5 -> 0 | ... O63: ='5105-510 Promotional Events'!O5 -> 0
B64: Actual | C64: ='5105-510 Promotional Events'!C6 -> 2008.82 | D64: ='5105-510 Promotional Events'!D6 -> 2770.4 | E64: ='5105-510 Promotional Events'!E6 -> 55.81 | F64: ='5105-510 Promotional Events'!F6 -> 2373.42 | G64: ='5105-510 Promotional Events'!G6 -> 1969.39 | H64: ='5105-510 Promotional Events'!H6 -> 3896.16 | I64: ='5105-510 Promotional Events'!I6 -> 96.71 | J64: ='5105-510 Promotional Events'!J6 -> 7626.13 | ... O64: ='5105-510 Promotional Events'!O6 -> 27328.19
A65: All costs for Events (WFK, WAS, etc). Food for departments, flyers and banners, etc. | B65: Budget Deficit/ Savings | C65: ='5105-510 Promotional Events'!C7 -> -2008.82 | D65: ='5105-510 Promotional Events'!D7 -> -2770.4 | E65: ='5105-510 Promotional Events'!E7 -> -55.81 | F65: ='5105-510 Promotional Events'!F7 -> -2373.42 | G65: ='5105-510 Promotional Events'!G7 -> -1969.39 | H65: ='5105-510 Promotional Events'!H7 -> -3896.16 | I65: ='5105-510 Promotional Events'!I7 -> -96.71 | J65: ='5105-510 Promotional Events'!J7 -> -7626.13 | ... O65: ='5105-510 Promotional Events'!O7 -> -27328.19
B66: Year to Date Spend | C66: ='5105-510 Promotional Events'!C8 -> 2008.82 | D66: ='5105-510 Promotional Events'!D8 -> 4779.22 | E66: ='5105-510 Promotional Events'!E8 -> 4835.03 | F66: ='5105-510 Promotional Events'!F8 -> 7208.45 | G66: ='5105-510 Promotional Events'!G8 -> 9177.84 | H66: ='5105-510 Promotional Events'!H8 -> 13074 | I66: ='5105-510 Promotional Events'!I8 -> 13170.71 | J66: ='5105-510 Promotional Events'!J8 -> 20796.84 | ... O66: ='5105-510 Promotional Events'!O8 -> 27328.19
B67: YTD Excess From Budget | C67: ='5105-510 Promotional Events'!C9 -> -2008.82 | D67: ='5105-510 Promotional Events'!D9 -> -4779.22 | E67: ='5105-510 Promotional Events'!E9 -> -4835.03 | F67: ='5105-510 Promotional Events'!F9 -> -7208.45 | G67: ='5105-510 Promotional Events'!G9 -> -9177.84 | H67: ='5105-510 Promotional Events'!H9 -> -13074 | I67: ='5105-510 Promotional Events'!I9 -> -13170.71 | J67: ='5105-510 Promotional Events'!J9 -> -20796.84 | ... O67: ='5105-510 Promotional Events'!O9 -> 0
A70: Operating Materials 5200-510 | B70: Actual 2024 | C70: ='5200-510 Operating Materials'!C3 -> 11179.59 | D70: ='5200-510 Operating Materials'!D3 -> 1172.82 | E70: ='5200-510 Operating Materials'!E3 -> 736.31 | F70: ='5200-510 Operating Materials'!F3 -> 664.21 | G70: ='5200-510 Operating Materials'!G3 -> 16420.22 | H70: ='5200-510 Operating Materials'!H3 -> 15007.29 | I70: ='5200-510 Operating Materials'!I3 -> 1207.31 | J70: ='5200-510 Operating Materials'!J3 -> 12974.18 | ... O70: ='5200-510 Operating Materials'!O3 -> 94546.77
B71: Estimated | C71: ='5200-510 Operating Materials'!C4 -> 10884.94 | D71: ='5200-510 Operating Materials'!D4 -> 2434.69 | E71: ='5200-510 Operating Materials'!E4 -> 16775 | F71: ='5200-510 Operating Materials'!F4 -> 1314 | G71: ='5200-510 Operating Materials'!G4 -> 3345 | H71: ='5200-510 Operating Materials'!H4 -> 15220 | I71: ='5200-510 Operating Materials'!I4 -> 1475 | J71: ='5200-510 Operating Materials'!J4 -> 14505 | ... O71: ='5200-510 Operating Materials'!O4 -> 100837.63 | Q71: =O71-O70 -> 6290.86
B72: Budget | C72: ='5200-510 Operating Materials'!C5 -> 10884.94 | D72: ='5200-510 Operating Materials'!D5 -> 2434.69 | E72: ='5200-510 Operating Materials'!E5 -> 16775 | F72: ='5200-510 Operating Materials'!F5 -> 1314 | G72: ='5200-510 Operating Materials'!G5 -> 3345 | H72: ='5200-510 Operating Materials'!H5 -> 15220 | I72: ='5200-510 Operating Materials'!I5 -> 1475 | J72: ='5200-510 Operating Materials'!J5 -> 14505 | ... O72: ='5200-510 Operating Materials'!O5 -> 100837.63
B73: Actual | C73: ='5200-510 Operating Materials'!C6 -> 44094.99 | D73: ='5200-510 Operating Materials'!D6 -> 13689.27 | E73: ='5200-510 Operating Materials'!E6 -> 18956.76 | F73: ='5200-510 Operating Materials'!F6 -> 571.13 | G73: ='5200-510 Operating Materials'!G6 -> 18214.76 | H73: ='5200-510 Operating Materials'!H6 -> 4108.58 | I73: ='5200-510 Operating Materials'!I6 -> 19645.82 | J73: ='5200-510 Operating Materials'!J6 -> 30129.71 | ... O73: ='5200-510 Operating Materials'!O6 -> 159620.39
A74: Materials (like print outs) for normal operations, and office supplies | B74: Budget Deficit/ Savings | C74: ='5200-510 Operating Materials'!C7 -> -33210.05 | D74: ='5200-510 Operating Materials'!D7 -> -11254.58 | E74: ='5200-510 Operating Materials'!E7 -> -2181.76 | F74: ='5200-510 Operating Materials'!F7 -> 742.87 | G74: ='5200-510 Operating Materials'!G7 -> -14869.76 | H74: ='5200-510 Operating Materials'!H7 -> 11111.42 | I74: ='5200-510 Operating Materials'!I7 -> -18170.82 | J74: ='5200-510 Operating Materials'!J7 -> -15624.71 | ... O74: ='5200-510 Operating Materials'!O7 -> -58782.76
B75: Year to Date Spend | C75: ='5200-510 Operating Materials'!C8 -> 44094.99 | D75: ='5200-510 Operating Materials'!D8 -> 57784.26 | E75: ='5200-510 Operating Materials'!E8 -> 76741.02 | F75: ='5200-510 Operating Materials'!F8 -> 77312.15 | G75: ='5200-510 Operating Materials'!G8 -> 95526.91 | H75: ='5200-510 Operating Materials'!H8 -> 99635.49 | I75: ='5200-510 Operating Materials'!I8 -> 119281.31 | J75: ='5200-510 Operating Materials'!J8 -> 149411.02 | ... O75: ='5200-510 Operating Materials'!O8 -> 159620.39
B76: YTD Excess From Budget | C76: ='5200-510 Operating Materials'!C9 -> -33210.05 | D76: ='5200-510 Operating Materials'!D9 -> -44464.63 | E76: ='5200-510 Operating Materials'!E9 -> -46646.39 | F76: ='5200-510 Operating Materials'!F9 -> -45903.52 | G76: ='5200-510 Operating Materials'!G9 -> -60773.28 | H76: ='5200-510 Operating Materials'!H9 -> -49661.86 | I76: ='5200-510 Operating Materials'!I9 -> -67832.68 | J76: ='5200-510 Operating Materials'!J9 -> -83457.39 | ... O76: ='5200-510 Operating Materials'!O9 -> 0
A78: Uniform 5201-510 | B78: Actual 2024 | C78: ='5201-510 Uniform'!C3 -> 0 | D78: ='5201-510 Uniform'!D3 -> 360.23 | E78: ='5201-510 Uniform'!E3 -> 695.32 | F78: ='5201-510 Uniform'!F3 -> 0 | G78: ='5201-510 Uniform'!G3 -> 85.42 | H78: ='5201-510 Uniform'!H3 -> 0 | I78: ='5201-510 Uniform'!I3 -> 0 | J78: ='5201-510 Uniform'!J3 -> 0 | ... O78: ='5201-510 Uniform'!O3 -> 1140.97
B79: Estimated | C79: ='5201-510 Uniform'!C4 -> 3500 | D79: ='5201-510 Uniform'!D4 -> 0 | E79: ='5201-510 Uniform'!E4 -> 0 | F79: ='5201-510 Uniform'!F4 -> 0 | G79: ='5201-510 Uniform'!G4 -> 0 | H79: ='5201-510 Uniform'!H4 -> 0 | I79: ='5201-510 Uniform'!I4 -> 0 | J79: ='5201-510 Uniform'!J4 -> 0 | ... O79: ='5201-510 Uniform'!O4 -> 3500 | Q79: =O79-O78 -> 2359.03
B80: Budget | C80: ='5201-510 Uniform'!C5 -> 0 | D80: ='5201-510 Uniform'!D5 -> 0 | E80: ='5201-510 Uniform'!E5 -> 0 | F80: ='5201-510 Uniform'!F5 -> 0 | G80: ='5201-510 Uniform'!G5 -> 0 | H80: ='5201-510 Uniform'!H5 -> 0 | I80: ='5201-510 Uniform'!I5 -> 0 | J80: ='5201-510 Uniform'!J5 -> 0 | ... O80: ='5201-510 Uniform'!O5 -> 0
B81: Actual | C81: ='5201-510 Uniform'!C6 -> 0 | D81: ='5201-510 Uniform'!D6 -> 0 | E81: ='5201-510 Uniform'!E6 -> 0 | F81: ='5201-510 Uniform'!F6 -> 1593.8 | G81: ='5201-510 Uniform'!G6 -> 0 | H81: ='5201-510 Uniform'!H6 -> 0 | I81: ='5201-510 Uniform'!I6 -> 0 | J81: ='5201-510 Uniform'!J6 -> 93.76 | ... O81: ='5201-510 Uniform'!O6 -> 1687.56
A82: Uniforms | B82: Budget Deficit/ Savings | C82: ='5201-510 Uniform'!C7 -> 0 | D82: ='5201-510 Uniform'!D7 -> 0 | E82: ='5201-510 Uniform'!E7 -> 0 | F82: ='5201-510 Uniform'!F7 -> -1593.8 | G82: ='5201-510 Uniform'!G7 -> 0 | H82: ='5201-510 Uniform'!H7 -> 0 | I82: ='5201-510 Uniform'!I7 -> 0 | J82: ='5201-510 Uniform'!J7 -> -93.76 | ... O82: ='5201-510 Uniform'!O7 -> -1687.56
B83: Year to Date Spend | C83: ='5201-510 Uniform'!C8 -> 0 | D83: ='5201-510 Uniform'!D8 -> 0 | E83: ='5201-510 Uniform'!E8 -> 0 | F83: ='5201-510 Uniform'!F8 -> 1593.8 | G83: ='5201-510 Uniform'!G8 -> 1593.8 | H83: ='5201-510 Uniform'!H8 -> 1593.8 | I83: ='5201-510 Uniform'!I8 -> 1593.8 | J83: ='5201-510 Uniform'!J8 -> 1687.56 | ... O83: ='5201-510 Uniform'!O8 -> 1687.56
B84: YTD Excess From Budget | C84: ='5201-510 Uniform'!C9 -> 0 | D84: ='5201-510 Uniform'!D9 -> 0 | E84: ='5201-510 Uniform'!E9 -> 0 | F84: ='5201-510 Uniform'!F9 -> -1593.8 | G84: ='5201-510 Uniform'!G9 -> -1593.8 | H84: ='5201-510 Uniform'!H9 -> -1593.8 | I84: ='5201-510 Uniform'!I9 -> -1593.8 | J84: ='5201-510 Uniform'!J9 -> -1687.56 | ... O84: ='5201-510 Uniform'!O9 -> 0
A86: Furnishings 5203-510 | B86: Actual 2024 | C86: ='5203-510 Furnishings'!C3 -> 3692.5 | D86: ='5203-510 Furnishings'!D3 -> 0 | E86: ='5203-510 Furnishings'!E3 -> 0 | F86: ='5203-510 Furnishings'!F3 -> 0 | G86: ='5203-510 Furnishings'!G3 -> 0 | H86: ='5203-510 Furnishings'!H3 -> 0 | I86: ='5203-510 Furnishings'!I3 -> 0 | J86: ='5203-510 Furnishings'!J3 -> 0 | ... O86: ='5203-510 Furnishings'!O3 -> 0 | R86: Why is purchase not on 2024
B87: Estimated | C87: ='5203-510 Furnishings'!C4 -> 38895.53 | D87: ='5203-510 Furnishings'!D4 -> 0 | E87: ='5203-510 Furnishings'!E4 -> 0 | F87: ='5203-510 Furnishings'!F4 -> 236.17 | G87: ='5203-510 Furnishings'!G4 -> 0 | H87: ='5203-510 Furnishings'!H4 -> 0 | I87: ='5203-510 Furnishings'!I4 -> 0 | J87: ='5203-510 Furnishings'!J4 -> 0 | ... O87: ='5203-510 Furnishings'!O4 -> 39131.7 | Q87: =O87-O86 -> 39131.7 | R87: Second have of equipment purchase from 2024
B88: Budget | C88: ='5203-510 Furnishings'!C5 -> 0 | D88: ='5203-510 Furnishings'!D5 -> 0 | E88: ='5203-510 Furnishings'!E5 -> 0 | F88: ='5203-510 Furnishings'!F5 -> 0 | G88: ='5203-510 Furnishings'!G5 -> 0 | H88: ='5203-510 Furnishings'!H5 -> 0 | I88: ='5203-510 Furnishings'!I5 -> 0 | J88: ='5203-510 Furnishings'!J5 -> 0 | ... O88: ='5203-510 Furnishings'!O5 -> 0
B89: Actual | C89: ='5203-510 Furnishings'!C6 -> 0 | D89: ='5203-510 Furnishings'!D6 -> 0 | E89: ='5203-510 Furnishings'!E6 -> 40709.16 | F89: ='5203-510 Furnishings'!F6 -> 3858.19 | G89: ='5203-510 Furnishings'!G6 -> 243.55 | H89: ='5203-510 Furnishings'!H6 -> 0 | I89: ='5203-510 Furnishings'!I6 -> 54.69 | J89: ='5203-510 Furnishings'!J6 -> 28.26 | ... O89: ='5203-510 Furnishings'!O6 -> 44950.54
A90: Equipment Purchases! Cameras, other content creation stuff | B90: Budget Deficit/ Savings | C90: ='5203-510 Furnishings'!C7 -> 0 | D90: ='5203-510 Furnishings'!D7 -> 0 | E90: ='5203-510 Furnishings'!E7 -> -40709.16 | F90: ='5203-510 Furnishings'!F7 -> -3858.19 | G90: ='5203-510 Furnishings'!G7 -> -243.55 | H90: ='5203-510 Furnishings'!H7 -> 0 | I90: ='5203-510 Furnishings'!I7 -> -54.69 | J90: ='5203-510 Furnishings'!J7 -> -28.26 | ... O90: ='5203-510 Furnishings'!O7 -> -44950.54
B91: Year to Date Spend | C91: ='5203-510 Furnishings'!C8 -> 0 | D91: ='5203-510 Furnishings'!D8 -> 0 | E91: ='5203-510 Furnishings'!E8 -> 40709.16 | F91: ='5203-510 Furnishings'!F8 -> 44567.35 | G91: ='5203-510 Furnishings'!G8 -> 44810.9 | H91: ='5203-510 Furnishings'!H8 -> 44810.9 | I91: ='5203-510 Furnishings'!I8 -> 44865.59 | J91: ='5203-510 Furnishings'!J8 -> 44893.85 | ... O91: ='5203-510 Furnishings'!O8 -> 44950.54
B92: YTD Excess From Budget | C92: ='5203-510 Furnishings'!C9 -> 0 | D92: ='5203-510 Furnishings'!D9 -> 0 | E92: ='5203-510 Furnishings'!E9 -> -40709.16 | F92: ='5203-510 Furnishings'!F9 -> -44567.35 | G92: ='5203-510 Furnishings'!G9 -> -44810.9 | H92: ='5203-510 Furnishings'!H9 -> -44810.9 | I92: ='5203-510 Furnishings'!I9 -> -44865.59 | J92: ='5203-510 Furnishings'!J9 -> -44893.85 | ... O92: ='5203-510 Furnishings'!O9 -> 0
A95: General Contracted 5312-510 | B95: Actual 2024 | C95: ='5312-510 General Contracted '!C3 -> 0 | D95: ='5312-510 General Contracted '!D3 -> 0 | E95: ='5312-510 General Contracted '!E3 -> 0 | F95: ='5312-510 General Contracted '!F3 -> 0 | G95: ='5312-510 General Contracted '!G3 -> 0 | H95: ='5312-510 General Contracted '!H3 -> 0 | I95: ='5312-510 General Contracted '!I3 -> 0 | J95: ='5312-510 General Contracted '!J3 -> 0 | ... O95: ='5312-510 General Contracted '!O3 -> 21173.35
B96: Estimated | C96: ='5312-510 General Contracted '!C4 -> 0 | D96: ='5312-510 General Contracted '!D4 -> 0 | E96: ='5312-510 General Contracted '!E4 -> 0 | F96: ='5312-510 General Contracted '!F4 -> 0 | G96: ='5312-510 General Contracted '!G4 -> 0 | H96: ='5312-510 General Contracted '!H4 -> 0 | I96: ='5312-510 General Contracted '!I4 -> 0 | J96: ='5312-510 General Contracted '!J4 -> 0 | ... O96: ='5312-510 General Contracted '!O4 -> 0 | Q96: =O96-O95 -> -21173.35
B97: Budget | C97: ='5312-510 General Contracted '!C5 -> 0 | D97: ='5312-510 General Contracted '!D5 -> 0 | E97: ='5312-510 General Contracted '!E5 -> 0 | F97: ='5312-510 General Contracted '!F5 -> 0 | G97: ='5312-510 General Contracted '!G5 -> 0 | H97: ='5312-510 General Contracted '!H5 -> 0 | I97: ='5312-510 General Contracted '!I5 -> 0 | J97: ='5312-510 General Contracted '!J5 -> 0 | ... O97: ='5312-510 General Contracted '!O5 -> 0
B98: Actual | C98: ='5312-510 General Contracted '!C6 -> 0 | D98: ='5312-510 General Contracted '!D6 -> 0 | E98: ='5312-510 General Contracted '!E6 -> 0 | F98: ='5312-510 General Contracted '!F6 -> 0 | G98: ='5312-510 General Contracted '!G6 -> 0 | H98: ='5312-510 General Contracted '!H6 -> 0 | I98: ='5312-510 General Contracted '!I6 -> 0 | J98: ='5312-510 General Contracted '!J6 -> 0 | ... O98: ='5312-510 General Contracted '!O6 -> 0
B99: Budget Deficit/ Savings | C99: ='5312-510 General Contracted '!C7 -> 0 | D99: ='5312-510 General Contracted '!D7 -> 0 | E99: ='5312-510 General Contracted '!E7 -> 0 | F99: ='5312-510 General Contracted '!F7 -> 0 | G99: ='5312-510 General Contracted '!G7 -> 0 | H99: ='5312-510 General Contracted '!H7 -> 0 | I99: ='5312-510 General Contracted '!I7 -> 0 | J99: ='5312-510 General Contracted '!J7 -> 0 | ... O99: ='5312-510 General Contracted '!O7 -> 0
A100: Bands and Sounds Systems (Usually for Ohana Club events) | B100: Year to Date Spend | C100: ='5312-510 General Contracted '!C8 -> 0 | D100: ='5312-510 General Contracted '!D8 -> 0 | E100: ='5312-510 General Contracted '!E8 -> 0 | F100: ='5312-510 General Contracted '!F8 -> 0 | G100: ='5312-510 General Contracted '!G8 -> 0 | H100: ='5312-510 General Contracted '!H8 -> 0 | I100: ='5312-510 General Contracted '!I8 -> 0 | J100: ='5312-510 General Contracted '!J8 -> 0 | ... O100: ='5312-510 General Contracted '!O8 -> 0
B101: YTD Excess From Budget | C101: ='5312-510 General Contracted '!C9 -> 0 | D101: ='5312-510 General Contracted '!D9 -> 0 | E101: ='5312-510 General Contracted '!E9 -> 0 | F101: ='5312-510 General Contracted '!F9 -> 0 | G101: ='5312-510 General Contracted '!G9 -> 0 | H101: ='5312-510 General Contracted '!H9 -> 0 | I101: ='5312-510 General Contracted '!I9 -> 0 | J101: ='5312-510 General Contracted '!J9 -> 0 | ... O101: ='5312-510 General Contracted '!O9 -> 0
A103: 5313-510 Telecommunications | B103: Actual 2024 | C103: ='5313-510 Telecommunications'!C3 -> 216.67 | D103: ='5313-510 Telecommunications'!D3 -> 216.67 | E103: ='5313-510 Telecommunications'!E3 -> 216.67 | F103: ='5313-510 Telecommunications'!F3 -> 216.67 | G103: ='5313-510 Telecommunications'!G3 -> 216.67 | H103: ='5313-510 Telecommunications'!H3 -> 216.67 | I103: ='5313-510 Telecommunications'!I3 -> 216.67 | J103: ='5313-510 Telecommunications'!J3 -> 216.67 | ... O103: ='5313-510 Telecommunications'!O3 -> 2600.04
B104: Estimated | C104: ='5313-510 Telecommunications'!C4 -> 216.67 | D104: ='5313-510 Telecommunications'!D4 -> 216.67 | E104: ='5313-510 Telecommunications'!E4 -> 216.67 | F104: ='5313-510 Telecommunications'!F4 -> 216.67 | G104: ='5313-510 Telecommunications'!G4 -> 216.67 | H104: ='5313-510 Telecommunications'!H4 -> 216.67 | I104: ='5313-510 Telecommunications'!I4 -> 216.67 | J104: ='5313-510 Telecommunications'!J4 -> 216.67 | ... O104: ='5313-510 Telecommunications'!O4 -> 2600.04 | Q104: =O104-O103 -> 0 | R104: Phones
B105: Budget | C105: ='5313-510 Telecommunications'!C5 -> 216.67 | D105: ='5313-510 Telecommunications'!D5 -> 216.67 | E105: ='5313-510 Telecommunications'!E5 -> 216.67 | F105: ='5313-510 Telecommunications'!F5 -> 216.67 | G105: ='5313-510 Telecommunications'!G5 -> 216.67 | H105: ='5313-510 Telecommunications'!H5 -> 216.67 | I105: ='5313-510 Telecommunications'!I5 -> 216.67 | J105: ='5313-510 Telecommunications'!J5 -> 216.67 | ... O105: ='5313-510 Telecommunications'!O5 -> 2600.04
B106: Actual | C106: ='5313-510 Telecommunications'!C6 -> 0 | D106: ='5313-510 Telecommunications'!D6 -> 0 | E106: ='5313-510 Telecommunications'!E6 -> 0 | F106: ='5313-510 Telecommunications'!F6 -> 0 | G106: ='5313-510 Telecommunications'!G6 -> 0 | H106: ='5313-510 Telecommunications'!H6 -> 0 | I106: ='5313-510 Telecommunications'!I6 -> 0 | J106: ='5313-510 Telecommunications'!J6 -> 0 | ... O106: ='5313-510 Telecommunications'!O6 -> 0
B107: Budget Deficit/ Savings | C107: ='5313-510 Telecommunications'!C7 -> 216.67 | D107: ='5313-510 Telecommunications'!D7 -> 216.67 | E107: ='5313-510 Telecommunications'!E7 -> 216.67 | F107: ='5313-510 Telecommunications'!F7 -> 216.67 | G107: ='5313-510 Telecommunications'!G7 -> 216.67 | H107: ='5313-510 Telecommunications'!H7 -> 216.67 | I107: ='5313-510 Telecommunications'!I7 -> 216.67 | J107: ='5313-510 Telecommunications'!J7 -> 216.67 | ... O107: ='5313-510 Telecommunications'!O7 -> 2600.04
A108: Phone Plans of managers and PCC Phones. | B108: Year to Date Spend | C108: ='5313-510 Telecommunications'!C8 -> 0 | D108: ='5313-510 Telecommunications'!D8 -> 0 | E108: ='5313-510 Telecommunications'!E8 -> 0 | F108: ='5313-510 Telecommunications'!F8 -> 0 | G108: ='5313-510 Telecommunications'!G8 -> 0 | H108: ='5313-510 Telecommunications'!H8 -> 0 | I108: ='5313-510 Telecommunications'!I8 -> 0 | J108: ='5313-510 Telecommunications'!J8 -> 0 | ... O108: ='5313-510 Telecommunications'!O8 -> 0
B109: YTD Excess From Budget | C109: ='5313-510 Telecommunications'!C9 -> 216.67 | D109: ='5313-510 Telecommunications'!D9 -> 433.34 | E109: ='5313-510 Telecommunications'!E9 -> 650.01 | F109: ='5313-510 Telecommunications'!F9 -> 866.68 | G109: ='5313-510 Telecommunications'!G9 -> 1083.35 | H109: ='5313-510 Telecommunications'!H9 -> 1300.02 | I109: ='5313-510 Telecommunications'!I9 -> 1516.69 | J109: ='5313-510 Telecommunications'!J9 -> 1733.36 | ... O109: ='5313-510 Telecommunications'!O9 -> 0
A111: 5314-510 Postage and Freight (Outward) | B111: Actual 2024 | C111: ='5314-510 Postage & Freight'!C3 -> 0 | D111: ='5314-510 Postage & Freight'!D3 -> 0 | E111: ='5314-510 Postage & Freight'!E3 -> 0 | F111: ='5314-510 Postage & Freight'!F3 -> 0 | G111: ='5314-510 Postage & Freight'!G3 -> 0 | H111: ='5314-510 Postage & Freight'!H3 -> 0 | I111: ='5314-510 Postage & Freight'!I3 -> 0 | J111: ='5314-510 Postage & Freight'!J3 -> 0 | ... O111: ='5314-510 Postage & Freight'!O3 -> 734.55
B112: Estimated | C112: ='5314-510 Postage & Freight'!C4 -> 0 | D112: ='5314-510 Postage & Freight'!D4 -> 0 | E112: ='5314-510 Postage & Freight'!E4 -> 0 | F112: ='5314-510 Postage & Freight'!F4 -> 0 | G112: 0 | H112: ='5314-510 Postage & Freight'!H4 -> 0 | I112: ='5314-510 Postage & Freight'!I4 -> 0 | J112: ='5314-510 Postage & Freight'!J4 -> 0 | K112: 0 | L112: ='5314-510 Postage & Freight'!L4 -> 0 | M112: ='5314-510 Postage & Freight'!M4 -> 0 | N112: ='5314-510 Postage & Freight'!N4 -> 0 | O112: ='5314-510 Postage & Freight'!O4 -> 734 | Q112: =O112-O111 -> -0.55
B113: Budget | C113: ='5314-510 Postage & Freight'!C5 -> 0 | D113: ='5314-510 Postage & Freight'!D5 -> 0 | E113: ='5314-510 Postage & Freight'!E5 -> 0 | F113: ='5314-510 Postage & Freight'!F5 -> 0 | G113: ='5314-510 Postage & Freight'!G5 -> 0 | H113: ='5314-510 Postage & Freight'!H5 -> 0 | I113: ='5314-510 Postage & Freight'!I5 -> 0 | J113: ='5314-510 Postage & Freight'!J5 -> 0 | ... O113: ='5314-510 Postage & Freight'!O5 -> 0
B114: Actual | C114: ='5314-510 Postage & Freight'!C6 -> 0 | D114: ='5314-510 Postage & Freight'!D6 -> 0 | E114: ='5314-510 Postage & Freight'!E6 -> 33.94 | F114: ='5314-510 Postage & Freight'!F6 -> 0 | G114: ='5314-510 Postage & Freight'!G6 -> 0 | H114: ='5314-510 Postage & Freight'!H6 -> 241.55 | I114: ='5314-510 Postage & Freight'!I6 -> 194.31 | J114: ='5314-510 Postage & Freight'!J6 -> 249.19 | ... O114: ='5314-510 Postage & Freight'!O6 -> 797.09
B115: Budget Deficit/ Savings | C115: ='5314-510 Postage & Freight'!C7 -> 0 | D115: ='5314-510 Postage & Freight'!D7 -> 0 | E115: ='5314-510 Postage & Freight'!E7 -> -33.94 | F115: ='5314-510 Postage & Freight'!F7 -> 0 | G115: ='5314-510 Postage & Freight'!G7 -> 0 | H115: ='5314-510 Postage & Freight'!H7 -> -241.55 | I115: ='5314-510 Postage & Freight'!I7 -> -194.31 | J115: ='5314-510 Postage & Freight'!J7 -> -249.19 | ... O115: ='5314-510 Postage & Freight'!O7 -> -797.09
A116: Fedex, USPS,UPS, etc. | B116: Year to Date Spend | C116: ='5314-510 Postage & Freight'!C8 -> 0 | D116: ='5314-510 Postage & Freight'!D8 -> 0 | E116: ='5314-510 Postage & Freight'!E8 -> 33.94 | F116: ='5314-510 Postage & Freight'!F8 -> 33.94 | G116: ='5314-510 Postage & Freight'!G8 -> 33.94 | H116: ='5314-510 Postage & Freight'!H8 -> 275.49 | I116: ='5314-510 Postage & Freight'!I8 -> 469.8 | J116: ='5314-510 Postage & Freight'!J8 -> 718.99 | ... O116: ='5314-510 Postage & Freight'!O8 -> 797.09
B117: YTD Excess From Budget | C117: ='5314-510 Postage & Freight'!C9 -> 0 | D117: ='5314-510 Postage & Freight'!D9 -> 0 | E117: ='5314-510 Postage & Freight'!E9 -> -33.94 | F117: ='5314-510 Postage & Freight'!F9 -> -33.94 | G117: ='5314-510 Postage & Freight'!G9 -> -33.94 | H117: ='5314-510 Postage & Freight'!H9 -> -275.49 | I117: ='5314-510 Postage & Freight'!I9 -> -469.8 | J117: ='5314-510 Postage & Freight'!J9 -> -718.99 | ... O117: ='5314-510 Postage & Freight'!O9 -> 0
A119: Techonology Services 5315-510 | B119: Actual 2024 | C119: ='5315-510 Technology Services'!C3 -> 6906.24 | D119: ='5315-510 Technology Services'!D3 -> 6134.72 | E119: ='5315-510 Technology Services'!E3 -> 5579.61 | F119: ='5315-510 Technology Services'!F3 -> 7145.87 | G119: ='5315-510 Technology Services'!G3 -> 6555.06 | H119: ='5315-510 Technology Services'!H3 -> 6400.36 | I119: ='5315-510 Technology Services'!I3 -> 6958.69 | J119: ='5315-510 Technology Services'!J3 -> 15241.24 | ... O119: ='5315-510 Technology Services'!O3 -> 94790.68
...

Sheet Adjustment

Sheet 5024-510 Individual Contractors
A1: 5024-510 Individual Contractors
C2: January | D2: February | E2: March | F2: April | G2: May | H2: June | I2: July | J2: August | K2: September | L2: October | M2: November | N2: December | O2: Total
A3: TOTAL | B3: Actual 2024 | C3: =SUMIFS(C$11:C971,$B$11:$B971,"Actual 2024") -> 15182.75 | D3: =SUMIFS(D$11:D971,$B$11:$B971,"Actual 2024") -> 14877.45 | E3: =SUMIFS(E$11:E971,$B$11:$B971,"Actual 2024") -> 15152.75 | F3: =SUMIFS(F$11:F971,$B$11:$B971,"Actual 2024") -> 15467 | G3: =SUMIFS(G$11:G971,$B$11:$B971,"Actual 2024") -> 16872.5 | H3: =SUMIFS(H$11:H971,$B$11:$B971,"Actual 2024") -> 15506.5 | I3: =SUMIFS(I$11:I971,$B$11:$B971,"Actual 2024") -> 22385.5 | J3: =SUMIFS(J$11:J971,$B$11:$B971,"Actual 2024") -> 23444 | ... O3: =SUMIFS(O$11:O971,$B$11:$B971,"Actual 2024") -> 235250.45
B4: Estimated | C4: =SUMIFS(C$11:C971,$B$11:$B971,"Estimated") -> 25473 | D4: =SUMIFS(D$11:D971,$B$11:$B971,"Estimated") -> 25473 | E4: =SUMIFS(E$11:E971,$B$11:$B971,"Estimated") -> 25473 | F4: =SUMIFS(F$11:F971,$B$11:$B971,"Estimated") -> 25473 | G4: =SUMIFS(G$11:G971,$B$11:$B971,"Estimated") -> 25473 | H4: =SUMIFS(H$11:H971,$B$11:$B971,"Estimated") -> 25473 | I4: =SUMIFS(I$11:I971,$B$11:$B971,"Estimated") -> 25473 | J4: =SUMIFS(J$11:J971,$B$11:$B971,"Estimated") -> 25473 | ... O4: =SUMIFS(O$11:O971,$B$11:$B971,"Estimated") -> 305676
B5: Budget | C5: 23573 | D5: 23573 | E5: 23573 | F5: 23573 | G5: 23573 | H5: 23573 | I5: 23573 | J5: 23573 | K5: 23573 | L5: 23573 | M5: 23573 | N5: 23573 | O5: =SUM(C5:N5) -> 282876 | P5: 282876
B6: Actual | C6: =SUMIFS(C$11:C976,$B$11:$B976,"Actual") -> 25960.83 | D6: =SUMIFS(D$11:D976,$B$11:$B976,"Actual") -> 23257.83 | E6: =SUMIFS(E$11:E976,$B$11:$B976,"Actual") -> 26377 | F6: =SUMIFS(F$11:F976,$B$11:$B976,"Actual") -> 36213.01 | G6: =SUMIFS(G$11:G976,$B$11:$B976,"Actual") -> 66882.95 | H6: =SUMIFS(H$11:H976,$B$11:$B976,"Actual") -> 49229.95 | I6: =SUMIFS(I$11:I976,$B$11:$B976,"Actual") -> 37253.5 | J6: =SUMIFS(J$11:J976,$B$11:$B976,"Actual") -> 19065 | ... O6: =SUMIFS(O$11:O976,$B$11:$B976,"Actual") -> 315566.74
B7: Budget Deficit/ Savings | C7: =C5-C6 -> -2387.83 | D7: =D5-D6 -> 315.17 | E7: =E5-E6 -> -2804 | F7: =F5-F6 -> -12640.01 | G7: =G5-G6 -> -43309.95 | H7: =H5-H6 -> -25656.95 | I7: =I5-I6 -> -13680.5 | J7: =J5-J6 -> 4508 | ... O7: =O5-O6 -> -32690.74
B8: Year to Date Spend | C8: =SUM($C6:C6) -> 25960.83 | D8: =SUM($C6:D6) -> 49218.66 | E8: =SUM($C6:E6) -> 75595.66 | F8: =SUM($C6:F6) -> 111808.67 | G8: =SUM($C6:G6) -> 178691.62 | H8: =SUM($C6:H6) -> 227921.57 | I8: =SUM($C6:I6) -> 265175.07 | J8: =SUM($C6:J6) -> 284240.07 | ... N8: =SUM($C6:N6) -> 318959.57 | O8: =O6 -> 315566.74
B9: YTD Excess From Budget | C9: =SUM($C5:C5)-C8 -> -2387.83 | D9: =SUM($C5:D5)-D8 -> -2072.66 | E9: =SUM($C5:E5)-E8 -> -4876.66 | F9: =SUM($C5:F5)-F8 -> -17516.67 | G9: =SUM($C5:G5)-G8 -> -60826.62 | H9: =SUM($C5:H5)-H8 -> -86483.57 | I9: =SUM($C5:I5)-I8 -> -100164.07 | J9: =SUM($C5:J5)-J8 -> -95656.07 | ... N9: =SUM($C5:N5)-N8 -> -36083.57 | T9: d
A11: Harley Charlebois | B11: Actual 2024 | C11: 4836 | D11: 4316 | E11: 4160 | F11: 4992 | G11: 6136 | H11: 5928 | I11: 6136 | J11: 6526 | K11: 4160 | L11: 4160 | M11: 4160 | N11: 5290 | O11: =SUM(C11:N11) -> 60800
B12: Estimated | C12: 3700 | D12: 3700 | E12: 3700 | F12: 3700 | G12: 3700 | H12: 3700 | I12: 3700 | J12: 3700 | K12: 3700 | L12: 3700 | M12: 3700 | N12: 3700 | O12: =SUM(C12:N12) -> 44400 | Q12: She is doing copywriting
B13: Budget | O13: =SUM(C13:N13) -> 0
B14: Actual | C14: 4160 | D14: 4160 | E14: 4160 | F14: =3120+2080 -> 5200 | G14: 3120 | H14: =2080+1080+2080 -> 5240 | I14: =2080 -> 2080 | J14: =2080+2080 -> 4160 | K14: 2080 | L14: 2080 | O14: =SUM(C14:N14) -> 36440
A15: Ephraim Tacuban | B15: Actual 2024 | C15: 3291.75 | D15: 3506.45 | E15: 3557.75 | F15: 3420 | G15: 3325 | H15: 3496 | I15: 3572 | J15: 3591 | K15: 3705 | L15: 4101 | M15: 3990 | N15: 3705 | O15: =SUM(C15:N15) -> 43260.95
B16: Estimated | C16: 3040 | D16: 3040 | E16: 3040 | F16: 3040 | G16: 3040 | H16: 3040 | I16: 3040 | J16: 3040 | K16: 3040 | L16: 3040 | M16: 3040 | N16: 3040 | O16: =SUM(C16:N16) -> 36480 | Q16: Web design
B17: Budget | O17: =SUM(C17:N17) -> 0
B18: Actual | C18: 3990 | D18: 3648 | E18: 3344 | F18: 1748 | G18: 3496 | H18: 3496 | I18: =3496 -> 3496 | J18: =3496 -> 3496 | O18: =SUM(C18:N18) -> 26714
A19: Shazer Llanera | B19: Actual 2024 | C19: 2400 | D19: 2400 | E19: 2400 | F19: 2400 | G19: 2400 | H19: 2400 | I19: 2400 | J19: 2400 | K19: 2400 | L19: 2400 | M19: 2400 | N19: 2400 | O19: =SUM(C19:N19) -> 28800
B20: Estimated | C20: 2400 | D20: 2400 | E20: 2400 | F20: 2400 | G20: 2400 | H20: 2400 | I20: 2400 | J20: 2400 | K20: 2400 | L20: 2400 | M20: 2400 | N20: 2400 | O20: =SUM(C20:N20) -> 28800 | Q20: Web design
B21: Budget | O21: =SUM(C21:N21) -> 0
B22: Actual | C22: 2400 | D22: 2400 | E22: 2400 | F22: 2400 | G22: 2400 | H22: 2400 | I22: 2400 | J22: 2400 | O22: =SUM(C22:N22) -> 19200
A23: Nani Laie (Mike Foley) | B23: Actual 2024 | C23: 3135 | D23: 3135 | E23: 3135 | F23: 3135 | G23: 3135 | H23: 1562.5 | I23: 1562.5 | J23: 3125 | K23: 3125 | L23: 3125 | M23: 3125 | N23: 2090 | O23: =SUM(C23:N23) -> 33390
B24: Estimated | C24: 2613 | D24: 2613 | E24: 2613 | F24: 2613 | G24: 2613 | H24: 2613 | I24: 2613 | J24: 2613 | K24: 2613 | L24: 2613 | M24: 2613 | N24: 2613 | O24: =SUM(C24:N24) -> 31356 | Q24: Copywrighting and Legacy
B25: Budget | O25: =SUM(C25:N25) -> 0
B26: Actual | C26: 2252.83 | D26: 2252.83 | E26: 3135 | F26: 3125.5 | G26: 3135.5 | H26: 3135.5 | I26: 3135.5 | K26: 3135.5 | O26: =SUM(D26:N26) -> 21055.33 | T26: =5*40*52 -> 10400
A27: Sam Merrill | B27: Actual 2024 | O27: =SUM(C27:N27) -> 0 | T27: =2*5*40*52 -> 20800
B28: Estimated | C28: 0 | D28: 0 | E28: 0 | F28: 0 | G28: 0 | H28: 0 | I28: 0 | J28: 0 | K28: 0 | L28: 0 | M28: 0 | N28: 0 | O28: =SUM(C28:N28) -> 0 | T28: =SUM(T26:T29) -> 49400
B29: Budget | O29: =SUM(C29:N29) -> 0 | T29: =2*5*35*52 -> 18200
B30: Actual | G30: 2420 | O30: =SUM(C30:N30) -> 2420
A31: Conor Lunt | B31: Actual 2024 | O31: =SUM(C31:N31) -> 0
B32: Estimated | C32: 0 | D32: 0 | E32: 0 | F32: 0 | G32: 0 | H32: 0 | I32: 0 | J32: 0 | K32: 0 | L32: 0 | M32: 0 | N32: 0 | O32: =SUM(C32:N32) -> 0
B33: Budget | O33: =SUM(C33:N33) -> 0
B34: Actual | G34: 4102.5 | O34: =SUM(C34:N34) -> 4102.5
A35: Tanner Fernandez | B35: Actual 2024 | O35: =SUM(C35:N35) -> 0
B36: Estimated | C36: 1000 | D36: 1000 | E36: 1000 | F36: 1000 | G36: 1000 | H36: 1000 | I36: 1000 | J36: 1000 | K36: 1000 | L36: 1000 | M36: 1000 | N36: 1000 | O36: =SUM(C36:N36) -> 12000
B37: Budget | O37: =SUM(C37:N37) -> 0
B38: Actual | O38: =SUM(C38:N38) -> 0
A39: Marc Purles | B39: Actual 2024 | C39: 1520 | D39: 1520 | E39: 1900 | F39: 1520 | G39: 1520 | H39: 1520 | I39: 1520 | J39: 1520 | K39: 1520 | L39: 1520 | M39: 1520 | N39: 1520 | O39: =SUM(C39:N39) -> 18620
B40: Estimated | C40: 1500 | D40: 1500 | E40: 1500 | F40: 1500 | G40: 1500 | H40: 1500 | I40: 1500 | J40: 1500 | K40: 1500 | L40: 1500 | M40: 1500 | N40: 1500 | O40: =SUM(C40:N40) -> 18000 | Q40: Online product sales--ex-Sr missionary
B41: Budget | O41: =SUM(C41:N41) -> 0
B42: Actual | C42: 1416 | D42: 1520 | E42: 1520 | F42: =760+760 -> 1520 | G42: =760+760 -> 1520 | H42: =760+760 -> 1520 | I42: 1140 | O42: =SUM(C42:N42) -> 10156
A43: Karizza Llanera | B43: Actual 2024 | H43: 600 | I43: 2700 | J43: 2700 | K43: 2400 | L43: 3000 | M43: 2400 | N43: 2400 | O43: =SUM(C43:N43) -> 16200
B44: Estimated | C44: 1900 | D44: 1900 | E44: 1900 | F44: 1900 | G44: 1900 | H44: 1900 | I44: 1900 | J44: 1900 | K44: 1900 | L44: 1900 | M44: 1900 | N44: 1900 | O44: =SUM(C44:N44) -> 22800 | Q44: Online product sales--did not backfill position
B45: Budget | O45: =SUM(C45:N45) -> 0
B46: Actual | C46: 3000 | D46: 2400 | E46: 2400 | F46: 1500 | G46: 2400 | H46: 2400 | I46: =2400 -> 2400 | O46: =SUM(C46:N46) -> 16500
A47: Photography/Videography contractor (Isaac) | B47: Actual 2024 | O47: =SUM(C47:N47) -> 0
B48: Estimated | C48: 0 | D48: 0 | E48: 0 | F48: 0 | G48: 0 | H48: 0 | I48: 0 | J48: 0 | K48: 0 | L48: 0 | M48: 0 | N48: 0 | O48: =SUM(C48:N48) -> 0
B49: Budget | O49: =SUM(C49:N49) -> 0
B50: Actual | O50: =SUM(C50:N50) -> 0
A51: David Butterfield | B51: Actual 2024 | G51: 356.5 | O51: =SUM(C51:N51) -> 356.5
B52: Estimated | C52: 0 | D52: 0 | E52: 0 | F52: 0 | G52: 0 | H52: 0 | I52: 0 | J52: 0 | K52: 0 | L52: 0 | M52: 0 | N52: 0 | O52: =SUM(C52:N52) -> 0
B53: Budget | O53: =SUM(C53:N53) -> 0
B54: Actual | O54: =SUM(C54:N54) -> 0
A55: Hisaka Inumaki | B55: Actual 2024 | I55: 2070 | J55: 2070 | K55: 2838 | L55: 2070 | M55: 1840 | N55: 2070 | O55: =SUM(C55:N55) -> 12958
B56: Estimated | C56: 2070 | D56: 2070 | E56: 2070 | F56: 2070 | G56: 2070 | H56: 2070 | I56: 2070 | J56: 2070 | K56: 2070 | L56: 2070 | M56: 2070 | N56: 2070 | O56: =SUM(C56:N56) -> 24840 | Q56: Japan Mktg support
B57: Budget | O57: =SUM(C57:N57) -> 0
B58: Actual | C58: 2530 | D58: 1840 | E58: 2990 | F58: 2116 | G58: 2760 | H58: 2070 | I58: 1840 | J58: =1840 -> 1840 | K58: 3576.5 | L58: 2323 | O58: =SUM(C58:N58) -> 23885.5
A59: Harold Pedroso | B59: Actual 2024 | I59: 525 | O59: =SUM(C59:N59) -> 525
B60: Estimated | C60: 0 | D60: 0 | E60: 0 | F60: 0 | G60: 0 | H60: 0 | I60: 0 | J60: 0 | K60: 0 | L60: 0 | M60: 0 | N60: 0 | O60: =SUM(C60:N60) -> 0
B61: Budget | O61: =SUM(C61:N61) -> 0
B62: Actual | O62: =SUM(C62:N62) -> 0
A63: Bala Pilli | B63: Actual 2024 | I63: 1900 | J63: 1226 | K63: 950 | L63: 1349 | M63: 1254 | N63: 1400 | O63: =SUM(C63:N63) -> 8079
B64: Estimated | C64: 1700 | D64: 1700 | E64: 1700 | F64: 1700 | G64: 1700 | H64: 1700 | I64: 1700 | J64: 1700 | K64: 1700 | L64: 1700 | M64: 1700 | N64: 1700 | O64: =SUM(C64:N64) -> 20400 | Q64: Graduated, analytics--seeking student replacement
B65: Budget | O65: =SUM(C65:N65) -> 0
B66: Actual | C66: 1140 | D66: 1045 | E66: 1140 | F66: 1178 | G66: 1178 | H66: 1045 | I66: 1026 | J66: 885 | K66: 779 | O66: =SUM(D66:N66) -> 8276
A67: Khoon An | B67: Actual 2024 | J67: 286 | K67: 1727 | L67: 1760 | M67: 1760 | N67: 1760 | O67: =SUM(C67:N67) -> 7293
B68: Estimated | C68: 1750 | D68: 1750 | E68: 1750 | F68: 1750 | G68: 1750 | H68: 1750 | I68: 1750 | J68: 1750 | K68: 1750 | L68: 1750 | M68: 1750 | N68: 1750 | O68: =SUM(C68:N68) -> 21000 | Q68: Korean Marketing Consultant
B69: Budget | O69: =SUM(C69:N69) -> 0
B70: Actual | C70: 1760 | D70: 1760 | E70: 1760 | F70: 1672 | G70: 1760 | H70: 1760 | I70: 1760 | J70: 1760 | K70: 1760 | O70: =SUM(C70:N70) -> 15752
A71: Kyle Vreeken | B71: Actual 2024 | L71: 1080 | M71: 2160 | N71: 1728 | O71: =SUM(C71:N71) -> 4968
B72: Estimated | C72: 2100 | D72: 2100 | E72: 2100 | F72: 2100 | G72: 2100 | H72: 2100 | I72: 2100 | J72: 2100 | K72: 2100 | L72: 2100 | M72: 2100 | N72: 2100 | O72: =SUM(C72:N72) -> 25200 | Q72: AB Testing and set up of Optimizely Testing
B73: Budget | O73: =SUM(C73:N73) -> 0
B74: Actual | C74: 1728 | D74: 864 | E74: 2160 | F74: 2268 | G74: 1998 | H74: 1458 | I74: 2241 | J74: 2106 | K74: 2322 | L74: 1188 | O74: =SUM(C74:N74) -> 18333
A75: Antoinette Yee | B75: Actual 2024 | O75: =SUM(C75:N75) -> 0
B76: Estimated | C76: 1700 | D76: 1700 | E76: 1700 | F76: 1700 | G76: 1700 | H76: 1700 | I76: 1700 | J76: 1700 | K76: 1700 | L76: 1700 | M76: 1700 | N76: 1700 | O76: =SUM(C76:N76) -> 20400 | Q76: Graduated Student--
B77: Budget | O77: =SUM(C77:N77) -> 0
B78: Actual | C78: 1584 | D78: 1368 | E78: 1368 | F78: 1638 | G78: 1440 | H78: 1368 | I78: 1710 | J78: 1368 | L78: 1818 | O78: =SUM(C78:N78) -> 13662
A79: A Hardflip Production LLC | B79: Actual 2024 | O79: =SUM(C79:N79) -> 0
B80: Estimated | C80: 0 | D80: 0 | E80: 0 | F80: 0 | G80: 0 | H80: 0 | I80: 0 | J80: 0 | K80: 0 | L80: 0 | M80: 0 | N80: 0 | O80: =SUM(C80:N80) -> 0
B81: Budget | O81: =SUM(C81:N81) -> 0
B82: Actual | F82: 2722.51 | G82: 2722.51 | H82: 2722.51 | O82: =SUM(C82:N82) -> 8167.53
A83: Tetrachrome (Joseph Trisolini) | B83: Actual 2024 | O83: =SUM(C83:N83) -> 0
B84: Estimated | C84: 0 | D84: 0 | E84: 0 | F84: 0 | G84: 0 | H84: 0 | I84: 0 | J84: 0 | K84: 0 | L84: 0 | M84: 0 | N84: 0 | O84: =SUM(C84:N84) -> 0
B85: Budget | O85: =SUM(C85:N85) -> 0
B86: Actual | F86: 9125 | H86: 9984.94 | O86: =SUM(C86:N86) -> 19109.94
A87: Nick Gruen | B87: Actual 2024 | O87: =SUM(C87:N87) -> 0
B88: Estimated | C88: 0 | D88: 0 | E88: 0 | F88: 0 | G88: 0 | H88: 0 | I88: 0 | J88: 0 | K88: 0 | L88: 0 | M88: 0 | N88: 0 | O88: =SUM(C88:N88) -> 0
B89: Budget | O89: =SUM(C89:N89) -> 0
B90: Actual | G90: 5720 | H90: 5610 | O90: =SUM(C90:N90) -> 11330
A91: Jairus Roda | B91: Actual 2024 | O91: =SUM(C91:N91) -> 0
B92: Estimated | C92: 0 | D92: 0 | E92: 0 | F92: 0 | G92: 0 | H92: 0 | I92: 0 | J92: 0 | K92: 0 | L92: 0 | M92: 0 | N92: 0 | O92: =SUM(C92:N92) -> 0
B93: Budget | O93: =SUM(C93:N93) -> 0
B94: Actual | H94: 270 | O94: =SUM(C94:N94) -> 270
A95: Jonah Bawden | B95: Actual 2024 | O95: =SUM(C95:N95) -> 0
B96: Estimated | C96: 0 | D96: 0 | E96: 0 | F96: 0 | G96: 0 | H96: 0 | I96: 0 | J96: 0 | K96: 0 | L96: 0 | M96: 0 | N96: 0 | O96: =SUM(C96:N96) -> 0
B97: Budget | O97: =SUM(C97:N97) -> 0
B98: Actual | G98: 180 | O98: =SUM(C98:N98) -> 180
A99: Nicholas Johnson | B99: Actual 2024 | O99: =SUM(C99:N99) -> 0
B100: Estimated | C100: 0 | D100: 0 | E100: 0 | F100: 0 | G100: 0 | H100: 0 | I100: 0 | J100: 0 | K100: 0 | L100: 0 | M100: 0 | N100: 0 | O100: =SUM(C100:N100) -> 0
B101: Budget | O101: =SUM(C101:N101) -> 0
...

Sheet 5100-510 Performance based
A1: 5100-510 Performance based
C2: January | D2: February | E2: March | F2: April | G2: May | H2: June | I2: July | J2: August | K2: September | L2: October | M2: November | N2: December | O2: Total
A3: TOTAL | B3: Actual 2024 | C3: =SUMIFS(C$11:C944,$B$11:$B944,"Actual 2024") -> 143539.3 | D3: =SUMIFS(D$11:D944,$B$11:$B944,"Actual 2024") -> 147248.13 | E3: =SUMIFS(E$11:E944,$B$11:$B944,"Actual 2024") -> 185140.97 | F3: =SUMIFS(F$11:F944,$B$11:$B944,"Actual 2024") -> 169233.26 | G3: =SUMIFS(G$11:G944,$B$11:$B944,"Actual 2024") -> 176262.06 | H3: =SUMIFS(H$11:H944,$B$11:$B944,"Actual 2024") -> 149970.94 | I3: =SUMIFS(I$11:I944,$B$11:$B944,"Actual 2024") -> 177140.26 | J3: =SUMIFS(J$11:J944,$B$11:$B944,"Actual 2024") -> 155860.75 | ... O3: =SUMIFS(O$11:O944,$B$11:$B944,"Actual 2024") -> 1976450.7
B4: Estimated | C4: =SUMIFS(C$11:C944,$B$11:$B944,"Estimated") -> 146953 | D4: =SUMIFS(D$11:D944,$B$11:$B944,"Estimated") -> 180607.9 | E4: =SUMIFS(E$11:E944,$B$11:$B944,"Estimated") -> 187009.76 | F4: =SUMIFS(F$11:F944,$B$11:$B944,"Estimated") -> 174751.99 | G4: =SUMIFS(G$11:G944,$B$11:$B944,"Estimated") -> 176957.38 | H4: =SUMIFS(H$11:H944,$B$11:$B944,"Estimated") -> 173636.33 | I4: =SUMIFS(I$11:I944,$B$11:$B944,"Estimated") -> 175447.32 | J4: =SUMIFS(J$11:J944,$B$11:$B944,"Estimated") -> 166596.13 | ... O4: =SUMIFS(O$11:O944,$B$11:$B944,"Estimated") -> 2042410.7 | Q4: =O4-O3 -> 65960.05
B5: Budget | C5: 154148.08 | D5: 189450.78 | E5: 196166.08 | F5: 183308.15 | G5: 185621.52 | H5: 182137.87 | I5: 184037.53 | J5: 174752.97 | K5: 179128.29 | L5: 171152.46 | M5: 170804.54 | N5: 171702.45 | O5: =SUM(C5:N5) -> 2142410.7 | P5: 2142410.7
B6: Actual | C6: =SUMIFS(C$11:C973,$B$11:$B973,"Actual") -> 167533.56 | D6: =SUMIFS(D$11:D973,$B$11:$B973,"Actual") -> 177155.24 | E6: =SUMIFS(E$11:E973,$B$11:$B973,"Actual") -> 194641.2 | F6: =SUMIFS(F$11:F973,$B$11:$B973,"Actual") -> 189109.5 | G6: =SUMIFS(G$11:G973,$B$11:$B973,"Actual") -> 186083.66 | H6: =SUMIFS(H$11:H973,$B$11:$B973,"Actual") -> 186467.29 | I6: =SUMIFS(I$11:I973,$B$11:$B973,"Actual") -> 218352.1 | J6: =SUMIFS(J$11:J973,$B$11:$B973,"Actual") -> 206940.24 | ... O6: =SUMIFS(O$11:O973,$B$11:$B973,"Actual") -> 1828114.5
B7: Budget Deficit/ Savings | C7: =C5-C6 -> -13385.48 | D7: =D5-D6 -> 12295.54 | E7: =E5-E6 -> 1524.88 | F7: =F5-F6 -> -5801.35 | G7: =G5-G6 -> -462.14 | H7: =H5-H6 -> -4329.42 | I7: =I5-I6 -> -34314.57 | J7: =J5-J6 -> -32187.27 | ... O7: =O5-O6 -> 314296.21
B8: Year to Date Spend | C8: =SUM($C6:C6) -> 167533.56 | D8: =SUM($C6:D6) -> 344688.8 | E8: =SUM($C6:E6) -> 539330 | F8: =SUM($C6:F6) -> 728439.5 | G8: =SUM($C6:G6) -> 914523.16 | H8: =SUM($C6:H6) -> 1100990.4 | I8: =SUM($C6:I6) -> 1319342.6 | J8: =SUM($C6:J6) -> 1526282.8 | ... N8: =SUM($C6:N6) -> 1828114.5 | O8: =O6 -> 1828114.5
B9: YTD Excess From Budget | C9: =SUM($C5:C5)-C8 -> -13385.48 | D9: =SUM($C5:D5)-D8 -> -1089.94 | E9: =SUM($C5:E5)-E8 -> 434.94 | F9: =SUM($C5:F5)-F8 -> -5366.41 | G9: =SUM($C5:G5)-G8 -> -5828.55 | H9: =SUM($C5:H5)-H8 -> -10157.97 | I9: =SUM($C5:I5)-I8 -> -44472.54 | J9: =SUM($C5:J5)-J8 -> -76659.81 | ... N9: =SUM($C5:N5)-N8 -> 314296.21
A11: World Media (TripAdvisor) | B11: Actual 2024 | C11: 4080.11 | D11: 4080.02 | E11: 5055.54 | O11: =SUM(C11:N11) -> 13215.67
B12: Estimated | P12: ?
B13: Budget | O13: =SUM(C13:N13) -> 0
B14: Actual | O14: =SUM(C14:N14) -> 0
A15: World Media (Display Video, Desk, & Simplifi) | B15: Actual 2024 | C15: 23728.84 | D15: 25101.35 | E15: 35455.78 | F15: 30823.51 | G15: 34320.48 | H15: 31083.3 | I15: 46651.12 | J15: 28881.14 | K15: 33040.97 | L15: 54634.92 | M15: 36526.24 | N15: 28723.21 | O15: =SUM(C15:N15) -> 408970.86
B16: Estimated | C16: 27915 | D16: 28740 | E16: 27740 | F16: 23500 | G16: 24000 | H16: 25046 | I16: 30153 | J16: 28740 | K16: 25240 | L16: 22000 | M16: 22000 | N16: 22000 | O16: =SUM(C16:N16) -> 307074
B17: Budget | O17: =SUM(C17:N17) -> 0
A18: Unlimited | B18: Actual | C18: 27010.09 | D18: 27771.94 | E18: 28635.33 | F18: =2627.29 + 13696.76 + 7123.68 -> 23447.73 | G18: =2937.5+13690.24+6974.2 -> 23601.94 | H18: =2519.17+15403.05+6547.48 -> 24469.7 | I18: =3830.28+13331.62+8573.84+1071.27 -> 26807.01 | J18: =6222.03+11760.15+6615.33+809.32 -> 25406.83 | K18: =4121.56+11093.88+9458.1+928.52 -> 25602.06 | L18: =4876.1+12331.45+6345.73+669.01 -> 24222.29 | O18: =SUM(C18:N18) -> 256974.92 | T18: =2627.29 +13696.76 +7123.68+ 2835 -> 26282.73
A19: World Media (Google/ SEM management fees) | B19: Actual 2024 | C19: 10396.22 | D19: 11973.43 | E19: 14258.09 | F19: 14596.9 | G19: 15566.91 | H19: 13568.25 | I19: 12885.75 | J19: 12381.23 | K19: 12090.85 | L19: 12045.27 | M19: 15738.74 | N19: 11505.59 | O19: =SUM(C19:N19) -> 157007.23
B20: Estimated | C20: 12007 | D20: 12907 | E20: 13772 | F20: 13325 | G20: 14099 | H20: 13342 | I20: 12557 | J20: 11437 | K20: 11761 | L20: 11652 | M20: 11980 | N20: 12090 | O20: =SUM(C20:N20) -> 150929
B21: Budget | O21: =SUM(C21:N21) -> 0
A22: Unlimited | B22: Actual | C22: 11759.1 | D22: 13371.99 | E22: 15324.07 | F22: =T22 -> 15750.9 | G22: =13835.66+1224.81 -> 15060.47 | H22: =13417.09+1208.88 -> 14625.97 | I22: =15940.09+1125.06 -> 17065.15 | J22: =15366.99+1204.03 -> 16571.02 | K22: =11569.11+1141.6 -> 12710.71 | L22: =12701.72+1167.32 -> 13869.04 | O22: =SUM(C22:N22) -> 146108.42 | T22: =14574.28 + 1176.62 -> 15750.9
A23: World Media (Ad Serving, Pass Along Cost) | B23: Actual 2024 | C23: 1865.66 | D23: 2071.98 | E23: 2523.65 | F23: 2662.37 | G23: 2758.1 | H23: 2512.19 | I23: 2333.57 | J23: 2308.11 | K23: 2492.39 | L23: 2761.25 | M23: 3312.05 | N23: 2514.09 | O23: =SUM(C23:N23) -> 30115.41
B24: Estimated | C24: 2430 | D24: 2574 | E24: 2659 | F24: 2237 | G24: 2350 | H24: 2270 | I24: 2570 | J24: 2379 | K24: 2317 | L24: 1985 | M24: 2029 | N24: 2044 | O24: =SUM(C24:N24) -> 27844
B25: Budget | O25: =SUM(C25:N25) -> 0
A26: Unlimited | B26: Actual | C26: 2348.92 | D26: 2651.88 | E26: 2901.93 | F26: 2835 | G26: 2803.67 | H26: 2526.42 | I26: 3245.04 | J26: 3259.19 | K26: 2626.51 | L26: =2537.33 -> 2537.33 | O26: =SUM(C26:N26) -> 27735.89
A27: World Media (SEM cc charges/Invoice)- Google | B27: Actual 2024 | C27: 61359.1 | D27: 71763.22 | E27: 87944.72 | F27: 89500.71 | G27: 98132.59 | H27: 76532.94 | I27: 87212.46 | J27: 82205.62 | K27: 79558.58 | L27: 79278.32 | M27: 101106.21 | N27: 70462.07 | O27: =SUM(C27:N27) -> 985056.54
B28: Estimated | C28: 80048 | D28: 86045 | E28: 91815 | F28: 88831 | G28: 93990 | H28: 88944 | I28: 83716 | J28: 76244 | K28: 78408 | L28: 77678 | M28: 79870 | N28: 80601 | O28: =SUM(C28:N28) -> 1006190
B29: Budget | O29: =SUM(C29:N29) -> 0
A30: Unlimited | B30: Actual | C30: 73580.71 | D30: 86812.28 | E30: 94038.6 | F30: 95076.47 | G30: 96180.01 | H30: 93644.6 | I30: =111299.05 -> 111299.05 | J30: 106684.02 | K30: 62362.41 | L30: 88507.3 | O30: =SUM(C30:N30) -> 908185.45
A31: Microsoft Advertising | B31: Actual 2024 | C31: 10449.98 | D31: 7348.92 | E31: 13648.39 | F31: 8388.62 | G31: 7406.11 | H31: 6347.45 | I31: 7395.7 | J31: 6291.66 | K31: 5242.36 | L31: 5243.94 | M31: 8390.36 | N31: 10486.3 | O31: =SUM(C31:N31) -> 96639.79
B32: Estimated | C32: 0 | D32: 0 | E32: 0 | F32: 0 | G32: 0 | H32: 0 | I32: 0 | J32: 0 | K32: 0 | L32: 0 | M32: 0 | N32: 0 | O32: =SUM(C32:N32) -> 0
B33: Budget | O33: =SUM(C33:N33) -> 0
B34: Actual | C34: 8401.23 | D34: 6314.85 | E34: 10948.41 | F34: 7616.42 | G34: =1049.98+1049.93+1050.82+1049.35+1047.16+1049.47+1048.68+1047.32 -> 8392.71 | H34: =1048.21+1051.36+1048.35+1049.65+1054.36+1050.66+1047.2+1048.41 -> 8398.2 | I34: 8671.2 | J34: 7345.99 | K34: 7352.35 | L34: 7870.58 | O34: =SUM(C34:N34) -> 81311.94
A35: Referral Rock (Commissions) | B35: Actual 2024 | O35: =SUM(C35:N35) -> 0
B36: Estimated | C36: 600 | D36: 600 | E36: 600 | F36: 600 | G36: 600 | H36: 600 | I36: 600 | J36: 600 | K36: 600 | L36: 600 | M36: =IF(ISBLANK(M38),M37,M38) -> 0 | N36: =IF(ISBLANK(N38),N37,N38) -> 0 | O36: =SUM(C36:N36) -> 6000
B37: Budget | O37: =SUM(C37:N37) -> 0
B38: Actual | O38: =SUM(C38:N38) -> 0
A39: Impact (Commisions) | B39: Actual 2024 | C39: 29593.72 | D39: 22425.13 | E39: 23018.05 | F39: 19396.51 | G39: 15622.07 | H39: 16940.29 | I39: 19042.02 | J39: 20211.42 | K39: 24772.37 | L39: 21996.24 | M39: 18628.08 | N39: 15919.31 | O39: =SUM(C39:N39) -> 247565.21
B40: Estimated | C40: $34, 032.78 | D40: 25788.9 | E40: 26470.76 | F40: 22305.99 | G40: 17965.38 | H40: 19481.33 | I40: 21898.32 | J40: 23243.13 | K40: 28488.23 | L40: 25295.68 | M40: 23000 | N40: 23000 | O40: =SUM(C40:N40) -> 256937.72
B41: Budget | O41: =SUM(C41:N41) -> 0
B42: Actual | C42: 14591.88 | D42: 15804.1 | E42: 18075.02 | F42: 18410.07 | G42: 16102.74 | H42: 17234.1 | I42: 26367.62 | J42: 23118.6 | K42: 25272.3 | O42: =SUM(C42:N42) -> 174976.43
A43: Facebook Ads (Hawaii Store- Nephi's card) | B43: Actual 2024 | E43: 180.9 | F43: 139.23 | G43: 121.78 | I43: 323.25 | J43: 370.72 | K43: 495.62 | L43: 1884.82 | M43: 343.92 | N43: 858.33 | O43: =SUM(C43:N43) -> 4718.57
B44: Estimated | C44: 333 | D44: 333 | E44: 333 | F44: 333 | G44: 333 | H44: 333 | I44: 333 | J44: 333 | K44: 333 | L44: 333 | M44: 333 | N44: 333 | O44: =SUM(C44:N44) -> 3996 | P44: ?
B45: Budget | O45: =SUM(C45:N45) -> 0
B46: Actual | C46: 635.95 | D46: 635.95 | E46: 109.6 | F46: 264.95 | G46: 278.8 | I46: 372.67 | J46: 556.64 | K46: 648.55 | L46: 622.09 | O46: =SUM(C46:N46) -> 4125.2
A47: PCC PAID Social (Facebook - Polynesian Cultural Center - Virginia's card) | B47: Actual 2024 | C47: 2065.67 | D47: 2484.08 | E47: 3055.85 | F47: 3725.41 | G47: 2334.02 | H47: 2986.52 | I47: 1296.39 | J47: 3210.85 | K47: 2408.37 | L47: 3352.49 | M47: 3015.21 | N47: 3226.53 | O47: =SUM(C47:N47) -> 33161.39
B48: Estimated | C48: 3620 | D48: 3620 | E48: 3620 | F48: 3620 | G48: 3620 | H48: 3620 | I48: 3620 | J48: 3620 | K48: 3620 | L48: 3620 | M48: 3620 | N48: 3620 | O48: =SUM(C48:N48) -> 43440
B49: Budget | O49: =SUM(C49:N49) -> 0
B50: Actual | C50: 3027.67 | D50: 3792.25 | E50: 4608.24 | F50: 5567.2 | G50: =1361.26+1361.26+733.8 -> 3456.32 | H50: =1361.26+1361.26+1361.25+1070.53 -> 5154.3 | I50: 4213.86 | J50: 3997.95 | K50: 3818.11 | L50: 3810.09 | O50: =SUM(C50:N50) -> 41445.99
A51: MNTN (cctv ads) | B51: Actual 2024 | O51: =SUM(C51:N51) -> 0
B52: Estimated | C52: 20000 | D52: 20000 | E52: 20000 | F52: 20000 | G52: 20000 | H52: 20000 | I52: 20000 | J52: 20000 | K52: 20000 | L52: 20000 | M52: 20000 | N52: 20000 | O52: =SUM(C52:N52) -> 240000
B53: Budget | O53: =SUM(C53:N53) -> 0
B54: Actual | C54: 20000 | D54: 20000 | E54: 20000 | F54: 20000 | G54: 20000 | H54: 20000 | I54: 20000 | J54: 20000 | K54: 20000 | O54: =SUM(C54:N54) -> 180000
A55: Aloha Street (Wincubic.com, Inc.) | B55: Actual 2024 | O55: =SUM(C55:N55) -> 0
B56: Estimated | C56: 0 | D56: 0 | E56: 0 | F56: 0 | G56: 0 | H56: 0 | I56: 0 | J56: 0 | K56: 0 | L56: 0 | M56: 0 | N56: 0 | O56: =SUM(C56:N56) -> 0
B57: Budget | O57: =SUM(C57:N57) -> 0
B58: Actual | C58: 6178.01 | O58: =SUM(C58:N58) -> 6178.01
A59: Tango | B59: Actual 2024 | O59: =SUM(C59:N59) -> 0
B60: Estimated | C60: 0 | D60: 0 | E60: 0 | F60: 0 | G60: 0 | H60: 0 | I60: 0 | J60: 0 | K60: 0 | L60: 0 | M60: 0 | N60: 0 | O60: =SUM(C60:N60) -> 0
B61: Budget | O61: =SUM(C61:N61) -> 0
B62: Actual | F62: 140.76 | G62: 207 | H62: 414 | I62: 310.5 | O62: =SUM(C62:N62) -> 1072.26
B63: Actual 2024 | O63: =SUM(C63:N63) -> 0
B64: Estimated | C64: 0 | D64: 0 | E64: 0 | F64: 0 | G64: 0 | H64: 0 | I64: 0 | J64: 0 | K64: 0 | L64: 0 | M64: 0 | N64: 0 | O64: =SUM(C64:N64) -> 0
B65: Budget | O65: =SUM(C65:N65) -> 0
B66: Actual | O66: =SUM(C66:N66) -> 0
B67: Actual 2024 | O67: =SUM(C67:N67) -> 0
B68: Estimated | C68: 0 | D68: 0 | E68: 0 | F68: 0 | G68: 0 | H68: 0 | I68: 0 | J68: 0 | K68: 0 | L68: 0 | M68: 0 | N68: 0 | O68: =SUM(C68:N68) -> 0
B69: Budget | O69: =SUM(C69:N69) -> 0
B70: Actual | O70: =SUM(C70:N70) -> 0
B71: Actual 2024 | O71: =SUM(C71:N71) -> 0
B72: Estimated | C72: 0 | D72: 0 | E72: 0 | F72: 0 | G72: 0 | H72: 0 | I72: 0 | J72: 0 | K72: 0 | L72: 0 | M72: 0 | N72: 0 | O72: =SUM(C72:N72) -> 0
B73: Budget | O73: =SUM(C73:N73) -> 0
B74: Actual | O74: =SUM(C74:N74) -> 0
B75: Actual 2024 | O75: =SUM(C75:N75) -> 0
B76: Estimated | C76: 0 | D76: 0 | E76: 0 | F76: 0 | G76: 0 | H76: 0 | I76: 0 | J76: 0 | K76: 0 | L76: 0 | M76: 0 | N76: 0 | O76: =SUM(C76:N76) -> 0
B77: Budget | O77: =SUM(C77:N77) -> 0
B78: Actual | O78: =SUM(C78:N78) -> 0
B79: Actual 2024 | O79: =SUM(C79:N79) -> 0
B80: Estimated | C80: 0 | D80: 0 | E80: 0 | F80: 0 | G80: 0 | H80: 0 | I80: 0 | J80: 0 | K80: 0 | L80: 0 | M80: 0 | N80: 0 | O80: =SUM(C80:N80) -> 0
B81: Budget | O81: =SUM(C81:N81) -> 0
B82: Actual | O82: =SUM(C82:N82) -> 0
B83: Actual 2024 | O83: =SUM(C83:N83) -> 0
B84: Estimated | C84: 0 | D84: 0 | E84: 0 | F84: 0 | G84: 0 | H84: 0 | I84: 0 | J84: 0 | K84: 0 | L84: 0 | M84: 0 | N84: 0 | O84: =SUM(C84:N84) -> 0
B85: Budget | O85: =SUM(C85:N85) -> 0
B86: Actual | O86: =SUM(C86:N86) -> 0
B87: Actual 2024 | O87: =SUM(C87:N87) -> 0
B88: Estimated | C88: 0 | D88: 0 | E88: 0 | F88: 0 | G88: 0 | H88: 0 | I88: 0 | J88: 0 | K88: 0 | L88: 0 | M88: 0 | N88: 0 | O88: =SUM(C88:N88) -> 0
B89: Budget | O89: =SUM(C89:N89) -> 0
B90: Actual | O90: =SUM(C90:N90) -> 0

Sheet 5101-510 Non performance based
A1: 5101-510 Non performance based
C2: January | D2: February | E2: March | F2: April | G2: May | H2: June | I2: July | J2: August | K2: September | L2: October | M2: November | N2: December | O2: Total
A3: TOTAL | B3: Actual 2024 | C3: =SUMIFS(C$11:C960,$B$11:$B960,"Actual 2024") -> 54961.34 | D3: =SUMIFS(D$11:D960,$B$11:$B960,"Actual 2024") -> 52303.61 | E3: =SUMIFS(E$11:E960,$B$11:$B960,"Actual 2024") -> 53970.61 | F3: =SUMIFS(F$11:F960,$B$11:$B960,"Actual 2024") -> 62526.2 | G3: =SUMIFS(G$11:G960,$B$11:$B960,"Actual 2024") -> 50448.93 | H3: =SUMIFS(H$11:H960,$B$11:$B960,"Actual 2024") -> 33734.71 | I3: =SUMIFS(I$11:I960,$B$11:$B960,"Actual 2024") -> 36157.39 | J3: =SUMIFS(J$11:J960,$B$11:$B960,"Actual 2024") -> 43318.85 | ... O3: =SUMIFS(O$11:O960,$B$11:$B960,"Actual 2024") -> 579457.29
B4: Estimated | C4: =SUMIFS(C$11:C960,$B$11:$B960,"Estimated") -> 73939 | D4: =SUMIFS(D$11:D960,$B$11:$B960,"Estimated") -> 58654 | E4: =SUMIFS(E$11:E960,$B$11:$B960,"Estimated") -> 50860 | F4: =SUMIFS(F$11:F960,$B$11:$B960,"Estimated") -> 64316 | G4: =SUMIFS(G$11:G960,$B$11:$B960,"Estimated") -> 47360 | H4: =SUMIFS(H$11:H960,$B$11:$B960,"Estimated") -> 42133 | I4: =SUMIFS(I$11:I960,$B$11:$B960,"Estimated") -> 29860 | J4: =SUMIFS(J$11:J960,$B$11:$B960,"Estimated") -> 43399 | ... O4: =SUMIFS(O$11:O960,$B$11:$B960,"Estimated") -> 605565 | Q4: =O4-O3 -> 26107.71
B5: Budget | C5: 75939 | D5: 58654 | E5: 50860 | F5: 66316 | G5: 47360 | H5: 42133 | I5: 31860 | J5: 43399 | K5: 55360 | L5: 47149 | M5: 35760 | N5: 58775 | O5: =SUM(C5:N5) -> 613565 | P5: 613565
B6: Actual | C6: =SUMIFS(C$11:C969,$B$11:$B969,"Actual") -> 48578.52 | D6: =SUMIFS(D$11:D969,$B$11:$B969,"Actual") -> 47324.93 | E6: =SUMIFS(E$11:E969,$B$11:$B969,"Actual") -> 43482.71 | F6: =SUMIFS(F$11:F969,$B$11:$B969,"Actual") -> 73020.92 | G6: =SUMIFS(G$11:G969,$B$11:$B969,"Actual") -> 35157.55 | H6: =SUMIFS(H$11:H969,$B$11:$B969,"Actual") -> 57157.04 | I6: =SUMIFS(I$11:I969,$B$11:$B969,"Actual") -> 37818.82 | J6: =SUMIFS(J$11:J969,$B$11:$B969,"Actual") -> 50222.33 | ... O6: =SUMIFS(O$11:O969,$B$11:$B969,"Actual") -> 491972.19 | Q6: =O6-P6 -> 491972.19
B7: Budget Deficit/ Savings | C7: =C5-C6 -> 27360.48 | D7: =D5-D6 -> 11329.07 | E7: =E5-E6 -> 7377.29 | F7: =F5-F6 -> -6704.92 | G7: =G5-G6 -> 12202.45 | H7: =H5-H6 -> -15024.04 | I7: =I5-I6 -> -5958.82 | J7: =J5-J6 -> -6823.33 | ... O7: =O5-O6 -> 121592.81
B8: Year to Date Spend | C8: =SUM($C6:C6) -> 48578.52 | D8: =SUM($C6:D6) -> 95903.45 | E8: =SUM($C6:E6) -> 139386.16 | F8: =SUM($C6:F6) -> 212407.08 | G8: =SUM($C6:G6) -> 247564.63 | H8: =SUM($C6:H6) -> 304721.67 | I8: =SUM($C6:I6) -> 342540.49 | J8: =SUM($C6:J6) -> 392762.82 | ... N8: =SUM($C6:N6) -> 491972.19 | O8: =O6 -> 491972.19
B9: YTD Excess From Budget | C9: =SUM($C5:C5)-C8 -> 27360.48 | D9: =SUM($C5:D5)-D8 -> 38689.55 | E9: =SUM($C5:E5)-E8 -> 46066.84 | F9: =SUM($C5:F5)-F8 -> 39361.92 | G9: =SUM($C5:G5)-G8 -> 51564.37 | H9: =SUM($C5:H5)-H8 -> 36540.33 | I9: =SUM($C5:I5)-I8 -> 30581.51 | J9: =SUM($C5:J5)-J8 -> 23758.18 | ... N9: =SUM($C5:N5)-N8 -> 121592.81
A11: Element 8 West Bound market | B11: Actual 2024 | C11: 44302 | D11: 32940 | E11: 27857 | F11: 33380 | G11: 27856.53 | H11: 33380 | I11: 27857 | J11: 33380 | K11: 27857 | L11: 33380.09 | M11: 27856.53 | N11: 56044.4 | O11: =SUM(C11:N11) -> 406090.55
B12: Estimated | C12: 45639 | D12: 41293 | E12: 29260 | F12: 34783 | G12: 29260 | H12: 34783 | I12: 29260 | J12: 34783 | K12: 29260 | L12: 34783 | M12: 29260 | N12: 46509 | O12: =SUM(C12:N12) -> 418873
B13: Budget | O13: =SUM(C13:N13) -> 0
B14: Actual | C14: 39146.58 | D14: 29277.48 | E14: 28753.92 | F14: 46267 | G14: 29259.67 | H14: 34783.23 | I14: =29259.67 -> 29259.67 | J14: 34783.23 | K14: 37147.63 | L14: 37173.81 | O14: =SUM(C14:N14) -> 345852.22
A15: Element 8 Local market | B15: Actual 2024 | C15: 10383.24 | D15: 19113.61 | E15: 19113.61 | F15: 25942.2 | G15: 22342.4 | H15: 104.71 | I15: 104.71 | J15: 9688.85 | K15: 18291.26 | L15: 5549.74 | M15: 4149.74 | N15: 6364.92 | O15: =SUM(C15:N15) -> 141148.99
B16: Estimated | C16: 11000 | D16: 16000 | E16: 15000 | F16: 25000 | G16: 15000 | H16: 0 | I16: 0 | J16: 8016 | K16: 22000 | L16: 6766 | M16: 5900 | N16: 11666 | O16: =SUM(C16:N16) -> 136348
B17: Budget | O17: =SUM(C17:N17) -> 0
B18: Actual | C18: 837.7 | D18: 16037.69 | E18: 8184.29 | F18: =73020.92-46267 -> 26753.92 | G18: 5897.88 | H18: 19283.75 | I18: =8559.15 -> 8559.15 | J18: 0 | K18: 8647.12 | L18: 9847.1 | O18: =SUM(C18:N18) -> 104048.6
A19: Hemisphere (United Airlines) inflight magazine (INK) | B19: Actual 2024 | E19: 6750 | O19: =SUM(C19:N19) -> 6750
B20: Estimated | C20: 0 | D20: 0 | E20: 0 | F20: 0 | G20: 0 | H20: 6750 | I20: 0 | J20: 0 | K20: 0 | L20: 0 | M20: 0 | N20: 0 | O20: =SUM(C20:N20) -> 6750
B21: Budget | O21: =SUM(C21:N21) -> 0
B22: Actual | O22: =SUM(C22:N22) -> 0
A23: Activities and Attraction Association of Hawaii | B23: Actual 2024 | O23: =SUM(C23:N23) -> 0
B24: Estimated | C24: 0 | D24: 0 | E24: 0 | F24: 0 | G24: 0 | H24: 0 | I24: 0 | J24: 0 | K24: 0 | L24: 0 | M24: 0 | N24: 0 | O24: =SUM(C24:N24) -> 0
B25: Budget | O25: =SUM(C25:N25) -> 0
B26: Actual | O26: =SUM(C26:N26) -> 0
A27: North Shore Map | B27: Actual 2024 | O27: =SUM(C27:N27) -> 0
B28: Estimated | C28: 0 | D28: 0 | E28: 0 | F28: 0 | G28: 0 | H28: 0 | I28: 0 | J28: 0 | K28: 0 | L28: 0 | M28: 0 | N28: 0 | O28: =SUM(C28:N28) -> 0
B29: Budget | O29: =SUM(C29:N29) -> 0
B30: Actual | O30: =SUM(C30:N30) -> 0
A31: Photoshoot (Hawaii Store) | B31: Actual 2024 | C31: 17.35 | O31: =SUM(C31:N31) -> 17.35
B32: Estimated | C32: =IF(ISBLANK(C34),C33,C34) -> 0 | D32: =IF(ISBLANK(D34),D33,D34) -> 0 | E32: =IF(ISBLANK(E34),E33,E34) -> 0 | F32: =IF(ISBLANK(F34),F33,F34) -> 0 | G32: =IF(ISBLANK(G34),G33,G34) -> 0 | H32: =IF(ISBLANK(H34),H33,H34) -> 0 | I32: =IF(ISBLANK(I34),I33,I34) -> 0 | J32: =IF(ISBLANK(J34),J33,J34) -> 0 | ... N32: =IF(ISBLANK(N34),N33,N34) -> 0 | O32: =SUM(C32:N32) -> 0
B33: Budget | O33: =SUM(C33:N33) -> 0
B34: Actual | O34: =SUM(C34:N34) -> 0
A35: Tango Card | B35: Actual 2024 | C35: 258.75 | D35: 250 | E35: 250 | F35: 250 | G35: 250 | H35: 250 | I35: 250 | J35: 250 | K35: 250 | L35: 250 | M35: 250 | N35: 250 | O35: =SUM(C35:N35) -> 3008.75
B36: Estimated | C36: =IF(ISBLANK(C38),C37,C38) -> 0 | D36: =IF(ISBLANK(D38),D37,D38) -> 0 | E36: =IF(ISBLANK(E38),E37,E38) -> 0 | F36: =IF(ISBLANK(F38),F37,F38) -> 0 | G36: =IF(ISBLANK(G38),G37,G38) -> 0 | H36: =IF(ISBLANK(H38),H37,H38) -> 0 | I36: =IF(ISBLANK(I38),I37,I38) -> 0 | J36: =IF(ISBLANK(J38),J37,J38) -> 0 | ... N36: =IF(ISBLANK(N38),N37,N38) -> 0 | O36: =SUM(C36:N36) -> 0
B37: Budget | O37: =SUM(C37:N37) -> 0
B38: Actual | O38: =SUM(C38:N38) -> 0
A39: dotComm Awards | B39: Actual 2024 | I39: 375 | O39: =SUM(C39:N39) -> 375
B40: Estimated | C40: 0 | D40: 0 | E40: 0 | F40: 0 | G40: 0 | H40: 0 | I40: 0 | J40: 0 | K40: 0 | L40: 0 | M40: 0 | N40: 0 | O40: =SUM(C40:N40) -> 0
B41: Budget | O41: =SUM(C41:N41) -> 0
B42: Actual | O42: =SUM(C42:N42) -> 0
A43: Dana Edmunds Photography LLC | B43: Actual 2024 | L43: 2787.2 | O43: =SUM(C43:N43) -> 2787.2
B44: Estimated | C44: 0 | D44: 0 | E44: 0 | F44: 0 | G44: 0 | H44: 0 | I44: 0 | J44: 0 | K44: 0 | L44: 0 | M44: 0 | N44: 0 | O44: =SUM(C44:N44) -> 0
B45: Budget | O45: =SUM(C45:N45) -> 0
B46: Actual | O46: =SUM(C46:N46) -> 0
A47: JTB Hawaii Travel, LLC | B47: Actual 2024 | M47: 2094.24 | N47: 2094.24 | O47: =SUM(C47:N47) -> 4188.48
B48: Estimated | C48: 6300 | D48: 0 | E48: 0 | F48: 0 | G48: 0 | H48: 0 | I48: 0 | J48: 0 | K48: 0 | L48: 0 | M48: 0 | N48: 0 | O48: =SUM(C48:N48) -> 6300
B49: Budget | O49: =SUM(C49:N49) -> 0
B50: Actual | C50: 2094.24 | D50: 732.98 | J50: 1701.57 | K50: 1701.57 | O50: =SUM(C50:N50) -> 6230.36
A51: Chikyu no Arukikata | B51: Actual 2024 | O51: =SUM(C51:N51) -> 0
B52: Estimated | C52: 4200 | D52: 0 | E52: 0 | F52: 0 | G52: 0 | H52: 0 | I52: 0 | J52: 0 | K52: 0 | L52: 0 | M52: 0 | N52: 0 | O52: =SUM(C52:N52) -> 4200
B53: Budget | O53: =SUM(C53:N53) -> 0
B54: Actual | O54: =SUM(C54:N54) -> 0
A55: Aloha Express (Island Creative Solutions, LLC.) | B55: Actual 2024 | N55: 1570.68 | O55: =SUM(C55:N55) -> 1570.68
B56: Estimated | C56: 6200 | D56: 0 | E56: 0 | F56: 0 | G56: 0 | H56: 0 | I56: 0 | J56: 0 | K56: 0 | L56: 0 | M56: 0 | N56: 0 | O56: =SUM(C56:N56) -> 6200
B57: Budget | O57: =SUM(C57:N57) -> 0
B58: Actual | E58: 6282.72 | O58: =SUM(C58:N58) -> 6282.72
A59: Japan Event Registration | B59: Actual 2024 | O59: =SUM(C59:N59) -> 0
B60: Estimated | C60: 0 | D60: 0 | E60: 0 | F60: 0 | G60: 1500 | H60: 0 | I60: 0 | J60: 0 | K60: 0 | L60: 1500 | M60: 0 | N60: 0 | O60: =SUM(C60:N60) -> 3000
B61: Budget | O61: =SUM(C61:N61) -> 0
B62: Actual | O62: =SUM(C62:N62) -> 0
A63: 320 Productions | B63: Actual 2024 | K63: 1645.89 | L63: 1349.72 | O63: =SUM(C63:N63) -> 2995.61
B64: Estimated | C64: 0 | D64: 0 | E64: 0 | F64: 0 | G64: 0 | H64: 0 | I64: 0 | J64: 0 | K64: 3500 | L64: 1500 | M64: 0 | N64: 0 | O64: =SUM(C64:N64) -> 5000
B65: Budget | O65: =SUM(C65:N65) -> 0
B66: Actual | H66: =856.02+406.81+556.02+614.66+656.55 -> 3090.06 | J66: =4751.83+485.7 -> 5237.53 | K66: 492.14 | O66: =SUM(C66:N66) -> 8819.73
A67: Oahu Publications | B67: Actual 2024 | I67: 1570.68 | O67: =SUM(C67:N67) -> 1570.68
B68: Estimated | C68: 0 | D68: 761 | E68: 0 | F68: 0 | G68: 0 | H68: 0 | I68: 0 | J68: 0 | K68: 0 | L68: 0 | M68: 0 | N68: 0 | O68: =SUM(C68:N68) -> 761
B69: Budget | O69: =SUM(C69:N69) -> 0
B70: Actual | D70: 261.78 | E70: 261.78 | O70: =SUM(C70:N70) -> 523.56
A71: Bonnevile | B71: Actual 2024 | F71: 2954 | O71: =SUM(C71:N71) -> 2954
B72: Estimated | C72: 0 | D72: 0 | E72: 0 | F72: 3933 | G72: 0 | H72: 0 | I72: 0 | J72: 0 | K72: 0 | L72: 0 | M72: 0 | N72: 0 | O72: =SUM(C72:N72) -> 3933
B73: Budget | O73: =SUM(C73:N73) -> 0
B74: Actual | O74: =SUM(C74:N74) -> 0
A75: Events Hawaii Tourism | B75: Actual 2024 | O75: =SUM(C75:N75) -> 0
B76: Estimated | C76: 0 | D76: 0 | E76: 0 | F76: 0 | G76: 1000 | H76: 0 | I76: 0 | J76: 0 | K76: 0 | L76: 0 | M76: 0 | N76: 0 | O76: =SUM(C76:N76) -> 1000
B77: Budget | O77: =SUM(C77:N77) -> 0
B78: Actual | O78: =SUM(C78:N78) -> 0
A79: AirSol | B79: Actual 2024 | O79: =SUM(C79:N79) -> 0
B80: Estimated | C80: 600 | D80: 600 | E80: 600 | F80: 600 | G80: 600 | H80: 600 | I80: 600 | J80: 600 | K80: 600 | L80: 600 | M80: 600 | N80: 600 | O80: =SUM(C80:N80) -> 7200
B81: Budget | O81: =SUM(C81:N81) -> 0
B82: Actual | O82: =SUM(C82:N82) -> 0
A83: Enveritas Group | B83: Actual 2024 | I83: 6000 | O83: =SUM(C83:N83) -> 6000
B84: Estimated | C84: 0 | D84: 0 | E84: 6000 | F84: 0 | G84: 0 | H84: 0 | I84: 0 | J84: 0 | K84: 0 | L84: 0 | M84: 0 | N84: 0 | O84: =SUM(C84:N84) -> 6000
B85: Budget | O85: =SUM(C85:N85) -> 0
B86: Actual | J86: 8500 | O86: =SUM(C86:N86) -> 8500
A87: David Galeai | B87: Actual 2024 | O87: =SUM(C87:N87) -> 0
B88: Estimated | C88: 0 | D88: 0 | E88: 0 | F88: 0 | G88: 0 | H88: 0 | I88: 0 | J88: 0 | K88: 0 | L88: 0 | M88: 0 | N88: 0 | O88: =SUM(C88:N88) -> 0
B89: Budget | O89: =SUM(C89:N89) -> 0
B90: Actual | C90: 6500 | D90: 1000 | O90: =SUM(C90:N90) -> 7500
A91: Hawaii Lodging & Tourism Association | B91: Actual 2024 | O91: =SUM(C91:N91) -> 0
B92: Estimated | C92: 0 | D92: 0 | E92: 0 | F92: 0 | G92: 0 | H92: 0 | I92: 0 | J92: 0 | K92: 0 | L92: 0 | M92: 0 | N92: 0 | O92: =SUM(C92:N92) -> 0
B93: Budget | O93: =SUM(C93:N93) -> 0
B94: Actual | D94: 15 | O94: =SUM(C94:N94) -> 15
A95: TravMedia | B95: Actual 2024 | O95: =SUM(C95:N95) -> 0
B96: Estimated | C96: 0 | D96: 0 | E96: 0 | F96: 0 | G96: 0 | H96: 0 | I96: 0 | J96: 0 | K96: 0 | L96: 0 | M96: 0 | N96: 0 | O96: =SUM(C96:N96) -> 0
A97: Registration for Media conference in NYC | B97: Budget | O97: =SUM(C97:N97) -> 0
B98: Actual | L98: 4200 | O98: =SUM(C98:N98) -> 4200

Sheet 5102-510 Advertising Agency Fee
A1: 5102-510 Advertising Agency Fees
C2: January | D2: February | E2: March | F2: April | G2: May | H2: June | I2: July | J2: August | K2: September | L2: October | M2: November | N2: December | O2: Total
A3: TOTAL | B3: Actual 2024 | C3: =SUMIFS(C$11:C991,$B$11:$B991,"Actual 2024") -> 30663.22 | D3: =SUMIFS(D$11:D991,$B$11:$B991,"Actual 2024") -> 34061.61 | E3: =SUMIFS(E$11:E991,$B$11:$B991,"Actual 2024") -> 48123.82 | F3: =SUMIFS(F$11:F991,$B$11:$B991,"Actual 2024") -> 35442.91 | G3: =SUMIFS(G$11:G991,$B$11:$B991,"Actual 2024") -> 57806.73 | H3: =SUMIFS(H$11:H991,$B$11:$B991,"Actual 2024") -> 42091.03 | I3: =SUMIFS(I$11:I991,$B$11:$B991,"Actual 2024") -> 39212.95 | J3: =SUMIFS(J$11:J991,$B$11:$B991,"Actual 2024") -> 38385.77 | ... O3: =SUMIFS(O$11:O991,$B$11:$B991,"Actual 2024") -> 489117.25
B4: Estimated | C4: =SUMIFS(C$11:C991,$B$11:$B991,"Estimated") -> 67567 | D4: =SUMIFS(D$11:D991,$B$11:$B991,"Estimated") -> 97522 | E4: =SUMIFS(E$11:E991,$B$11:$B991,"Estimated") -> 58826 | F4: =SUMIFS(F$11:F991,$B$11:$B991,"Estimated") -> 51522 | G4: =SUMIFS(G$11:G991,$B$11:$B991,"Estimated") -> 65022 | H4: =SUMIFS(H$11:H991,$B$11:$B991,"Estimated") -> 49022 | I4: =SUMIFS(I$11:I991,$B$11:$B991,"Estimated") -> 47085 | J4: =SUMIFS(J$11:J991,$B$11:$B991,"Estimated") -> 47022 | ... O4: =SUMIFS(O$11:O991,$B$11:$B991,"Estimated") -> 697176 | Q4: =O4-O3 -> 208058.75
B5: Budget | C5: 67567 | D5: 97522 | E5: 58826 | F5: 51522 | G5: 65022 | H5: 49022 | I5: 47085 | J5: 47022 | K5: 47522 | L5: 56022 | M5: 57522 | N5: 52522 | O5: =SUM(C5:N5) -> 697176 | P5: 697176
B6: Actual | C6: =SUMIFS(C$11:C996,$B$11:$B996,"Actual") -> 51418.5 | D6: =SUMIFS(D$11:D996,$B$11:$B996,"Actual") -> 59616.7 | E6: =SUMIFS(E$11:E996,$B$11:$B996,"Actual") -> 47803.15 | F6: =SUMIFS(F$11:F996,$B$11:$B996,"Actual") -> 54958.58 | G6: =SUMIFS(G$11:G996,$B$11:$B996,"Actual") -> 55320.83 | H6: =SUMIFS(H$11:H996,$B$11:$B996,"Actual") -> 58388.51 | I6: =SUMIFS(I$11:I996,$B$11:$B996,"Actual") -> 63125.88 | J6: =SUMIFS(J$11:J996,$B$11:$B996,"Actual") -> 59393.07 | ... O6: =SUMIFS(O$11:O996,$B$11:$B996,"Actual") -> 528819.66
B7: Budget Deficit/ Savings | C7: =C5-C6 -> 16148.5 | D7: =D5-D6 -> 37905.3 | E7: =E5-E6 -> 11022.85 | F7: =F5-F6 -> -3436.58 | G7: =G5-G6 -> 9701.17 | H7: =H5-H6 -> -9366.51 | I7: =I5-I6 -> -16040.88 | J7: =J5-J6 -> -12371.07 | ... O7: =O5-O6 -> 168356.34
B8: Year to Date Spend | C8: =SUM($C6:C6) -> 51418.5 | D8: =SUM($C6:D6) -> 111035.2 | E8: =SUM($C6:E6) -> 158838.35 | F8: =SUM($C6:F6) -> 213796.93 | G8: =SUM($C6:G6) -> 269117.76 | H8: =SUM($C6:H6) -> 327506.27 | I8: =SUM($C6:I6) -> 390632.15 | J8: =SUM($C6:J6) -> 450025.22 | ... N8: =SUM($C6:N6) -> 528819.66 | O8: =O6 -> 528819.66
B9: YTD Excess From Budget | C9: =SUM($C5:C5)-C8 -> 16148.5 | D9: =SUM($C5:D5)-D8 -> 54053.8 | E9: =SUM($C5:E5)-E8 -> 65076.65 | F9: =SUM($C5:F5)-F8 -> 61640.07 | G9: =SUM($C5:G5)-G8 -> 71341.24 | H9: =SUM($C5:H5)-H8 -> 61974.73 | I9: =SUM($C5:I5)-I8 -> 45933.85 | J9: =SUM($C5:J5)-J8 -> 33562.78 | ... N9: =SUM($C5:N5)-N8 -> 168356.34
A11: World Media (Analytics Retainer & Agency Fee) | B11: Actual 2024 | C11: 8000 | D11: 8000 | E11: 8000 | F11: 8000 | G11: 8000 | H11: 8000 | I11: 8000 | J11: 8000 | K11: 8000 | L11: 8000 | M11: 8000 | N11: 8000 | O11: =SUM(C11:N11) -> 96000
B12: Estimated | C12: 8000 | D12: 10500 | E12: 10500 | F12: 10500 | G12: 10500 | H12: 10500 | I12: 10500 | J12: 10500 | K12: 10500 | L12: 10500 | M12: 10500 | N12: 10500 | O12: =SUM(C12:N12) -> 123500 | U12: Harley Charlebois | X12: Jairus Roda
B13: Budget | O13: =SUM(C13:N13) -> 0 | U13: Ephraim Tacuban | X13: Jonah Bawden
B14: Actual | C14: 8000 | D14: 10500 | E14: 10500 | F14: 10500 | G14: 10500 | H14: 10500 | I14: 10500 | J14: =10500+1650 -> 12150 | O14: =SUM(C14:N14) -> 83150 | U14: Shazer Llanera | X14: Nicholas Johnson
A15: World Media (SEO Retainer) | B15: Actual 2024 | U15: Nani Laie (Mike Foley) | X15: David Newbold
B16: Estimated | C16: 5000 | D16: 5000 | E16: 5000 | F16: 5000 | G16: 5000 | H16: 5000 | I16: 5000 | J16: 5000 | K16: 5000 | L16: 5000 | M16: 5000 | N16: 5000 | O16: =SUM(C16:N16) -> 60000 | U16: Sam Merrill | X16: Geo Growth
B17: Budget | U17: Conor Lunt | X17: AI Revolution Labs
B18: Actual | D18: 5000 | E18: 5000 | F18: 5000 | G18: 5000 | H18: 5000 | I18: 5000 | J18: 5000 | O18: =SUM(C18:N18) -> 35000 | U18: Tanner Fernandez | X18: Ric Noyle
A19: World Media Interactive: Run Analytics setup fee | B19: Actual 2024 | O19: =SUM(C19:N19) -> 0 | U19: Marc Purles | X19: Telesia Tonga
B20: Estimated | C20: 0 | D20: 50000 | E20: 0 | F20: 0 | G20: 0 | H20: 0 | I20: 0 | J20: 0 | K20: 0 | L20: 0 | M20: 0 | N20: 0 | O20: =SUM(C20:N20) -> 50000 | U20: Karizza Llanera | X20: Kasey Padgett
B21: Budget | O21: =SUM(C21:N21) -> 0 | U21: Photography/Videography contractor (Isaac) | X21: Evette Loo
B22: Actual | O22: =SUM(C22:N22) -> 0 | U22: David Butterfield | X22: Manuarii Tefan
A23: Pacific Digital Signs | B23: Actual 2024 | E23: 1303.66 | O23: =SUM(C23:N23) -> 1303.66 | U23: Hisaka Inumaki | X23: Bright Edge - Enterprise SEO Platform: Heavy Overlap with Ahrefs
B24: Estimated | C24: 0 | D24: 0 | E24: 1304 | F24: 0 | G24: 0 | H24: 0 | I24: 0 | J24: 0 | K24: 0 | L24: 0 | M24: 0 | N24: 0 | O24: =SUM(C24:N24) -> 1304 | U24: Harold Pedroso
B25: Budget | O25: =SUM(C25:N25) -> 0 | U25: Bala Pilli
B26: Actual | O26: =SUM(C26:N26) -> 0 | U26: Khoon An
A27: Sound Partner (Jeremy) | B27: Actual 2024 | C27: 2000 | D27: 2000 | E27: 2000 | F27: 2000 | G27: 2000 | H27: 2000 | I27: 2000 | J27: 2000 | K27: 2000 | L27: 2000 | M27: 2000 | N27: 2000 | O27: =SUM(C27:N27) -> 24000 | U27: Kyle Vreeken
B28: Estimated | C28: 2000 | D28: 2000 | E28: 2000 | F28: 2000 | G28: 2000 | H28: 2000 | I28: 2000 | J28: 2000 | K28: 2000 | L28: 2000 | M28: 2000 | N28: 2000 | O28: =SUM(C28:N28) -> 24000 | U28: Antoinette Yee
A29: Affiliate Program Manager in Impact | B29: Budget | O29: =SUM(C29:N29) -> 0 | U29: A Hardflip Production LLC
B30: Actual | C30: 2000 | D30: 2000 | E30: 2000 | F30: 2000 | G30: 2000 | H30: 2000 | I30: 2000 | J30: 2000 | K30: 2000 | L30: 2000 | O30: =SUM(C30:N30) -> 20000 | U30: Tetrachrome (Joseph Trisolini)
A31: Element 8 (Retainers) | B31: Actual 2024 | C31: 7283.77 | D31: 7283.77 | E31: 7283.77 | F31: 7283.77 | G31: 7283.77 | H31: 7283.77 | I31: 7283.77 | J31: 7283.77 | K31: 7283.77 | L31: 7283.77 | M31: 7283.77 | N31: 7283.77 | O31: =SUM(C31:N31) -> 87405.24 | U31: Nick Gruen
B32: Estimated | C32: 8625 | D32: 8625 | E32: 8625 | F32: 8625 | G32: 8625 | H32: 8625 | I32: 8625 | J32: 8625 | K32: 8625 | L32: 8625 | M32: 8625 | N32: 8625 | O32: =SUM(C32:N32) -> 103500
B33: Budget | O33: =SUM(C33:N33) -> 0
B34: Actual | C34: 9031.41 | D34: 9031.41 | E34: 9031.41 | F34: 9031.41 | G34: 9031.41 | H34: 9031.41 | I34: =9031.41 -> 9031.41 | J34: =9031.41 -> 9031.41 | K34: =9031.41 -> 9031.41 | L34: 9031.41 | O34: =SUM(C34:N34) -> 90314.1
A35: Element 8 (Creative services) | B35: Actual 2024 | C35: 4462.82 | D35: 4211.46 | E35: 13958.01 | F35: 4450.26 | G35: 26013.08 | H35: 10241.88 | I35: 5919.36 | J35: 9637.12 | K35: 8813.45 | L35: 13923.55 | M35: 13156.34 | N35: 15187.12 | O35: =SUM(C35:N35) -> 129974.45
B36: Estimated | C36: 5000 | D36: 5000 | E36: 15000 | F36: 5000 | G36: 27000 | H36: 11000 | I36: 6000 | J36: 11000 | K36: 10000 | L36: 15000 | M36: 14000 | N36: 14000 | O36: =SUM(C36:N36) -> 138000
B37: Budget | O37: =SUM(C37:N37) -> 0
B38: Actual | C38: 19336.71 | D38: 14493.1 | E38: 4581.15 | F38: 12237.69 | G38: 10465.44 | H38: 14566.22 | I38: =16659.15 -> 16659.15 | J38: 11471.28 | K38: 24445.58 | L38: 7436.28 | O38: =SUM(C38:N38) -> 135692.6
A39: The Design Farm | B39: Actual 2024 | O39: =SUM(C39:N39) -> 0
B40: Estimated | C40: 0 | D40: 0 | E40: 0 | F40: 0 | G40: 0 | H40: 0 | I40: 0 | J40: 0 | K40: 0 | L40: 0 | M40: 0 | N40: 0 | O40: =SUM(C40:N40) -> 0
B41: Budget | O41: =SUM(C41:N41) -> 0
B42: Actual | O42: =SUM(C42:N42) -> 0
A43: Island Brochure (Edward Enterprises) | B43: Actual 2024 | C43: 497.38 | D43: 497.38 | E43: 497.38 | F43: 497.38 | G43: 497.38 | H43: 497.38 | I43: 497.38 | J43: 497.38 | K43: 497.38 | L43: 497.38 | M43: 497.38 | N43: 497.38 | O43: =SUM(C43:N43) -> 5968.56
B44: Estimated | C44: 497 | D44: 497 | E44: 497 | F44: 497 | G44: 497 | H44: 497 | I44: 497 | J44: 497 | K44: 497 | L44: 497 | M44: 497 | N44: 497 | O44: =SUM(C44:N44) -> 5964
B45: Budget | O45: =SUM(C45:N45) -> 0
B46: Actual | C46: 497.38 | D46: 497.38 | E46: 497.38 | F46: 497.38 | G46: 497.38 | H46: 497.38 | I46: 497.38 | J46: 497.38 | K46: 497.38 | L46: 497.38 | O46: =SUM(C46:N46) -> 4973.8
A47: Trinity One (Outerbox) | B47: Actual 2024 | C47: 4375 | D47: 4375 | E47: 4375 | F47: 4375 | G47: 4375 | H47: 4375 | I47: 4375 | J47: 4375 | K47: 4375 | L47: 4375 | M47: 4375 | N47: 4375 | O47: =SUM(C47:N47) -> 52500
B48: Estimated | C48: 4400 | D48: 4400 | E48: 4400 | F48: 4400 | G48: 4400 | H48: 4400 | I48: 4400 | J48: 4400 | K48: 4400 | L48: 4400 | M48: 4400 | N48: 4400 | O48: =SUM(C48:N48) -> 52800
B49: Budget | O49: =SUM(C49:N49) -> 0
B50: Actual | C50: 4375 | D50: 4374.94 | E50: 4375 | F50: 6363.6 | G50: 6363.6 | H50: 4375 | I50: 4375 | J50: 4375 | K50: 4375 | L50: 4375 | O50: =SUM(C50:N50) -> 47727.14
A51: PXP "Pony Express" (Moblile App CMS DEV) | B51: Actual 2024 | O51: =SUM(C51:N51) -> 0
B52: Estimated | F52: 4500 | I52: 4500 | O52: =SUM(D52:N52) -> 9000
B53: Budget | O53: =SUM(C53:N53) -> 0
B54: Actual | O54: =SUM(C54:N54) -> 0
A55: Bus wraps | B55: Actual 2024 | O55: =SUM(C55:N55) -> 0
B56: Estimated | C56: 12000 | D56: 0 | E56: 0 | F56: 0 | G56: 0 | H56: 0 | I56: 0 | J56: 0 | K56: 0 | L56: 0 | M56: 0 | N56: 0 | O56: =SUM(C56:N56) -> 12000
B57: Budget | O57: =SUM(C57:N57) -> 0
B58: Actual | O58: =SUM(C58:N58) -> 0
A59: BIG LEAP | B59: Actual 2024 | O59: =SUM(C59:N59) -> 0
B60: Estimated | C60: 2500 | D60: 2500 | E60: 2500 | F60: 2500 | G60: 2500 | H60: 2500 | I60: 2500 | J60: 2500 | K60: 2500 | L60: 2500 | M60: 2500 | N60: 2500 | O60: =SUM(C60:N60) -> 30000
B61: Budget | O61: =SUM(C61:N61) -> 0
B62: Actual | O62: =SUM(C62:N62) -> 0
A63: BLEND INTERACTIVE | B63: Actual 2024 | O63: =SUM(C63:N63) -> 0
B64: Estimated | C64: 0 | D64: 0 | E64: 0 | F64: 0 | G64: 0 | H64: 0 | I64: 0 | J64: 0 | K64: 0 | L64: 0 | M64: 0 | N64: 0 | O64: =SUM(C64:N64) -> 0
B65: Budget | O65: =SUM(C65:N65) -> 0
B66: Actual | O66: =SUM(C66:N66) -> 0
A67: PXP "Pony Express" (Retainer) | B67: Actual 2024 | C67: 4044.25 | D67: 7694 | E67: 10706 | F67: 8836.5 | G67: 9637.5 | H67: 9693 | I67: 10572 | J67: 6592.5 | K67: 7162.5 | L67: 5333.15 | M67: 5128.5 | N67: 6000 | O67: =SUM(C67:N67) -> 91399.9
B68: Estimated | C68: =50*150 -> 7500 | D68: =50*150 -> 7500 | E68: =50*150 -> 7500 | F68: =50*150 -> 7500 | G68: =50*150 -> 7500 | H68: =50*150 -> 7500 | I68: =50*150 -> 7500 | J68: =50*150 -> 7500 | ... N68: =50*150 -> 7500 | O68: =SUM(C68:N68) -> 90000
B69: Budget | O69: =SUM(C69:N69) -> 0
B70: Actual | C70: 8178 | D70: 9345 | E70: 11769 | F70: 9328.5 | G70: 11463 | H70: 12418.5 | I70: 14497.5 | J70: 14868 | K70: 15006 | O70: =SUM(C70:N70) -> 106873.5
A71: Japan Webiste OPti Migration | B71: Actual 2024 | O71: =SUM(C71:N71) -> 0
B72: Estimated | C72: 0 | D72: 0 | E72: 0 | F72: 2000 | G72: 2000 | H72: 2000 | I72: 0 | J72: 0 | K72: 0 | L72: 0 | M72: 0 | N72: 0 | O72: =SUM(C72:N72) -> 6000
B73: Budget | O73: =SUM(C73:N73) -> 0
B74: Actual | O74: =SUM(C74:N74) -> 0
A75: Korea Website Migration | B75: Actual 2024 | O75: =SUM(C75:N75) -> 0
B76: Estimated | C76: 2000 | D76: 2000 | E76: 2000 | F76: 0 | G76: 0 | H76: 0 | I76: 0 | J76: 0 | K76: 0 | L76: 0 | M76: 0 | N76: 0 | O76: =SUM(C76:N76) -> 6000
B77: Budget | O77: =SUM(C77:N77) -> 0
B78: Actual | O78: =SUM(C78:N78) -> 0
A79: China Website Migration | B79: Actual 2024 | O79: =SUM(C79:N79) -> 0
B80: Estimated | C80: 0 | D80: 0 | E80: 0 | F80: 0 | G80: 0 | H80: 0 | I80: 0 | J80: 0 | K80: 0 | L80: 2000 | M80: 2000 | N80: 2000 | O80: =SUM(C80:N80) -> 6000
B81: Budget | O81: =SUM(C81:N81) -> 0
B82: Actual | O82: =SUM(C82:N82) -> 0
A83: Kula Software - PonoRez (A3H) | B83: Actual 2024 | I83: 565.44 | O83: =SUM(C83:N83) -> 565.44
B84: Estimated | C84: 0 | D84: 0 | E84: 0 | F84: 0 | G84: 0 | H84: 0 | I84: 563 | J84: 0 | K84: 0 | L84: 0 | M84: 0 | N84: 0 | O84: =SUM(C84:N84) -> 563
B85: Budget | O85: =SUM(C85:N85) -> 0
B86: Actual | I86: 565.44 | O86: =SUM(C86:N86) -> 565.44
A87: Heinson (Moblle App Dev) | B87: Actual 2024 | O87: =SUM(C87:N87) -> 0
B88: Estimated | C88: 0 | D88: 0 | E88: 0 | F88: 0 | G88: 0 | H88: 0 | I88: 0 | J88: 0 | K88: 0 | L88: 0 | M88: 0 | N88: 0 | O88: =SUM(C88:N88) -> 0
B89: Budget | O89: =SUM(C89:N89) -> 0
B90: Actual | O90: =SUM(C90:N90) -> 0
A91: Boncom | B91: Actual 2024 | O91: =SUM(C91:N91) -> 0
B92: Estimated | C92: 0 | D92: 0 | E92: 0 | F92: 0 | G92: 0 | H92: 0 | I92: 0 | J92: 0 | K92: 0 | L92: 0 | M92: 0 | N92: 0 | O92: =SUM(C92:N92) -> 0
B93: Budget | O93: =SUM(C93:N93) -> 0
B94: Actual | O94: =SUM(C94:N94) -> 0
A95: Rakuten | B95: Actual 2024 | O95: =SUM(C95:N95) -> 0
B96: Estimated | C96: 9000 | D96: 0 | E96: 0 | F96: 0 | G96: 0 | H96: 0 | I96: 0 | J96: 0 | K96: 0 | L96: 0 | M96: 0 | N96: 0 | O96: =SUM(C96:N96) -> 9000
A97: Japanese Amazon (and reviews like TripAdvisor) | B97: Budget | O97: =SUM(C97:N97) -> 0
A98: Mia | B98: Actual | O98: =SUM(C98:N98) -> 0
A99: Server side Tagging | B99: Actual 2024 | O99: =SUM(C99:N99) -> 0
B100: Estimated | C100: 1500 | D100: 0 | E100: 0 | F100: 1500 | G100: 0 | H100: 0 | I100: 0 | J100: 0 | K100: 1500 | L100: 0 | M100: 0 | N100: 0 | O100: =SUM(C100:N100) -> 4500
B101: Budget | O101: =SUM(C101:N101) -> 0
...

Sheet 5104-510 Public Relations
A1: 5104-510 Public Relations
C2: January | D2: February | E2: March | F2: April | G2: May | H2: June | I2: July | J2: August | K2: September | L2: October | M2: November | N2: December | O2: Total
A3: TOTAL | B3: Actual 2024 | C3: =SUMIFS(C$11:C996,$B$11:$B996,"Actual 2024") -> 8376.96 | D3: =SUMIFS(D$11:D996,$B$11:$B996,"Actual 2024") -> 8376.96 | E3: =SUMIFS(E$11:E996,$B$11:$B996,"Actual 2024") -> 8376.96 | F3: =SUMIFS(F$11:F996,$B$11:$B996,"Actual 2024") -> 17177.88 | G3: =SUMIFS(G$11:G996,$B$11:$B996,"Actual 2024") -> 23701.57 | H3: =SUMIFS(H$11:H996,$B$11:$B996,"Actual 2024") -> 11057.63 | I3: =SUMIFS(I$11:I996,$B$11:$B996,"Actual 2024") -> 10209.42 | J3: =SUMIFS(J$11:J996,$B$11:$B996,"Actual 2024") -> 10209.42 | ... O3: =SUMIFS(O$11:O996,$B$11:$B996,"Actual 2024") -> 157545.37
B4: Estimated | C4: =SUMIFS(C$11:C996,$B$11:$B996,"Estimated") -> 10209.46 | D4: =SUMIFS(D$11:D996,$B$11:$B996,"Estimated") -> 10209.46 | E4: =SUMIFS(E$11:E996,$B$11:$B996,"Estimated") -> 21832.46 | F4: =SUMIFS(F$11:F996,$B$11:$B996,"Estimated") -> 10209.46 | G4: =SUMIFS(G$11:G996,$B$11:$B996,"Estimated") -> 16832.46 | H4: =SUMIFS(H$11:H996,$B$11:$B996,"Estimated") -> 10209.46 | I4: =SUMIFS(I$11:I996,$B$11:$B996,"Estimated") -> 10209.46 | J4: =SUMIFS(J$11:J996,$B$11:$B996,"Estimated") -> 10209.46 | ... O4: =SUMIFS(O$11:O996,$B$11:$B996,"Estimated") -> 152382.52 | Q4: =O4-O3 -> -5162.85
B5: Budget | C5: 10209.46 | D5: 10209.46 | E5: 21832.46 | F5: 10209.46 | G5: 16832.46 | H5: 10209.46 | I5: 10209.46 | J5: 10209.46 | K5: 21832.46 | L5: 10209.46 | M5: 10209.46 | N5: 10209.46 | O5: =SUM(C5:N5) -> 152382.52 | P5: 152382.52
B6: Actual | C6: =SUMIFS(C$11:C1001,$B$11:$B1001,"Actual") -> 10467.72 | D6: =SUMIFS(D$11:D1001,$B$11:$B1001,"Actual") -> 12294.22 | E6: =SUMIFS(E$11:E1001,$B$11:$B1001,"Actual") -> 10209.42 | F6: =SUMIFS(F$11:F1001,$B$11:$B1001,"Actual") -> 9126.96 | G6: =SUMIFS(G$11:G1001,$B$11:$B1001,"Actual") -> 21267.29 | H6: =SUMIFS(H$11:H1001,$B$11:$B1001,"Actual") -> 13282.01 | I6: =SUMIFS(I$11:I1001,$B$11:$B1001,"Actual") -> 8376.96 | J6: =SUMIFS(J$11:J1001,$B$11:$B1001,"Actual") -> 8376.96 | ... O6: =SUMIFS(O$11:O1001,$B$11:$B1001,"Actual") -> 103610.96
B7: Budget Deficit/ Savings | C7: =C5-C6 -> -258.26 | D7: =D5-D6 -> -2084.76 | E7: =E5-E6 -> 11623.04 | F7: =F5-F6 -> 1082.5 | G7: =G5-G6 -> -4434.83 | H7: =H5-H6 -> -3072.55 | I7: =I5-I6 -> 1832.5 | J7: =J5-J6 -> 1832.5 | ... O7: =O5-O6 -> 48771.56 | P7: =O4-O7 -> 103610.96
B8: Year to Date Spend | C8: =SUM($C6:C6) -> 10467.72 | D8: =SUM($C6:D6) -> 22761.94 | E8: =SUM($C6:E6) -> 32971.36 | F8: =SUM($C6:F6) -> 42098.32 | G8: =SUM($C6:G6) -> 63365.61 | H8: =SUM($C6:H6) -> 76647.62 | I8: =SUM($C6:I6) -> 85024.58 | J8: =SUM($C6:J6) -> 93401.54 | ... N8: =SUM($C6:N6) -> 103610.96 | O8: =O6 -> 103610.96
B9: YTD Excess From Budget | C9: =SUM($C5:C5)-C8 -> -258.26 | D9: =SUM($C5:D5)-D8 -> -2343.02 | E9: =SUM($C5:E5)-E8 -> 9280.02 | F9: =SUM($C5:F5)-F8 -> 10362.52 | G9: =SUM($C5:G5)-G8 -> 5927.69 | H9: =SUM($C5:H5)-H8 -> 2855.14 | I9: =SUM($C5:I5)-I8 -> 4687.64 | J9: =SUM($C5:J5)-J8 -> 6520.14 | ... N9: =SUM($C5:N5)-N8 -> 48771.56
A11: Anthology- Finn Partners | B11: Actual 2024 | C11: 8376.96 | D11: 8376.96 | E11: 8376.96 | F11: 8376.96 | G11: 12273.07 | H11: 9225.17 | I11: 8376.96 | J11: 8376.96 | K11: 10763.79 | L11: 8376.96 | M11: 18848.16 | N11: 8376.96 | O11: =SUM(C11:N11) -> 118125.87
B12: Estimated | C12: 8377 | D12: 8377 | E12: 20000 | F12: 8377 | G12: 15000 | H12: 8377 | I12: 8377 | J12: 8377 | K12: 20000 | L12: 8377 | M12: 8377 | N12: 8377 | O12: =SUM(C12:N12) -> 130393
B13: Budget | O13: =SUM(C13:N13) -> 0
B14: Actual | C14: 8635.26 | D14: 8376.96 | E14: 8376.96 | F14: =8376.96+750 -> 9126.96 | G14: =8376.96+12709.92 -> 21086.88 | H14: =222.87+4682.18+8376.96 -> 13282.01 | I14: =8376.96 -> 8376.96 | J14: 8376.96 | K14: 8376.96 | O14: =SUM(C14:N14) -> 94015.91
A15: S. Morris and Associates, LLC | B15: Actual 2024 | F15: 1832.46 | G15: 1832.46 | H15: 1832.46 | I15: 1832.46 | J15: 1832.46 | K15: 1832.46 | L15: 1832.46 | M15: 1832.46 | N15: 1832.46 | O15: =SUM(C15:N15) -> 16492.14
B16: Estimated | C16: 1832.46 | D16: 1832.46 | E16: 1832.46 | F16: 1832.46 | G16: 1832.46 | H16: 1832.46 | I16: 1832.46 | J16: 1832.46 | K16: 1832.46 | L16: 1832.46 | M16: 1832.46 | N16: 1832.46 | O16: =SUM(C16:N16) -> 21989.52
B17: Budget | O17: =SUM(C17:N17) -> 0
B18: Actual | C18: 1832.46 | D18: 1832.46 | E18: 1832.46 | K18: 1832.46 | O18: =SUM(C18:N18) -> 7329.84
A19: Delta Airlines | B19: Actual 2024 | F19: 6968.46 | O19: =SUM(C19:N19) -> 6968.46
B20: Estimated | C20: 0 | D20: 0 | E20: 0 | F20: 0 | G20: 0 | H20: 0 | I20: 0 | J20: 0 | K20: 0 | L20: 0 | M20: 0 | N20: 0 | O20: =SUM(C20:N20) -> 0
B21: Budget | O21: =SUM(C21:N21) -> 0
B22: Actual | O22: =SUM(C22:N22) -> 0
A23: American Broadcasting Companies Inc. | B23: Actual 2024 | G23: 9596.04 | O23: =SUM(C23:N23) -> 9596.04
B24: Estimated | C24: 0 | D24: 0 | E24: 0 | F24: 0 | G24: 0 | H24: 0 | I24: 0 | J24: 0 | K24: 0 | L24: 0 | M24: 0 | N24: 0 | O24: =SUM(C24:N24) -> 0
B25: Budget | O25: =SUM(C25:N25) -> 0
B26: Actual | O26: =SUM(C26:N26) -> 0
A27: Southwest | B27: Actual 2024 | L27: 441.4 | O27: =SUM(C27:N27) -> 441.4
B28: Estimated | C28: 0 | D28: 0 | E28: 0 | F28: 0 | G28: 0 | H28: 0 | I28: 0 | J28: 0 | K28: 0 | L28: 0 | M28: 0 | N28: 0 | O28: =SUM(C28:N28) -> 0
B29: Budget | O29: =SUM(C29:N29) -> 0
B30: Actual | O30: =SUM(C30:N30) -> 0
A31: Air Canada | B31: Actual 2024 | L31: 789.36 | O31: =SUM(C31:N31) -> 789.36
B32: Estimated | C32: 0 | D32: 0 | E32: 0 | F32: 0 | G32: 0 | H32: 0 | I32: 0 | J32: 0 | K32: 0 | L32: 0 | M32: 0 | N32: 0 | O32: =SUM(C32:N32) -> 0
B33: Budget | O33: =SUM(C33:N33) -> 0
B34: Actual | O34: =SUM(C34:N34) -> 0
A35: United | B35: Actual 2024 | L35: 649.42 | O35: =SUM(C35:N35) -> 649.42
B36: Estimated | C36: 0 | D36: 0 | E36: 0 | F36: 0 | G36: 0 | H36: 0 | I36: 0 | J36: 0 | K36: 0 | L36: 0 | M36: 0 | N36: 0 | O36: =SUM(C36:N36) -> 0
B37: Budget | O37: =SUM(C37:N37) -> 0
B38: Actual | O38: =SUM(C38:N38) -> 0
A39: Hawaiian Airlines | B39: Actual 2024 | M39: 2971.22 | O39: =SUM(C39:N39) -> 2971.22
B40: Estimated | C40: 0 | D40: 0 | E40: 0 | F40: 0 | G40: 0 | H40: 0 | I40: 0 | J40: 0 | K40: 0 | L40: 0 | M40: 0 | N40: 0 | O40: =SUM(C40:N40) -> 0
B41: Budget | O41: =SUM(C41:N41) -> 0
B42: Actual | D42: 2084.8 | O42: =SUM(C42:N42) -> 2084.8
A43: Courtyard by Marriot | B43: Actual 2024 | M43: 1511.46 | O43: =SUM(C43:N43) -> 1511.46
B44: Estimated | C44: 0 | D44: 0 | E44: 0 | F44: 0 | G44: 0 | H44: 0 | I44: 0 | J44: 0 | K44: 0 | L44: 0 | M44: 0 | N44: 0 | O44: =SUM(C44:N44) -> 0
B45: Budget | O45: =SUM(C45:N45) -> 0
B46: Actual | O46: =SUM(C46:N46) -> 0
A47: Large Format Printing | B47: Actual 2024 | O47: =SUM(C47:N47) -> 0
B48: Estimated | C48: 0 | D48: 0 | E48: 0 | F48: 0 | G48: 0 | H48: 0 | I48: 0 | J48: 0 | K48: 0 | L48: 0 | M48: 0 | N48: 0 | O48: =SUM(C48:N48) -> 0
B49: Budget | O49: =SUM(C49:N49) -> 0
B50: Actual | G50: 180.41 | O50: =SUM(C50:N50) -> 180.41
A51: Raksul | B51: Actual 2024 | O51: =SUM(C51:N51) -> 0
B52: Estimated | C52: 0 | D52: 0 | E52: 0 | F52: 0 | G52: 0 | H52: 0 | I52: 0 | J52: 0 | K52: 0 | L52: 0 | M52: 0 | N52: 0 | O52: =SUM(C52:N52) -> 0
B53: Budget | O53: =SUM(C53:N53) -> 0
B54: Actual | O54: =SUM(C54:N54) -> 0
B55: Actual 2024 | O55: =SUM(C55:N55) -> 0
B56: Estimated | C56: 0 | D56: 0 | E56: 0 | F56: 0 | G56: 0 | H56: 0 | I56: 0 | J56: 0 | K56: 0 | L56: 0 | M56: 0 | N56: 0 | O56: =SUM(C56:N56) -> 0
B57: Budget | O57: =SUM(C57:N57) -> 0
B58: Actual | O58: =SUM(C58:N58) -> 0
B59: Actual 2024 | O59: =SUM(C59:N59) -> 0
B60: Estimated | C60: 0 | D60: 0 | E60: 0 | F60: 0 | G60: 0 | H60: 0 | I60: 0 | J60: 0 | K60: 0 | L60: 0 | M60: 0 | N60: 0 | O60: =SUM(C60:N60) -> 0
B61: Budget | O61: =SUM(C61:N61) -> 0
B62: Actual | O62: =SUM(C62:N62) -> 0
B63: Actual 2024 | O63: =SUM(C63:N63) -> 0
B64: Estimated | C64: 0 | D64: 0 | E64: 0 | F64: 0 | G64: 0 | H64: 0 | I64: 0 | J64: 0 | K64: 0 | L64: 0 | M64: 0 | N64: 0 | O64: =SUM(C64:N64) -> 0
B65: Budget | O65: =SUM(C65:N65) -> 0
B66: Actual | O66: =SUM(C66:N66) -> 0
B67: Actual 2024 | O67: =SUM(C67:N67) -> 0
B68: Estimated | C68: 0 | D68: 0 | E68: 0 | F68: 0 | G68: 0 | H68: 0 | I68: 0 | J68: 0 | K68: 0 | L68: 0 | M68: 0 | N68: 0 | O68: =SUM(C68:N68) -> 0
B69: Budget | O69: =SUM(C69:N69) -> 0
B70: Actual | O70: =SUM(C70:N70) -> 0
B71: Actual 2024 | O71: =SUM(C71:N71) -> 0
B72: Estimated | C72: 0 | D72: 0 | E72: 0 | F72: 0 | G72: 0 | H72: 0 | I72: 0 | J72: 0 | K72: 0 | L72: 0 | M72: 0 | N72: 0 | O72: =SUM(C72:N72) -> 0
B73: Budget | O73: =SUM(C73:N73) -> 0
B74: Actual | O74: =SUM(C74:N74) -> 0
B75: Actual 2024 | O75: =SUM(C75:N75) -> 0
B76: Estimated | C76: 0 | D76: 0 | E76: 0 | F76: 0 | G76: 0 | H76: 0 | I76: 0 | J76: 0 | K76: 0 | L76: 0 | M76: 0 | N76: 0 | O76: =SUM(C76:N76) -> 0
B77: Budget | O77: =SUM(C77:N77) -> 0
B78: Actual | O78: =SUM(C78:N78) -> 0
B79: Actual 2024 | O79: =SUM(C79:N79) -> 0
B80: Estimated | C80: 0 | D80: 0 | E80: 0 | F80: 0 | G80: 0 | H80: 0 | I80: 0 | J80: 0 | K80: 0 | L80: 0 | M80: 0 | N80: 0 | O80: =SUM(C80:N80) -> 0
B81: Budget | O81: =SUM(C81:N81) -> 0
B82: Actual | O82: =SUM(C82:N82) -> 0
B83: Actual 2024 | O83: =SUM(C83:N83) -> 0
B84: Estimated | C84: 0 | D84: 0 | E84: 0 | F84: 0 | G84: 0 | H84: 0 | I84: 0 | J84: 0 | K84: 0 | L84: 0 | M84: 0 | N84: 0 | O84: =SUM(C84:N84) -> 0
B85: Budget | O85: =SUM(C85:N85) -> 0
B86: Actual | O86: =SUM(C86:N86) -> 0
B87: Actual 2024 | O87: =SUM(C87:N87) -> 0
B88: Estimated | C88: 0 | D88: 0 | E88: 0 | F88: 0 | G88: 0 | H88: 0 | I88: 0 | J88: 0 | K88: 0 | L88: 0 | M88: 0 | N88: 0 | O88: =SUM(C88:N88) -> 0
B89: Budget | O89: =SUM(C89:N89) -> 0
B90: Actual | O90: =SUM(C90:N90) -> 0
B91: Actual 2024 | O91: =SUM(C91:N91) -> 0
B92: Estimated | C92: 0 | D92: 0 | E92: 0 | F92: 0 | G92: 0 | H92: 0 | I92: 0 | J92: 0 | K92: 0 | L92: 0 | M92: 0 | N92: 0 | O92: =SUM(C92:N92) -> 0
B93: Budget | O93: =SUM(C93:N93) -> 0
B94: Actual | O94: =SUM(C94:N94) -> 0
B95: Actual 2024 | O95: =SUM(C95:N95) -> 0
B96: Estimated | C96: 0 | D96: 0 | E96: 0 | F96: 0 | G96: 0 | H96: 0 | I96: 0 | J96: 0 | K96: 0 | L96: 0 | M96: 0 | N96: 0 | O96: =SUM(C96:N96) -> 0
B97: Budget | O97: =SUM(C97:N97) -> 0
B98: Actual | O98: =SUM(C98:N98) -> 0

Sheet 5105-510 Promotional Events
A1: 5105-510 Promotional Events
C2: January | D2: February | E2: March | F2: April | G2: May | H2: June | I2: July | J2: August | K2: September | L2: October | M2: November | N2: December | O2: Total
A3: TOTAL | B3: Actual 2024 | C3: =SUMIFS(C$11:C996,$B$11:$B996,"Actual 2024") -> 0 | D3: =SUMIFS(D$11:D996,$B$11:$B996,"Actual 2024") -> 0 | E3: =SUMIFS(E$11:E996,$B$11:$B996,"Actual 2024") -> 0 | F3: =SUMIFS(F$11:F996,$B$11:$B996,"Actual 2024") -> 0 | G3: =SUMIFS(G$11:G996,$B$11:$B996,"Actual 2024") -> 0 | H3: =SUMIFS(H$11:H996,$B$11:$B996,"Actual 2024") -> 0 | I3: =SUMIFS(I$11:I996,$B$11:$B996,"Actual 2024") -> 0 | J3: =SUMIFS(J$11:J996,$B$11:$B996,"Actual 2024") -> 0 | ... O3: =SUMIFS(O$11:O996,$B$11:$B996,"Actual 2024") -> 0
B4: Estimated | C4: =SUMIFS(C$11:C996,$B$11:$B996,"Estimated") -> 0 | D4: =SUMIFS(D$11:D996,$B$11:$B996,"Estimated") -> 0 | E4: =SUMIFS(E$11:E996,$B$11:$B996,"Estimated") -> 0 | F4: =SUMIFS(F$11:F996,$B$11:$B996,"Estimated") -> 0 | G4: =SUMIFS(G$11:G996,$B$11:$B996,"Estimated") -> 0 | H4: =SUMIFS(H$11:H996,$B$11:$B996,"Estimated") -> 0 | I4: =SUMIFS(I$11:I996,$B$11:$B996,"Estimated") -> 0 | J4: =SUMIFS(J$11:J996,$B$11:$B996,"Estimated") -> 0 | ... O4: =SUMIFS(O$11:O996,$B$11:$B996,"Estimated") -> 0 | Q4: =O4-O3 -> 0
B5: Budget | C5: 0 | D5: 0 | E5: 0 | F5: 0 | G5: 0 | H5: 0 | I5: 0 | J5: 0 | K5: 0 | L5: 0 | M5: 0 | N5: 0 | O5: =SUM(C5:N5) -> 0 | P5: 0
B6: Actual | C6: =SUMIFS(C$11:C1001,$B$11:$B1001,"Actual") -> 2008.82 | D6: =SUMIFS(D$11:D1001,$B$11:$B1001,"Actual") -> 2770.4 | E6: =SUMIFS(E$11:E1001,$B$11:$B1001,"Actual") -> 55.81 | F6: =SUMIFS(F$11:F1001,$B$11:$B1001,"Actual") -> 2373.42 | G6: =SUMIFS(G$11:G1001,$B$11:$B1001,"Actual") -> 1969.39 | H6: =SUMIFS(H$11:H1001,$B$11:$B1001,"Actual") -> 3896.16 | I6: =SUMIFS(I$11:I1001,$B$11:$B1001,"Actual") -> 96.71 | J6: =SUMIFS(J$11:J1001,$B$11:$B1001,"Actual") -> 7626.13 | ... O6: =SUMIFS(O$11:O1001,$B$11:$B1001,"Actual") -> 27328.19
B7: Budget Deficit/ Savings | C7: =C5-C6 -> -2008.82 | D7: =D5-D6 -> -2770.4 | E7: =E5-E6 -> -55.81 | F7: =F5-F6 -> -2373.42 | G7: =G5-G6 -> -1969.39 | H7: =H5-H6 -> -3896.16 | I7: =I5-I6 -> -96.71 | J7: =J5-J6 -> -7626.13 | ... O7: =O5-O6 -> -27328.19
B8: Year to Date Spend | C8: =SUM($C6:C6) -> 2008.82 | D8: =SUM($C6:D6) -> 4779.22 | E8: =SUM($C6:E6) -> 4835.03 | F8: =SUM($C6:F6) -> 7208.45 | G8: =SUM($C6:G6) -> 9177.84 | H8: =SUM($C6:H6) -> 13074 | I8: =SUM($C6:I6) -> 13170.71 | J8: =SUM($C6:J6) -> 20796.84 | ... N8: =SUM($C6:N6) -> 27328.19 | O8: =O6 -> 27328.19
B9: YTD Excess From Budget | C9: =SUM($C5:C5)-C8 -> -2008.82 | D9: =SUM($C5:D5)-D8 -> -4779.22 | E9: =SUM($C5:E5)-E8 -> -4835.03 | F9: =SUM($C5:F5)-F8 -> -7208.45 | G9: =SUM($C5:G5)-G8 -> -9177.84 | H9: =SUM($C5:H5)-H8 -> -13074 | I9: =SUM($C5:I5)-I8 -> -13170.71 | J9: =SUM($C5:J5)-J8 -> -20796.84 | ... N9: =SUM($C5:N5)-N8 -> -27328.19
A11: Sharing Aloha | B11: Actual 2024 | O11: =SUM(C11:N11) -> 0
B12: Estimated | C12: 0 | D12: 0 | E12: 0 | F12: 0 | G12: 0 | H12: 0 | I12: 0 | J12: 0 | K12: 0 | L12: 0 | M12: 0 | N12: 0 | O12: =SUM(C12:N12) -> 0
B13: Budget | O13: =SUM(C13:N13) -> 0
B14: Actual | C14: 2008.82 | D14: 2770.4 | E14: 55.81 | G14: 148.3 | H14: 1909 | I14: 96.71 | J14: =279.9-194.61-15.04+20.94+6.59+32.14+34.54+46.96+131.46+118.58+2985+390+17.79+63.26+3035.6 -> 6953.11 | K14: =3474.49+106.02+81.52+8.76 -> 3670.79 | O14: =SUM(C14:N14) -> 17612.94
A15: WFK | B15: Actual 2024 | O15: =SUM(C15:N15) -> 0
B16: Estimated | C16: 0 | D16: 0 | E16: 0 | F16: 0 | G16: 0 | H16: 0 | I16: 0 | J16: 0 | K16: 0 | L16: 0 | M16: 0 | N16: 0 | O16: =SUM(C16:N16) -> 0
B17: Budget | O17: =SUM(C17:N17) -> 0
B18: Actual | G18: =25.29+11.6+15.55+269.27+17.33+80.63+60.47 -> 480.14 | O18: =SUM(C18:N18) -> 480.14
A19: WAS (E02) | B19: Actual 2024 | O19: =SUM(C19:N19) -> 0
B20: Estimated | C20: 0 | D20: 0 | E20: 0 | F20: 0 | G20: 0 | H20: 0 | I20: 0 | J20: 0 | K20: 0 | L20: 0 | M20: 0 | N20: 0 | O20: =SUM(C20:N20) -> 0
B21: Budget | O21: =SUM(C21:N21) -> 0
B22: Actual | F22: =392.94+209.96 -> 602.9 | G22: 127.43 | O22: =SUM(C22:N22) -> 730.33
A23: Japan Promo | B23: Actual 2024 | O23: =SUM(C23:N23) -> 0
B24: Estimated | C24: 0 | D24: 0 | E24: 0 | F24: 0 | G24: 0 | H24: 0 | I24: 0 | J24: 0 | K24: 0 | L24: 0 | M24: 0 | N24: 0 | O24: =SUM(C24:N24) -> 0
B25: Budget | O25: =SUM(C25:N25) -> 0
B26: Actual | F26: =567.04+95.44+701.02+201.55 -> 1565.05 | G26: =27.35+220.94+36.65+258.62+81.65+393.64 -> 1018.85 | K26: =250.03 -> 250.03 | O26: =SUM(C26:N26) -> 2833.93
A27: May Day (E06) | B27: Actual 2024 | O27: =SUM(C27:N27) -> 0
B28: Estimated | C28: 0 | D28: 0 | E28: 0 | F28: 0 | G28: 0 | H28: 0 | I28: 0 | J28: 0 | K28: 0 | L28: 0 | M28: 0 | N28: 0 | O28: =SUM(C28:N28) -> 0
B29: Budget | O29: =SUM(C29:N29) -> 0
B30: Actual | F30: 205.47 | O30: =SUM(C30:N30) -> 205.47
A31: 4th of July (E04) | B31: Actual 2024 | O31: =SUM(C31:N31) -> 0
B32: Estimated | C32: 0 | D32: 0 | E32: 0 | F32: 0 | G32: 0 | H32: 0 | I32: 0 | J32: 0 | K32: 0 | L32: 0 | M32: 0 | N32: 0 | O32: =SUM(C32:N32) -> 0
B33: Budget | O33: =SUM(C33:N33) -> 0
B34: Actual | O34: =SUM(C34:N34) -> 0
A35: Kamehaha Parade | B35: Actual 2024 | O35: =SUM(C35:N35) -> 0
B36: Estimated | C36: 0 | D36: 0 | E36: 0 | F36: 0 | G36: 0 | H36: 0 | I36: 0 | J36: 0 | K36: 0 | L36: 0 | M36: 0 | N36: 0 | O36: =SUM(C36:N36) -> 0
B37: Budget | O37: =SUM(C37:N37) -> 0
B38: Actual | G38: =100+94.67 -> 194.67 | H38: 1987.16 | O38: =SUM(C38:N38) -> 2181.83
A39: KCCN BDAY BAsh | B39: Actual 2024 | O39: =SUM(C39:N39) -> 0
B40: Estimated | C40: 0 | D40: 0 | E40: 0 | F40: 0 | G40: 0 | H40: 0 | I40: 0 | J40: 0 | K40: 0 | L40: 0 | M40: 0 | N40: 0 | O40: =SUM(C40:N40) -> 0
B41: Budget | O41: =SUM(C41:N41) -> 0
B42: Actual | J42: =23.69+523.48+77.75+42.47+5.63 -> 673.02 | O42: =SUM(C42:N42) -> 673.02
A43: Mahalo Month | B43: Actual 2024 | O43: =SUM(C43:N43) -> 0
B44: Estimated | C44: 0 | D44: 0 | E44: 0 | F44: 0 | G44: 0 | H44: 0 | I44: 0 | J44: 0 | K44: 0 | L44: 0 | M44: 0 | N44: 0 | O44: =SUM(C44:N44) -> 0
B45: Budget | O45: =SUM(C45:N45) -> 0
B46: Actual | K46: 308.81 | O46: =SUM(C46:N46) -> 308.81
A47: Ohana Club (E08) | B47: Actual 2024 | O47: =SUM(C47:N47) -> 0
B48: Estimated | C48: 0 | D48: 0 | E48: 0 | F48: 0 | G48: 0 | H48: 0 | I48: 0 | J48: 0 | K48: 0 | L48: 0 | M48: 0 | N48: 0 | O48: =SUM(C48:N48) -> 0
B49: Budget | O49: =SUM(C49:N49) -> 0
B50: Actual | L50: =1038.74+349.45+910.47+101.21-127.75+29.6 -> 2301.72 | O50: =SUM(C50:N50) -> 2301.72
B51: Actual 2024 | O51: =SUM(C51:N51) -> 0
B52: Estimated | C52: 0 | D52: 0 | E52: 0 | F52: 0 | G52: 0 | H52: 0 | I52: 0 | J52: 0 | K52: 0 | L52: 0 | M52: 0 | N52: 0 | O52: =SUM(C52:N52) -> 0
B53: Budget | O53: =SUM(C53:N53) -> 0
B54: Actual | O54: =SUM(C54:N54) -> 0
B55: Actual 2024 | O55: =SUM(C55:N55) -> 0
B56: Estimated | C56: 0 | D56: 0 | E56: 0 | F56: 0 | G56: 0 | H56: 0 | I56: 0 | J56: 0 | K56: 0 | L56: 0 | M56: 0 | N56: 0 | O56: =SUM(C56:N56) -> 0
B57: Budget | O57: =SUM(C57:N57) -> 0
B58: Actual | O58: =SUM(C58:N58) -> 0
B59: Actual 2024 | O59: =SUM(C59:N59) -> 0
B60: Estimated | C60: 0 | D60: 0 | E60: 0 | F60: 0 | G60: 0 | H60: 0 | I60: 0 | J60: 0 | K60: 0 | L60: 0 | M60: 0 | N60: 0 | O60: =SUM(C60:N60) -> 0
B61: Budget | O61: =SUM(C61:N61) -> 0
B62: Actual | O62: =SUM(C62:N62) -> 0
B63: Actual 2024 | O63: =SUM(C63:N63) -> 0
B64: Estimated | C64: 0 | D64: 0 | E64: 0 | F64: 0 | G64: 0 | H64: 0 | I64: 0 | J64: 0 | K64: 0 | L64: 0 | M64: 0 | N64: 0 | O64: =SUM(C64:N64) -> 0
B65: Budget | O65: =SUM(C65:N65) -> 0
B66: Actual | O66: =SUM(C66:N66) -> 0
B67: Actual 2024 | O67: =SUM(C67:N67) -> 0
B68: Estimated | C68: 0 | D68: 0 | E68: 0 | F68: 0 | G68: 0 | H68: 0 | I68: 0 | J68: 0 | K68: 0 | L68: 0 | M68: 0 | N68: 0 | O68: =SUM(C68:N68) -> 0
B69: Budget | O69: =SUM(C69:N69) -> 0
B70: Actual | O70: =SUM(C70:N70) -> 0
B71: Actual 2024 | O71: =SUM(C71:N71) -> 0
B72: Estimated | C72: 0 | D72: 0 | E72: 0 | F72: 0 | G72: 0 | H72: 0 | I72: 0 | J72: 0 | K72: 0 | L72: 0 | M72: 0 | N72: 0 | O72: =SUM(C72:N72) -> 0
B73: Budget | O73: =SUM(C73:N73) -> 0
B74: Actual | O74: =SUM(C74:N74) -> 0
B75: Actual 2024 | O75: =SUM(C75:N75) -> 0
B76: Estimated | C76: 0 | D76: 0 | E76: 0 | F76: 0 | G76: 0 | H76: 0 | I76: 0 | J76: 0 | K76: 0 | L76: 0 | M76: 0 | N76: 0 | O76: =SUM(C76:N76) -> 0
B77: Budget | O77: =SUM(C77:N77) -> 0
B78: Actual | O78: =SUM(C78:N78) -> 0
B79: Actual 2024 | O79: =SUM(C79:N79) -> 0
B80: Estimated | C80: 0 | D80: 0 | E80: 0 | F80: 0 | G80: 0 | H80: 0 | I80: 0 | J80: 0 | K80: 0 | L80: 0 | M80: 0 | N80: 0 | O80: =SUM(C80:N80) -> 0
B81: Budget | O81: =SUM(C81:N81) -> 0
B82: Actual | O82: =SUM(C82:N82) -> 0
B83: Actual 2024 | O83: =SUM(C83:N83) -> 0
B84: Estimated | C84: 0 | D84: 0 | E84: 0 | F84: 0 | G84: 0 | H84: 0 | I84: 0 | J84: 0 | K84: 0 | L84: 0 | M84: 0 | N84: 0 | O84: =SUM(C84:N84) -> 0
B85: Budget | O85: =SUM(C85:N85) -> 0
B86: Actual | O86: =SUM(C86:N86) -> 0
B87: Actual 2024 | O87: =SUM(C87:N87) -> 0
B88: Estimated | C88: 0 | D88: 0 | E88: 0 | F88: 0 | G88: 0 | H88: 0 | I88: 0 | J88: 0 | K88: 0 | L88: 0 | M88: 0 | N88: 0 | O88: =SUM(C88:N88) -> 0
B89: Budget | O89: =SUM(C89:N89) -> 0
B90: Actual | O90: =SUM(C90:N90) -> 0
B91: Actual 2024 | O91: =SUM(C91:N91) -> 0
B92: Estimated | C92: 0 | D92: 0 | E92: 0 | F92: 0 | G92: 0 | H92: 0 | I92: 0 | J92: 0 | K92: 0 | L92: 0 | M92: 0 | N92: 0 | O92: =SUM(C92:N92) -> 0
B93: Budget | O93: =SUM(C93:N93) -> 0
B94: Actual | O94: =SUM(C94:N94) -> 0
B95: Actual 2024 | O95: =SUM(C95:N95) -> 0
B96: Estimated | C96: 0 | D96: 0 | E96: 0 | F96: 0 | G96: 0 | H96: 0 | I96: 0 | J96: 0 | K96: 0 | L96: 0 | M96: 0 | N96: 0 | O96: =SUM(C96:N96) -> 0
B97: Budget | O97: =SUM(C97:N97) -> 0
B98: Actual | O98: =SUM(C98:N98) -> 0

Sheet 5200-510 Operating Materials
A1: 5200-510 Operating Materials (Consumables)
C2: January | D2: February | E2: March | F2: April | G2: May | H2: June | I2: July | J2: August | K2: September | L2: October | M2: November | N2: December | O2: Total
A3: TOTAL | B3: Actual 2024 | C3: =SUMIFS(C$11:C951,$B$11:$B951,"Actual 2024") -> 11179.59 | D3: =SUMIFS(D$11:D951,$B$11:$B951,"Actual 2024") -> 1172.82 | E3: =SUMIFS(E$11:E951,$B$11:$B951,"Actual 2024") -> 736.31 | F3: =SUMIFS(F$11:F951,$B$11:$B951,"Actual 2024") -> 664.21 | G3: =SUMIFS(G$11:G951,$B$11:$B951,"Actual 2024") -> 16420.22 | H3: =SUMIFS(H$11:H951,$B$11:$B951,"Actual 2024") -> 15007.29 | I3: =SUMIFS(I$11:I951,$B$11:$B951,"Actual 2024") -> 1207.31 | J3: =SUMIFS(J$11:J951,$B$11:$B951,"Actual 2024") -> 12974.18 | ... O3: =SUMIFS(O$11:O951,$B$11:$B951,"Actual 2024") -> 94546.77
B4: Estimated | C4: =SUMIFS(C$11:C951,$B$11:$B951,"Estimated") -> 10884.94 | D4: =SUMIFS(D$11:D951,$B$11:$B951,"Estimated") -> 2434.69 | E4: =SUMIFS(E$11:E951,$B$11:$B951,"Estimated") -> 16775 | F4: =SUMIFS(F$11:F951,$B$11:$B951,"Estimated") -> 1314 | G4: =SUMIFS(G$11:G951,$B$11:$B951,"Estimated") -> 3345 | H4: =SUMIFS(H$11:H951,$B$11:$B951,"Estimated") -> 15220 | I4: =SUMIFS(I$11:I951,$B$11:$B951,"Estimated") -> 1475 | J4: =SUMIFS(J$11:J951,$B$11:$B951,"Estimated") -> 14505 | ... O4: =SUMIFS(O$11:O951,$B$11:$B951,"Estimated") -> 100837.63 | Q4: =O4-O3 -> 6290.86
B5: Budget | C5: 10884.94 | D5: 2434.69 | E5: 16775 | F5: 1314 | G5: 3345 | H5: 15220 | I5: 1475 | J5: 14505 | K5: 31059 | L5: 2275 | M5: 775 | N5: 775 | O5: =SUM(C5:N5) -> 100837.63 | P5: 100837.63
B6: Actual | C6: =SUMIFS(C$11:C956,$B$11:$B956,"Actual") -> 44094.99 | D6: =SUMIFS(D$11:D956,$B$11:$B956,"Actual") -> 13689.27 | E6: =SUMIFS(E$11:E956,$B$11:$B956,"Actual") -> 18956.76 | F6: =SUMIFS(F$11:F956,$B$11:$B956,"Actual") -> 571.13 | G6: =SUMIFS(G$11:G956,$B$11:$B956,"Actual") -> 18214.76 | H6: =SUMIFS(H$11:H956,$B$11:$B956,"Actual") -> 4108.58 | I6: =SUMIFS(I$11:I956,$B$11:$B956,"Actual") -> 19645.82 | J6: =SUMIFS(J$11:J956,$B$11:$B956,"Actual") -> 30129.71 | ... O6: =SUMIFS(O$11:O956,$B$11:$B956,"Actual") -> 159620.39
B7: Budget Deficit/ Savings | C7: =C5-C6 -> -33210.05 | D7: =D5-D6 -> -11254.58 | E7: =E5-E6 -> -2181.76 | F7: =F5-F6 -> 742.87 | G7: =G5-G6 -> -14869.76 | H7: =H5-H6 -> 11111.42 | I7: =I5-I6 -> -18170.82 | J7: =J5-J6 -> -15624.71 | ... O7: =O5-O6 -> -58782.76
B8: Year to Date Spend | C8: =SUM($C6:C6) -> 44094.99 | D8: =SUM($C6:D6) -> 57784.26 | E8: =SUM($C6:E6) -> 76741.02 | F8: =SUM($C6:F6) -> 77312.15 | G8: =SUM($C6:G6) -> 95526.91 | H8: =SUM($C6:H6) -> 99635.49 | I8: =SUM($C6:I6) -> 119281.31 | J8: =SUM($C6:J6) -> 149411.02 | ... N8: =SUM($C6:N6) -> 159620.39 | O8: =O6 -> 159620.39
B9: YTD Excess From Budget | C9: =SUM($C5:C5)-C8 -> -33210.05 | D9: =SUM($C5:D5)-D8 -> -44464.63 | E9: =SUM($C5:E5)-E8 -> -46646.39 | F9: =SUM($C5:F5)-F8 -> -45903.52 | G9: =SUM($C5:G5)-G8 -> -60773.28 | H9: =SUM($C5:H5)-H8 -> -49661.86 | I9: =SUM($C5:I5)-I8 -> -67832.68 | J9: =SUM($C5:J5)-J8 -> -83457.39 | ... N9: =SUM($C5:N5)-N8 -> -58782.76
A11: Edward Enterprises Inc. (Rack Brochures) | B11: Actual 2024 | C11: 10795.81 | H11: 14445.02 | J11: 11230.36 | K11: 30214.64 | O11: =SUM(C11:N11) -> 66685.83
B12: Estimated | C12: 10109.94 | D12: 1659.69 | E12: 0 | F12: 539 | H12: 14445 | I12: 0 | J12: 11230 | K12: 30214 | L12: 0 | M12: 0 | N12: 0 | O12: =SUM(C12:N12) -> 68197.63
B13: Budget | O13: =SUM(C13:N13) -> 0
B14: Actual | C14: 43921.45 | D14: 13320.93 | F14: 539.27 | G14: 17873.09 | I14: 724.75 | J14: =1617.8+26586.38 -> 28204.18 | K14: =2062.83+7777.37 -> 9840.2 | O14: =SUM(C14:N14) -> 114423.87
A15: American Solutions for Businesss | B15: Actual 2024 | G15: 15390.57 | O15: =SUM(C15:N15) -> 15390.57
B16: Estimated | C16: 0 | D16: 0 | E16: 16000 | F16: 0 | G16: 0 | H16: 0 | I16: 0 | J16: 0 | K16: 0 | L16: 0 | M16: 0 | N16: 0 | O16: =SUM(C16:N16) -> 16000
B17: Budget | O17: =SUM(C17:N17) -> 0
B18: Actual | E18: 18837.69 | H18: 3275.39 | I18: =17680.62 -> 17680.62 | O18: =SUM(C18:N18) -> 39793.7
A19: Walmart | B19: Actual 2024 | D19: 103.05 | F19: 182.06 | H19: 50.71 | J19: 100.72 | L19: 188.63 | O19: =SUM(C19:N19) -> 625.17
B20: Estimated | C20: 75 | D20: 75 | E20: 75 | F20: 75 | G20: 75 | H20: 75 | I20: 75 | J20: 75 | K20: 75 | L20: 75 | M20: 75 | N20: 75 | O20: =SUM(C20:N20) -> 900
B21: Budget | C21: 75 | D21: 75 | E21: 75 | F21: 75 | G21: 75 | H21: 75 | I21: 75 | J21: 75 | K21: 75 | L21: 75 | M21: 75 | N21: 75 | O21: =SUM(C21:N21) -> 900
B22: Actual | C22: 46.81 | E22: 119.07 | H22: =35.64+106.03+3.52+157.45+24.46 -> 327.1 | I22: 52.32 | K22: 91.96 | O22: =SUM(C22:N22) -> 637.26
A23: Costco | B23: Actual 2024 | H23: 403.11 | J23: 76.49 | L23: 151.11 | O23: =SUM(C23:N23) -> 630.71
B24: Estimated | C24: 75 | D24: 75 | E24: 75 | F24: 75 | G24: 75 | H24: 75 | I24: 75 | J24: 75 | K24: 75 | L24: 75 | M24: 75 | N24: 75 | O24: =SUM(C24:N24) -> 900
B25: Budget | C25: 75 | D25: 75 | E25: 75 | F25: 75 | G25: 75 | H25: 75 | I25: 75 | J25: 75 | K25: 75 | L25: 75 | M25: 75 | N25: 75 | O25: =SUM(C25:N25) -> 900
B26: Actual | C26: 82.01 | G26: 106.3 | H26: =286.01 -> 286.01 | I26: 124.3 | K26: 83.72 | O26: =SUM(C26:N26) -> 682.34
A27: Foodland | B27: Actual 2024 | O27: =SUM(C27:N27) -> 0
B28: Estimated | C28: 25 | D28: 25 | E28: 25 | F28: 25 | G28: 25 | H28: 25 | I28: 25 | J28: 25 | K28: 25 | L28: 25 | M28: 25 | N28: 25 | O28: =SUM(C28:N28) -> 300
B29: Budget | O29: =SUM(C29:N29) -> 0
B30: Actual | O30: =SUM(C30:N30) -> 0
A31: BYUH Print Services | B31: Actual 2024 | C31: 383.78 | D31: 1069.77 | E31: 730.99 | F31: 451.82 | G31: 994.58 | H31: 108.45 | I31: 1186.38 | J31: 678.68 | K31: 1904.38 | L31: 785.35 | M31: 272.85 | O31: =SUM(C31:N31) -> 8567.03
B32: Estimated | C32: 600 | D32: 600 | E32: 600 | F32: 600 | G32: 600 | H32: 600 | I32: 600 | J32: 600 | K32: 600 | L32: 600 | M32: 600 | N32: 600 | O32: =SUM(C32:N32) -> 7200
B33: Budget | O33: =SUM(C33:N33) -> 0
B34: Actual | C34: 44.72 | D34: 62.43 | F34: 31.86 | G34: 77.01 | H34: =19.43+93.88 -> 113.31 | I34: =174.79+387.04+45.18 -> 607.01 | K34: 32.14 | O34: =SUM(C34:N34) -> 968.48
A35: Home Depot | B35: Actual 2024 | O35: =SUM(C35:N35) -> 0
B36: Estimated | C36: 0 | D36: 0 | E36: 0 | F36: 0 | G36: 0 | H36: 0 | I36: 0 | J36: 0 | K36: 0 | L36: 0 | M36: 0 | N36: 0 | O36: =SUM(C36:N36) -> 0
B37: Budget | O37: =SUM(C37:N37) -> 0
B38: Actual | O38: =SUM(C38:N38) -> 0
A39: Pioneer Ace Hardware | B39: Actual 2024 | F39: 8.37 | L39: 35.58 | O39: =SUM(C39:N39) -> 43.95
B40: Estimated | C40: 0 | D40: 0 | E40: 0 | F40: 0 | G40: 0 | H40: 0 | I40: 0 | J40: 0 | K40: 0 | L40: 0 | M40: 0 | N40: 0 | O40: =SUM(C40:N40) -> 0
B41: Budget | O41: =SUM(C41:N41) -> 0
B42: Actual | D42: 3.75 | K42: 10.46 | L42: 38.63 | O42: =SUM(C42:N42) -> 52.84
A43: Longs | B43: Actual 2024 | E43: 5.32 | L43: 24.51 | O43: =SUM(C43:N43) -> 29.83
B44: Estimated | C44: 0 | D44: 0 | E44: 0 | F44: 0 | G44: 0 | H44: 0 | I44: 0 | J44: 0 | K44: 0 | L44: 0 | M44: 0 | N44: 0 | O44: =SUM(C44:N44) -> 0
B45: Budget | O45: =SUM(C45:N45) -> 0
B46: Actual | I46: 10.46 | J46: 25.91 | O46: =SUM(C46:N46) -> 36.37
A47: ABC Store | B47: Actual 2024 | F47: 21.96 | O47: =SUM(C47:N47) -> 21.96
B48: Estimated | C48: 0 | D48: 0 | E48: 0 | F48: 0 | G48: 0 | H48: 0 | I48: 0 | J48: 0 | K48: 0 | L48: 0 | M48: 0 | N48: 0 | O48: =SUM(C48:N48) -> 0
B49: Budget | O49: =SUM(C49:N49) -> 0
B50: Actual | O50: =SUM(C50:N50) -> 0
A51: Amazon | B51: Actual 2024 | G51: 35.07 | I51: 20.93 | O51: =SUM(C51:N51) -> 56
B52: Estimated | C52: 0 | D52: 0 | E52: 0 | F52: 0 | G52: 0 | H52: 0 | I52: 0 | J52: 0 | K52: 0 | L52: 0 | M52: 0 | N52: 0 | O52: =SUM(C52:N52) -> 0
B53: Budget | O53: =SUM(C53:N53) -> 0
B54: Actual | D54: 192.62 | G54: =49.2+58.89 -> 108.09 | H54: 43.95 | I54: =39.13+45.08 -> 84.21 | J54: =485.87+520.59+19.05+147.6+14.2+600.54+38.82 -> 1826.67 | K54: 39.75 | L54: =23.14+7.49 -> 30.63 | O54: =SUM(C54:N54) -> 2325.92
A55: Japan Expo | B55: Actual 2024 | J55: 887.93 | O55: =SUM(C55:N55) -> 887.93
B56: Estimated | C56: 0 | D56: 0 | E56: 0 | F56: 0 | G56: 2500 | H56: 0 | I56: 0 | J56: 2500 | K56: 0 | L56: 0 | M56: 0 | N56: 0 | O56: =SUM(C56:N56) -> 5000
B57: Budget | J57: 1500 | O57: =SUM(C57:N57) -> 1500
B58: Actual | O58: =SUM(C58:N58) -> 0
A59: Loralei Gift Shop | B59: Actual 2024 | K59: 1000 | O59: =SUM(C59:N59) -> 1000
B60: Estimated | C60: 0 | D60: 0 | E60: 0 | F60: 0 | G60: 0 | H60: 0 | I60: 0 | J60: 0 | K60: 0 | L60: 0 | M60: 0 | N60: 0 | O60: =SUM(C60:N60) -> 0
B61: Budget | O61: =SUM(C61:N61) -> 0
B62: Actual | O62: =SUM(C62:N62) -> 0
A63: Japan Wireless | B63: Actual 2024 | K63: 70.28 | O63: =SUM(C63:N63) -> 70.28
B64: Estimated | C64: 0 | D64: 0 | E64: 0 | F64: 0 | G64: 70 | H64: 0 | I64: 0 | J64: 0 | K64: 70 | L64: 0 | M64: 0 | N64: 0 | O64: =SUM(C64:N64) -> 140
B65: Budget | O65: =SUM(C65:N65) -> 0
B66: Actual | O66: =SUM(C66:N66) -> 0
A67: BYUH Bookstore | B67: Actual 2024 | L67: 8.36 | M67: 23.34 | O67: =SUM(C67:N67) -> 31.7
B68: Estimated | C68: 0 | D68: 0 | E68: 0 | F68: 0 | G68: 0 | H68: 0 | I68: 0 | J68: 0 | K68: 0 | L68: 0 | M68: 0 | N68: 0 | O68: =SUM(C68:N68) -> 0
B69: Budget | O69: =SUM(C69:N69) -> 0
B70: Actual | O70: =SUM(C70:N70) -> 0
A71: Bedlam Zone | B71: Actual 2024 | L71: 455.5 | O71: =SUM(C71:N71) -> 455.5
B72: Estimated | C72: 0 | D72: 0 | E72: 0 | F72: 0 | G72: 0 | H72: 0 | I72: 0 | J72: 0 | K72: 0 | L72: 0 | M72: 0 | N72: 0 | O72: =SUM(C72:N72) -> 0
B73: Budget | O73: =SUM(C73:N73) -> 0
B74: Actual | O74: =SUM(C74:N74) -> 0
A75: Ross | B75: Actual 2024 | L75: 50.31 | O75: =SUM(C75:N75) -> 50.31
B76: Estimated | C76: 0 | D76: 0 | E76: 0 | F76: 0 | G76: 0 | H76: 0 | I76: 0 | J76: 0 | K76: 0 | L76: 0 | M76: 0 | N76: 0 | O76: =SUM(C76:N76) -> 0
B77: Budget | O77: =SUM(C77:N77) -> 0
B78: Actual | O78: =SUM(C78:N78) -> 0
A79: Ohana Club Printing | B79: Actual 2024 | O79: =SUM(C79:N79) -> 0
B80: Estimated | C80: 0 | D80: 0 | E80: 0 | F80: 0 | G80: 0 | H80: 0 | I80: 700 | J80: 0 | K80: 0 | L80: 1500 | M80: 0 | N80: 0 | O80: =SUM(C80:N80) -> 2200
B81: Budget | O81: =SUM(C81:N81) -> 0
B82: Actual | O82: =SUM(C82:N82) -> 0
A83: Fisher Hawaii | B83: Actual 2024 | O83: =SUM(C83:N83) -> 0
B84: Estimated | C84: 0 | D84: 0 | E84: 0 | F84: 0 | G84: 0 | H84: 0 | I84: 0 | J84: 0 | K84: 0 | L84: 0 | M84: 0 | N84: 0 | O84: =SUM(C84:N84) -> 0
B85: Budget | O85: =SUM(C85:N85) -> 0
B86: Actual | D86: 92.79 | J86: 72.95 | O86: =SUM(C86:N86) -> 165.74
A87: 808 E Network | B87: Actual 2024 | O87: =SUM(C87:N87) -> 0
B88: Estimated | C88: 0 | D88: 0 | E88: 0 | F88: 0 | G88: 0 | H88: 0 | I88: 0 | J88: 0 | K88: 0 | L88: 0 | M88: 0 | N88: 0 | O88: =SUM(C88:N88) -> 0
B89: Budget | O89: =SUM(C89:N89) -> 0
B90: Actual | D90: 16.75 | G90: =20.94+29.33 -> 50.27 | L90: 41.88 | O90: =SUM(C90:N90) -> 108.9
A91: Target | B91: Actual 2024 | O91: =SUM(C91:N91) -> 0
B92: Estimated | C92: 0 | D92: 0 | E92: 0 | F92: 0 | G92: 0 | H92: 0 | I92: 0 | J92: 0 | K92: 0 | L92: 0 | M92: 0 | N92: 0 | O92: =SUM(C92:N92) -> 0
B93: Budget | O93: =SUM(C93:N93) -> 0
B94: Actual | H94: 62.82 | O94: =SUM(C94:N94) -> 62.82
A95: Tif Honolulu Florist | B95: Actual 2024 | O95: =SUM(C95:N95) -> 0
B96: Estimated | C96: 0 | D96: 0 | E96: 0 | F96: 0 | G96: 0 | H96: 0 | I96: 0 | J96: 0 | K96: 0 | L96: 0 | M96: 0 | N96: 0 | O96: =SUM(C96:N96) -> 0
B97: Budget | O97: =SUM(C97:N97) -> 0
B98: Actual | I98: 219.74 | O98: =SUM(C98:N98) -> 219.74
A99: Signs Today | B99: Actual 2024 | O99: =SUM(C99:N99) -> 0
B100: Estimated | C100: 0 | D100: 0 | E100: 0 | F100: 0 | G100: 0 | H100: 0 | I100: 0 | J100: 0 | K100: 0 | L100: 0 | M100: 0 | N100: 0 | O100: =SUM(C100:N100) -> 0
B101: Budget | O101: =SUM(C101:N101) -> 0
...

Sheet 5201-510 Uniform
A1: 5201-510 Uniform
C2: January | D2: February | E2: March | F2: April | G2: May | H2: June | I2: July | J2: August | K2: September | L2: October | M2: November | N2: December | O2: Total
A3: TOTAL | B3: Actual 2024 | C3: =SUMIFS(C$11:C1000,$B$11:$B1000,"Actual 2024") -> 0 | D3: =SUMIFS(D$11:D1000,$B$11:$B1000,"Actual 2024") -> 360.23 | E3: =SUMIFS(E$11:E1000,$B$11:$B1000,"Actual 2024") -> 695.32 | F3: =SUMIFS(F$11:F1000,$B$11:$B1000,"Actual 2024") -> 0 | G3: =SUMIFS(G$11:G1000,$B$11:$B1000,"Actual 2024") -> 85.42 | H3: =SUMIFS(H$11:H1000,$B$11:$B1000,"Actual 2024") -> 0 | I3: =SUMIFS(I$11:I1000,$B$11:$B1000,"Actual 2024") -> 0 | J3: =SUMIFS(J$11:J1000,$B$11:$B1000,"Actual 2024") -> 0 | ... O3: =SUMIFS(O$11:O1000,$B$11:$B1000,"Actual 2024") -> 1140.97
B4: Estimated | C4: =SUMIFS(C$11:C1000,$B$11:$B1000,"Estimated") -> 3500 | D4: =SUMIFS(D$11:D1000,$B$11:$B1000,"Estimated") -> 0 | E4: =SUMIFS(E$11:E1000,$B$11:$B1000,"Estimated") -> 0 | F4: =SUMIFS(F$11:F1000,$B$11:$B1000,"Estimated") -> 0 | G4: =SUMIFS(G$11:G1000,$B$11:$B1000,"Estimated") -> 0 | H4: =SUMIFS(H$11:H1000,$B$11:$B1000,"Estimated") -> 0 | I4: =SUMIFS(I$11:I1000,$B$11:$B1000,"Estimated") -> 0 | J4: =SUMIFS(J$11:J1000,$B$11:$B1000,"Estimated") -> 0 | ... O4: =SUMIFS(O$11:O1000,$B$11:$B1000,"Estimated") -> 3500
B5: Budget | C5: 0 | D5: 0 | E5: 0 | F5: 0 | G5: 0 | H5: 0 | I5: 0 | J5: 0 | K5: 0 | L5: 0 | M5: 0 | N5: 0 | O5: =SUM(C5:N5) -> 0 | P5: 0
B6: Actual | C6: =SUMIFS(C$11:C1005,$B$11:$B1005,"Actual") -> 0 | D6: =SUMIFS(D$11:D1005,$B$11:$B1005,"Actual") -> 0 | E6: =SUMIFS(E$11:E1005,$B$11:$B1005,"Actual") -> 0 | F6: =SUMIFS(F$11:F1005,$B$11:$B1005,"Actual") -> 1593.8 | G6: =SUMIFS(G$11:G1005,$B$11:$B1005,"Actual") -> 0 | H6: =SUMIFS(H$11:H1005,$B$11:$B1005,"Actual") -> 0 | I6: =SUMIFS(I$11:I1005,$B$11:$B1005,"Actual") -> 0 | J6: =SUMIFS(J$11:J1005,$B$11:$B1005,"Actual") -> 93.76 | ... O6: =SUMIFS(O$11:O1005,$B$11:$B1005,"Actual") -> 1687.56
B7: Budget Deficit/ Savings | C7: =C5-C6 -> 0 | D7: =D5-D6 -> 0 | E7: =E5-E6 -> 0 | F7: =F5-F6 -> -1593.8 | G7: =G5-G6 -> 0 | H7: =H5-H6 -> 0 | I7: =I5-I6 -> 0 | J7: =J5-J6 -> -93.76 | ... O7: =O5-O6 -> -1687.56
B8: Year to Date Spend | C8: =SUM($C6:C6) -> 0 | D8: =SUM($C6:D6) -> 0 | E8: =SUM($C6:E6) -> 0 | F8: =SUM($C6:F6) -> 1593.8 | G8: =SUM($C6:G6) -> 1593.8 | H8: =SUM($C6:H6) -> 1593.8 | I8: =SUM($C6:I6) -> 1593.8 | J8: =SUM($C6:J6) -> 1687.56 | ... N8: =SUM($C6:N6) -> 1687.56 | O8: =O6 -> 1687.56
B9: YTD Excess From Budget | C9: =SUM($C5:C5)-C8 -> 0 | D9: =SUM($C5:D5)-D8 -> 0 | E9: =SUM($C5:E5)-E8 -> 0 | F9: =SUM($C5:F5)-F8 -> -1593.8 | G9: =SUM($C5:G5)-G8 -> -1593.8 | H9: =SUM($C5:H5)-H8 -> -1593.8 | I9: =SUM($C5:I5)-I8 -> -1593.8 | J9: =SUM($C5:J5)-J8 -> -1687.56 | ... N9: =SUM($C5:N5)-N8 -> -1687.56
A11: Waiono Designs LLC | B11: Actual 2024 | D11: 360.23 | E11: 695.32 | G11: 85.42 | O11: =SUM(C11:N11) -> 1140.97
B12: Estimated | C12: 3500 | D12: 0 | E12: 0 | F12: 0 | G12: 0 | H12: 0 | I12: 0 | J12: 0 | K12: 0 | L12: 0 | M12: 0 | N12: 0 | O12: =SUM(C12:N12) -> 3500
B13: Budget | O13: =SUM(C13:N13) -> 0
B14: Actual | F14: 1593.8 | J14: 93.76 | O14: =SUM(C14:N14) -> 1687.56
B15: Actual 2024 | O15: =SUM(C15:N15) -> 0
B16: Estimated | C16: 0 | D16: 0 | E16: 0 | F16: 0 | G16: 0 | H16: 0 | I16: 0 | J16: 0 | K16: 0 | L16: 0 | M16: 0 | N16: 0 | O16: =SUM(C16:N16) -> 0
B17: Budget | O17: =SUM(C17:N17) -> 0
B18: Actual | O18: =SUM(C18:N18) -> 0
B19: Actual 2024 | O19: =SUM(C19:N19) -> 0
B20: Estimated | C20: 0 | D20: 0 | E20: 0 | F20: 0 | G20: 0 | H20: 0 | I20: 0 | J20: 0 | K20: 0 | L20: 0 | M20: 0 | N20: 0 | O20: =SUM(C20:N20) -> 0
B21: Budget | O21: =SUM(C21:N21) -> 0
B22: Actual | O22: =SUM(C22:N22) -> 0
B23: Actual 2024 | O23: =SUM(C23:N23) -> 0
B24: Estimated | C24: 0 | D24: 0 | E24: 0 | F24: 0 | G24: 0 | H24: 0 | I24: 0 | J24: 0 | K24: 0 | L24: 0 | M24: 0 | N24: 0 | O24: =SUM(C24:N24) -> 0
B25: Budget | O25: =SUM(C25:N25) -> 0
B26: Actual | O26: =SUM(C26:N26) -> 0
B27: Actual 2024 | O27: =SUM(C27:N27) -> 0
B28: Estimated | C28: 0 | D28: 0 | E28: 0 | F28: 0 | G28: 0 | H28: 0 | I28: 0 | J28: 0 | K28: 0 | L28: 0 | M28: 0 | N28: 0 | O28: =SUM(C28:N28) -> 0
B29: Budget | O29: =SUM(C29:N29) -> 0
B30: Actual | O30: =SUM(C30:N30) -> 0
B31: Actual 2024 | O31: =SUM(C31:N31) -> 0
B32: Estimated | C32: 0 | D32: 0 | E32: 0 | F32: 0 | G32: 0 | H32: 0 | I32: 0 | J32: 0 | K32: 0 | L32: 0 | M32: 0 | N32: 0 | O32: =SUM(C32:N32) -> 0
B33: Budget | O33: =SUM(C33:N33) -> 0
B34: Actual | O34: =SUM(C34:N34) -> 0
B35: Actual 2024 | O35: =SUM(C35:N35) -> 0
B36: Estimated | C36: 0 | D36: 0 | E36: 0 | F36: 0 | G36: 0 | H36: 0 | I36: 0 | J36: 0 | K36: 0 | L36: 0 | M36: 0 | N36: 0 | O36: =SUM(C36:N36) -> 0
B37: Budget | O37: =SUM(C37:N37) -> 0
B38: Actual | O38: =SUM(C38:N38) -> 0
B39: Actual 2024 | O39: =SUM(C39:N39) -> 0
B40: Estimated | C40: 0 | D40: 0 | E40: 0 | F40: 0 | G40: 0 | H40: 0 | I40: 0 | J40: 0 | K40: 0 | L40: 0 | M40: 0 | N40: 0 | O40: =SUM(C40:N40) -> 0
B41: Budget | O41: =SUM(C41:N41) -> 0
B42: Actual | O42: =SUM(C42:N42) -> 0
B43: Actual 2024 | O43: =SUM(C43:N43) -> 0
B44: Estimated | C44: 0 | D44: 0 | E44: 0 | F44: 0 | G44: 0 | H44: 0 | I44: 0 | J44: 0 | K44: 0 | L44: 0 | M44: 0 | N44: 0 | O44: =SUM(C44:N44) -> 0
B45: Budget | O45: =SUM(C45:N45) -> 0
B46: Actual | O46: =SUM(C46:N46) -> 0
B47: Actual 2024 | O47: =SUM(C47:N47) -> 0
B48: Estimated | C48: 0 | D48: 0 | E48: 0 | F48: 0 | G48: 0 | H48: 0 | I48: 0 | J48: 0 | K48: 0 | L48: 0 | M48: 0 | N48: 0 | O48: =SUM(C48:N48) -> 0
B49: Budget | O49: =SUM(C49:N49) -> 0
B50: Actual | O50: =SUM(C50:N50) -> 0
B51: Actual 2024 | O51: =SUM(C51:N51) -> 0
B52: Estimated | C52: 0 | D52: 0 | E52: 0 | F52: 0 | G52: 0 | H52: 0 | I52: 0 | J52: 0 | K52: 0 | L52: 0 | M52: 0 | N52: 0 | O52: =SUM(C52:N52) -> 0
B53: Budget | O53: =SUM(C53:N53) -> 0
B54: Actual | O54: =SUM(C54:N54) -> 0
B55: Actual 2024 | O55: =SUM(C55:N55) -> 0
B56: Estimated | C56: 0 | D56: 0 | E56: 0 | F56: 0 | G56: 0 | H56: 0 | I56: 0 | J56: 0 | K56: 0 | L56: 0 | M56: 0 | N56: 0 | O56: =SUM(C56:N56) -> 0
B57: Budget | O57: =SUM(C57:N57) -> 0
B58: Actual | O58: =SUM(C58:N58) -> 0
B59: Actual 2024 | O59: =SUM(C59:N59) -> 0
B60: Estimated | C60: 0 | D60: 0 | E60: 0 | F60: 0 | G60: 0 | H60: 0 | I60: 0 | J60: 0 | K60: 0 | L60: 0 | M60: 0 | N60: 0 | O60: =SUM(C60:N60) -> 0
B61: Budget | O61: =SUM(C61:N61) -> 0
B62: Actual | O62: =SUM(C62:N62) -> 0
B63: Actual 2024 | O63: =SUM(C63:N63) -> 0
B64: Estimated | C64: 0 | D64: 0 | E64: 0 | F64: 0 | G64: 0 | H64: 0 | I64: 0 | J64: 0 | K64: 0 | L64: 0 | M64: 0 | N64: 0 | O64: =SUM(C64:N64) -> 0
B65: Budget | O65: =SUM(C65:N65) -> 0
B66: Actual | O66: =SUM(C66:N66) -> 0
B67: Actual 2024 | O67: =SUM(C67:N67) -> 0
B68: Estimated | C68: 0 | D68: 0 | E68: 0 | F68: 0 | G68: 0 | H68: 0 | I68: 0 | J68: 0 | K68: 0 | L68: 0 | M68: 0 | N68: 0 | O68: =SUM(C68:N68) -> 0
B69: Budget | O69: =SUM(C69:N69) -> 0
B70: Actual | O70: =SUM(C70:N70) -> 0
B71: Actual 2024 | O71: =SUM(C71:N71) -> 0
B72: Estimated | C72: 0 | D72: 0 | E72: 0 | F72: 0 | G72: 0 | H72: 0 | I72: 0 | J72: 0 | K72: 0 | L72: 0 | M72: 0 | N72: 0 | O72: =SUM(C72:N72) -> 0
B73: Budget | O73: =SUM(C73:N73) -> 0
B74: Actual | O74: =SUM(C74:N74) -> 0
B75: Actual 2024 | O75: =SUM(C75:N75) -> 0
B76: Estimated | C76: 0 | D76: 0 | E76: 0 | F76: 0 | G76: 0 | H76: 0 | I76: 0 | J76: 0 | K76: 0 | L76: 0 | M76: 0 | N76: 0 | O76: =SUM(C76:N76) -> 0
B77: Budget | O77: =SUM(C77:N77) -> 0
B78: Actual | O78: =SUM(C78:N78) -> 0
B79: Actual 2024 | O79: =SUM(C79:N79) -> 0
B80: Estimated | C80: 0 | D80: 0 | E80: 0 | F80: 0 | G80: 0 | H80: 0 | I80: 0 | J80: 0 | K80: 0 | L80: 0 | M80: 0 | N80: 0 | O80: =SUM(C80:N80) -> 0
B81: Budget | O81: =SUM(C81:N81) -> 0
B82: Actual | O82: =SUM(C82:N82) -> 0
B83: Actual 2024 | O83: =SUM(C83:N83) -> 0
B84: Estimated | C84: 0 | D84: 0 | E84: 0 | F84: 0 | G84: 0 | H84: 0 | I84: 0 | J84: 0 | K84: 0 | L84: 0 | M84: 0 | N84: 0 | O84: =SUM(C84:N84) -> 0
B85: Budget | O85: =SUM(C85:N85) -> 0
B86: Actual | O86: =SUM(C86:N86) -> 0
B87: Actual 2024 | O87: =SUM(C87:N87) -> 0
B88: Estimated | C88: 0 | D88: 0 | E88: 0 | F88: 0 | G88: 0 | H88: 0 | I88: 0 | J88: 0 | K88: 0 | L88: 0 | M88: 0 | N88: 0 | O88: =SUM(C88:N88) -> 0
B89: Budget | O89: =SUM(C89:N89) -> 0
B90: Actual | O90: =SUM(C90:N90) -> 0
B91: Actual 2024 | O91: =SUM(C91:N91) -> 0
B92: Estimated | C92: 0 | D92: 0 | E92: 0 | F92: 0 | G92: 0 | H92: 0 | I92: 0 | J92: 0 | K92: 0 | L92: 0 | M92: 0 | N92: 0 | O92: =SUM(C92:N92) -> 0
B93: Budget | O93: =SUM(C93:N93) -> 0
B94: Actual | O94: =SUM(C94:N94) -> 0
B95: Actual 2024 | O95: =SUM(C95:N95) -> 0
B96: Estimated | C96: 0 | D96: 0 | E96: 0 | F96: 0 | G96: 0 | H96: 0 | I96: 0 | J96: 0 | K96: 0 | L96: 0 | M96: 0 | N96: 0 | O96: =SUM(C96:N96) -> 0
B97: Budget | O97: =SUM(C97:N97) -> 0
B98: Actual | O98: =SUM(C98:N98) -> 0
B99: Actual 2024 | O99: =SUM(C99:N99) -> 0
B100: Estimated | C100: 0 | D100: 0 | E100: 0 | F100: 0 | G100: 0 | H100: 0 | I100: 0 | J100: 0 | K100: 0 | L100: 0 | M100: 0 | N100: 0 | O100: =SUM(C100:N100) -> 0
B101: Budget | O101: =SUM(C101:N101) -> 0
...

Sheet 5203-510 Furnishings
A1: 5203-510 Furnishings and Equipment
C2: January | D2: February | E2: March | F2: April | G2: May | H2: June | I2: July | J2: August | K2: September | L2: October | M2: November | N2: December | O2: Total
A3: TOTAL | B3: Actual 2024 | C3: 3692.5 | D3: =SUMIFS(D$11:D996,$B$11:$B996,"Actual 2024") -> 0 | E3: =SUMIFS(E$11:E996,$B$11:$B996,"Actual 2024") -> 0 | F3: =SUMIFS(F$11:F996,$B$11:$B996,"Actual 2024") -> 0 | G3: =SUMIFS(G$11:G996,$B$11:$B996,"Actual 2024") -> 0 | H3: =SUMIFS(H$11:H996,$B$11:$B996,"Actual 2024") -> 0 | I3: =SUMIFS(I$11:I996,$B$11:$B996,"Actual 2024") -> 0 | J3: =SUMIFS(J$11:J996,$B$11:$B996,"Actual 2024") -> 0 | K3: =SUMIFS(K$11:K996,$B$11:$B996,"Actual 2024") -> 0 | ... O3: =SUMIFS(O$11:O996,$B$11:$B996,"Actual 2024") -> 0
B4: Estimated | C4: =SUMIFS(C$11:C996,$B$11:$B996,"Estimated") -> 38895.53 | D4: =SUMIFS(D$11:D996,$B$11:$B996,"Estimated") -> 0 | E4: =SUMIFS(E$11:E996,$B$11:$B996,"Estimated") -> 0 | F4: =SUMIFS(F$11:F996,$B$11:$B996,"Estimated") -> 236.17 | G4: =SUMIFS(G$11:G996,$B$11:$B996,"Estimated") -> 0 | H4: =SUMIFS(H$11:H996,$B$11:$B996,"Estimated") -> 0 | I4: =SUMIFS(I$11:I996,$B$11:$B996,"Estimated") -> 0 | J4: =SUMIFS(J$11:J996,$B$11:$B996,"Estimated") -> 0 | ... O4: =SUMIFS(O$11:O996,$B$11:$B996,"Estimated") -> 39131.7
B5: Budget | C5: 0 | D5: 0 | E5: 0 | F5: 0 | G5: 0 | H5: 0 | I5: 0 | J5: 0 | K5: 0 | L5: 0 | M5: 0 | N5: 0 | O5: =SUM(C5:N5) -> 0 | P5: 0
B6: Actual | C6: =SUMIFS(C$11:C1001,$B$11:$B1001,"Actual") -> 0 | D6: =SUMIFS(D$11:D1001,$B$11:$B1001,"Actual") -> 0 | E6: =SUMIFS(E$11:E1001,$B$11:$B1001,"Actual") -> 40709.16 | F6: =SUMIFS(F$11:F1001,$B$11:$B1001,"Actual") -> 3858.19 | G6: =SUMIFS(G$11:G1001,$B$11:$B1001,"Actual") -> 243.55 | H6: =SUMIFS(H$11:H1001,$B$11:$B1001,"Actual") -> 0 | I6: =SUMIFS(I$11:I1001,$B$11:$B1001,"Actual") -> 54.69 | J6: =SUMIFS(J$11:J1001,$B$11:$B1001,"Actual") -> 28.26 | ... O6: =SUMIFS(O$11:O1001,$B$11:$B1001,"Actual") -> 44950.54
B7: Budget Deficit/ Savings | C7: =C5-C6 -> 0 | D7: =D5-D6 -> 0 | E7: =E5-E6 -> -40709.16 | F7: =F5-F6 -> -3858.19 | G7: =G5-G6 -> -243.55 | H7: =H5-H6 -> 0 | I7: =I5-I6 -> -54.69 | J7: =J5-J6 -> -28.26 | ... O7: =O5-O6 -> -44950.54
B8: Year to Date Spend | C8: =SUM($C6:C6) -> 0 | D8: =SUM($C6:D6) -> 0 | E8: =SUM($C6:E6) -> 40709.16 | F8: =SUM($C6:F6) -> 44567.35 | G8: =SUM($C6:G6) -> 44810.9 | H8: =SUM($C6:H6) -> 44810.9 | I8: =SUM($C6:I6) -> 44865.59 | J8: =SUM($C6:J6) -> 44893.85 | ... N8: =SUM($C6:N6) -> 44950.54 | O8: =O6 -> 44950.54
B9: YTD Excess From Budget | C9: =SUM($C5:C5)-C8 -> 0 | D9: =SUM($C5:D5)-D8 -> 0 | E9: =SUM($C5:E5)-E8 -> -40709.16 | F9: =SUM($C5:F5)-F8 -> -44567.35 | G9: =SUM($C5:G5)-G8 -> -44810.9 | H9: =SUM($C5:H5)-H8 -> -44810.9 | I9: =SUM($C5:I5)-I8 -> -44865.59 | J9: =SUM($C5:J5)-J8 -> -44893.85 | ... N9: =SUM($C5:N5)-N8 -> -44950.54
A11: Apple | B11: Actual 2024 | O11: =SUM(C11:N11) -> 0
B12: Estimated | C12: 0 | D12: 0 | E12: 0 | F12: 0 | G12: 0 | H12: 0 | I12: 0 | J12: 0 | K12: 0 | L12: 0 | M12: 0 | N12: 0 | O12: =SUM(C12:N12) -> 0
B13: Budget | O13: =SUM(C13:N13) -> 0
B14: Actual | O14: =SUM(C14:N14) -> 0
A15: B&H Photo | B15: Actual 2024 | O15: =SUM(C15:N15) -> 0
B16: Estimated | C16: 0 | D16: 0 | E16: 0 | F16: 0 | G16: 0 | H16: 0 | I16: 0 | J16: 0 | K16: 0 | L16: 0 | M16: 0 | N16: 0 | O16: =SUM(C16:N16) -> 0
B17: Budget | O17: =SUM(C17:N17) -> 0
B18: Actual | E18: 10502.39 | O18: =SUM(C18:N18) -> 10502.39
A19: DJI Drones | B19: Actual 2024 | O19: =SUM(C19:N19) -> 0
B20: Estimated | C20: 0 | D20: 0 | E20: 0 | F20: 0 | G20: 0 | H20: 0 | I20: 0 | J20: 0 | K20: 0 | L20: 0 | M20: 0 | N20: 0 | O20: =SUM(C20:N20) -> 0
B21: Budget | O21: =SUM(C21:N21) -> 0
B22: Actual | E22: 1147.41 | O22: =SUM(C22:N22) -> 1147.41
A23: Bestbuy | B23: Actual 2024 | O23: =SUM(C23:N23) -> 0
B24: Estimated | C24: 0 | D24: 0 | E24: 0 | F24: 0 | G24: 0 | H24: 0 | I24: 0 | J24: 0 | K24: 0 | L24: 0 | M24: 0 | N24: 0 | O24: =SUM(C24:N24) -> 0
B25: Budget | O25: =SUM(C25:N25) -> 0
B26: Actual | O26: =SUM(C26:N26) -> 0
A27: Amazon | B27: Actual 2024 | O27: =SUM(C27:N27) -> 0
B28: Estimated | C28: 0 | D28: 0 | E28: 0 | F28: 0 | G28: 0 | H28: 0 | I28: 0 | J28: 0 | K28: 0 | L28: 0 | M28: 0 | N28: 0 | O28: =SUM(C28:N28) -> 0
B29: Budget | O29: =SUM(C29:N29) -> 0
B30: Actual | E30: 28954.74 | F30: 3370.8 | G30: =36.64 -> 36.64 | J30: 28.26 | K30: 56.69 | O30: =SUM(C30:N30) -> 32447.13
A31: Walmart | B31: Actual 2024 | O31: =SUM(C31:N31) -> 0
B32: Estimated | C32: 0 | D32: 0 | E32: 0 | F32: 0 | G32: 0 | H32: 0 | I32: 0 | J32: 0 | K32: 0 | L32: 0 | M32: 0 | N32: 0 | O32: =SUM(C32:N32) -> 0
B33: Budget | O33: =SUM(C33:N33) -> 0
B34: Actual | I34: 54.69 | O34: =SUM(C34:N34) -> 54.69
A35: Aliexpress | B35: Actual 2024 | O35: =SUM(C35:N35) -> 0
B36: Estimated | C36: 0 | D36: 0 | E36: 0 | F36: 0 | G36: 0 | H36: 0 | I36: 0 | J36: 0 | K36: 0 | L36: 0 | M36: 0 | N36: 0 | O36: =SUM(C36:N36) -> 0
B37: Budget | O37: =SUM(C37:N37) -> 0
B38: Actual | O38: =SUM(C38:N38) -> 0
A39: Rode | B39: Actual 2024 | O39: =SUM(C39:N39) -> 0
B40: Estimated | C40: 0 | D40: 0 | E40: 0 | F40: 0 | G40: 0 | H40: 0 | I40: 0 | J40: 0 | K40: 0 | L40: 0 | M40: 0 | N40: 0 | O40: =SUM(C40:N40) -> 0
B41: Budget | O41: =SUM(C41:N41) -> 0
B42: Actual | O42: =SUM(C42:N42) -> 0
A43: RockNRoller | B43: Actual 2024 | O43: =SUM(C43:N43) -> 0
B44: Estimated | C44: 0 | D44: 0 | E44: 0 | F44: 0 | G44: 0 | H44: 0 | I44: 0 | J44: 0 | K44: 0 | L44: 0 | M44: 0 | N44: 0 | O44: =SUM(C44:N44) -> 0
B45: Budget | O45: =SUM(C45:N45) -> 0
B46: Actual | O46: =SUM(C46:N46) -> 0
A47: Came-TV | B47: Actual 2024 | O47: =SUM(C47:N47) -> 0
B48: Estimated | C48: 0 | D48: 0 | E48: 0 | F48: 0 | G48: 0 | H48: 0 | I48: 0 | J48: 0 | K48: 0 | L48: 0 | M48: 0 | N48: 0 | O48: =SUM(C48:N48) -> 0
B49: Budget | O49: =SUM(C49:N49) -> 0
B50: Actual | O50: =SUM(C50:N50) -> 0
A51: Content Creation Team (NON CAP-EX Proposed Purchases) | B51: Actual 2024 | O51: =SUM(C51:N51) -> 0
B52: Estimated | C52: 19546.8 | D52: 0 | E52: 0 | F52: 0 | G52: 0 | H52: 0 | I52: 0 | J52: 0 | K52: 0 | L52: 0 | M52: 0 | N52: 0 | O52: =SUM(C52:N52) -> 19546.8
B53: Budget | O53: =SUM(C53:N53) -> 0
B54: Actual | O54: =SUM(C54:N54) -> 0
A55: Content Creation Team (CAP-EX Proposed Purchases) | B55: Actual 2024 | O55: =SUM(C55:N55) -> 0
B56: Estimated | C56: 19348.73 | D56: 0 | E56: 0 | F56: 0 | G56: 0 | H56: 0 | I56: 0 | J56: 0 | K56: 0 | L56: 0 | M56: 0 | N56: 0 | O56: =SUM(C56:N56) -> 19348.73
B57: Budget | O57: =SUM(C57:N57) -> 0
B58: Actual | O58: =SUM(C58:N58) -> 0
A59: Jason Cases | B59: Actual 2024 | O59: =SUM(C59:N59) -> 0
B60: Estimated | C60: 0 | D60: 0 | E60: 0 | F60: 0 | G60: 0 | H60: 0 | I60: 0 | J60: 0 | K60: 0 | L60: 0 | M60: 0 | N60: 0 | O60: =SUM(C60:N60) -> 0
B61: Budget | O61: =SUM(C61:N61) -> 0
B62: Actual | O62: =SUM(C62:N62) -> 0
A63: Lens Rental | B63: Actual 2024 | O63: =SUM(C63:N63) -> 0
B64: Estimated | C64: 0 | D64: 0 | E64: 0 | F64: 236.17 | G64: 0 | H64: 0 | I64: 0 | J64: 0 | K64: 0 | L64: 0 | M64: 0 | N64: 0 | O64: =SUM(C64:N64) -> 236.17
B65: Budget | O65: =SUM(C65:N65) -> 0
B66: Actual | G66: =206.91 -> 206.91 | O66: =SUM(C66:N66) -> 206.91
A67: Paypal | B67: Actual 2024 | O67: =SUM(C67:N67) -> 0
B68: Estimated | C68: 0 | D68: 0 | E68: 0 | F68: 0 | G68: 0 | H68: 0 | I68: 0 | J68: 0 | K68: 0 | L68: 0 | M68: 0 | N68: 0 | O68: =SUM(C68:N68) -> 0
B69: Budget | O69: =SUM(C69:N69) -> 0
B70: Actual | O70: =SUM(C70:N70) -> 0
A71: GoPro | B71: Actual 2024 | O71: =SUM(C71:N71) -> 0
B72: Estimated | C72: 0 | D72: 0 | E72: 0 | F72: 0 | G72: 0 | H72: 0 | I72: 0 | J72: 0 | K72: 0 | L72: 0 | M72: 0 | N72: 0 | O72: =SUM(C72:N72) -> 0
B73: Budget | O73: =SUM(C73:N73) -> 0
B74: Actual | O74: =SUM(C74:N74) -> 0
A75: Costco | B75: Actual 2024 | O75: =SUM(C75:N75) -> 0
B76: Estimated | C76: 0 | D76: 0 | E76: 0 | F76: 0 | G76: 0 | H76: 0 | I76: 0 | J76: 0 | K76: 0 | L76: 0 | M76: 0 | N76: 0 | O76: =SUM(C76:N76) -> 0
B77: Budget | O77: =SUM(C77:N77) -> 0
B78: Actual | E78: 104.62 | F78: 344.49 | O78: =SUM(C78:N78) -> 449.11
A79: Instacart | B79: Actual 2024 | O79: =SUM(C79:N79) -> 0
B80: Estimated | C80: 0 | D80: 0 | E80: 0 | F80: 0 | G80: 0 | H80: 0 | I80: 0 | J80: 0 | K80: 0 | L80: 0 | M80: 0 | N80: 0 | O80: =SUM(C80:N80) -> 0
B81: Budget | O81: =SUM(C81:N81) -> 0
B82: Actual | F82: 142.9 | O82: =SUM(C82:N82) -> 142.9
B83: Actual 2024 | O83: =SUM(C83:N83) -> 0
B84: Estimated | C84: 0 | D84: 0 | E84: 0 | F84: 0 | G84: 0 | H84: 0 | I84: 0 | J84: 0 | K84: 0 | L84: 0 | M84: 0 | N84: 0 | O84: =SUM(C84:N84) -> 0
B85: Budget | O85: =SUM(C85:N85) -> 0
B86: Actual | O86: =SUM(C86:N86) -> 0
B87: Actual 2024 | O87: =SUM(C87:N87) -> 0
B88: Estimated | C88: 0 | D88: 0 | E88: 0 | F88: 0 | G88: 0 | H88: 0 | I88: 0 | J88: 0 | K88: 0 | L88: 0 | M88: 0 | N88: 0 | O88: =SUM(C88:N88) -> 0
B89: Budget | O89: =SUM(C89:N89) -> 0
B90: Actual | O90: =SUM(C90:N90) -> 0
B91: Actual 2024 | O91: =SUM(C91:N91) -> 0
B92: Estimated | C92: 0 | D92: 0 | E92: 0 | F92: 0 | G92: 0 | H92: 0 | I92: 0 | J92: 0 | K92: 0 | L92: 0 | M92: 0 | N92: 0 | O92: =SUM(C92:N92) -> 0
B93: Budget | O93: =SUM(C93:N93) -> 0
B94: Actual | O94: =SUM(C94:N94) -> 0
B95: Actual 2024 | O95: =SUM(C95:N95) -> 0
B96: Estimated | C96: 0 | D96: 0 | E96: 0 | F96: 0 | G96: 0 | H96: 0 | I96: 0 | J96: 0 | K96: 0 | L96: 0 | M96: 0 | N96: 0 | O96: =SUM(C96:N96) -> 0
B97: Budget | O97: =SUM(C97:N97) -> 0
B98: Actual | O98: =SUM(C98:N98) -> 0
B99: Actual 2024 | O99: =SUM(C99:N99) -> 0
B100: Estimated | C100: 0 | D100: 0 | E100: 0 | F100: 0 | G100: 0 | H100: 0 | I100: 0 | J100: 0 | K100: 0 | L100: 0 | M100: 0 | N100: 0 | O100: =SUM(C100:N100) -> 0
B101: Budget | O101: =SUM(C101:N101) -> 0
...

Sheet 5312-510 General Contracted 
A1: 5312-510 Professional Fees
C2: January | D2: February | E2: March | F2: April | G2: May | H2: June | I2: July | J2: August | K2: September | L2: October | M2: November | N2: December | O2: Total
A3: TOTAL | B3: Actual 2024 | C3: =SUMIFS(C$11:C992,$B$11:$B992,"Actual 2024") -> 0 | D3: =SUMIFS(D$11:D992,$B$11:$B992,"Actual 2024") -> 0 | E3: =SUMIFS(E$11:E992,$B$11:$B992,"Actual 2024") -> 0 | F3: =SUMIFS(F$11:F992,$B$11:$B992,"Actual 2024") -> 0 | G3: =SUMIFS(G$11:G992,$B$11:$B992,"Actual 2024") -> 0 | H3: =SUMIFS(H$11:H992,$B$11:$B992,"Actual 2024") -> 0 | I3: =SUMIFS(I$11:I992,$B$11:$B992,"Actual 2024") -> 0 | J3: =SUMIFS(J$11:J992,$B$11:$B992,"Actual 2024") -> 0 | ... O3: =SUMIFS(O$11:O992,$B$11:$B992,"Actual 2024") -> 21173.35 | P3: 21233.35
B4: Estimated | C4: =SUMIFS(C$11:C992,$B$11:$B992,"Estimated") -> 0 | D4: =SUMIFS(D$11:D992,$B$11:$B992,"Estimated") -> 0 | E4: =SUMIFS(E$11:E992,$B$11:$B992,"Estimated") -> 0 | F4: =SUMIFS(F$11:F992,$B$11:$B992,"Estimated") -> 0 | G4: =SUMIFS(G$11:G992,$B$11:$B992,"Estimated") -> 0 | H4: =SUMIFS(H$11:H992,$B$11:$B992,"Estimated") -> 0 | I4: =SUMIFS(I$11:I992,$B$11:$B992,"Estimated") -> 0 | J4: =SUMIFS(J$11:J992,$B$11:$B992,"Estimated") -> 0 | ... O4: =SUMIFS(O$11:O992,$B$11:$B992,"Estimated") -> 0
B5: Budget | C5: 0 | D5: 0 | E5: 0 | F5: 0 | G5: 0 | H5: 0 | I5: 0 | J5: 0 | K5: 0 | L5: 0 | M5: 0 | N5: 0 | O5: =SUM(C5:N5) -> 0 | P5: 0
B6: Actual | C6: =SUMIFS(C$11:C997,$B$11:$B997,"Actual") -> 0 | D6: =SUMIFS(D$11:D997,$B$11:$B997,"Actual") -> 0 | E6: =SUMIFS(E$11:E997,$B$11:$B997,"Actual") -> 0 | F6: =SUMIFS(F$11:F997,$B$11:$B997,"Actual") -> 0 | G6: =SUMIFS(G$11:G997,$B$11:$B997,"Actual") -> 0 | H6: =SUMIFS(H$11:H997,$B$11:$B997,"Actual") -> 0 | I6: =SUMIFS(I$11:I997,$B$11:$B997,"Actual") -> 0 | J6: =SUMIFS(J$11:J997,$B$11:$B997,"Actual") -> 0 | ... O6: =SUMIFS(O$11:O997,$B$11:$B997,"Actual") -> 0
B7: Budget Deficit/ Savings | C7: =C5-C6 -> 0 | D7: =D5-D6 -> 0 | E7: =E5-E6 -> 0 | F7: =F5-F6 -> 0 | G7: =G5-G6 -> 0 | H7: =H5-H6 -> 0 | I7: =I5-I6 -> 0 | J7: =J5-J6 -> 0 | ... O7: =O5-O6 -> 0
B8: Year to Date Spend | C8: =SUM($C6:C6) -> 0 | D8: =SUM($C6:D6) -> 0 | E8: =SUM($C6:E6) -> 0 | F8: =SUM($C6:F6) -> 0 | G8: =SUM($C6:G6) -> 0 | H8: =SUM($C6:H6) -> 0 | I8: =SUM($C6:I6) -> 0 | J8: =SUM($C6:J6) -> 0 | ... N8: =SUM($C6:N6) -> 0 | O8: =O6 -> 0
B9: YTD Excess From Budget | C9: =SUM($C5:C5)-C8 -> 0 | D9: =SUM($C5:D5)-D8 -> 0 | E9: =SUM($C5:E5)-E8 -> 0 | F9: =SUM($C5:F5)-F8 -> 0 | G9: =SUM($C5:G5)-G8 -> 0 | H9: =SUM($C5:H5)-H8 -> 0 | I9: =SUM($C5:I5)-I8 -> 0 | J9: =SUM($C5:J5)-J8 -> 0 | ... N9: =SUM($C5:N5)-N8 -> 0
A11: The Green Band LLC | B11: Actual 2024 | K11: 6240 | L11: 6240 | O11: =SUM(C11:N11) -> 12480
B12: Estimated | C12: 0 | D12: 0 | E12: 0 | F12: 0 | G12: 0 | H12: 0 | I12: 0 | J12: 0 | K12: 0 | L12: 0 | M12: 0 | N12: 0 | O12: =SUM(C12:N12) -> 0
B13: Budget | M13: 0 | O13: =SUM(C13:N13) -> 0
B14: Actual | O14: =SUM(C14:N14) -> 0
A15: The Vitals 808 | B15: Actual 2024 | K15: 4000 | O15: =SUM(C15:N15) -> 4000
B16: Estimated | C16: 0 | D16: 0 | E16: 0 | F16: 0 | G16: 0 | H16: 0 | I16: 0 | J16: 0 | K16: 0 | L16: 0 | M16: 0 | N16: 0 | O16: =SUM(C16:N16) -> 0
B17: Budget | O17: =SUM(C17:N17) -> 0
B18: Actual | O18: =SUM(C18:N18) -> 0
A19: Ha.Ka. Entertainment Inc | B19: Actual 2024 | L19: 4693.35 | O19: =SUM(C19:N19) -> 4693.35
B20: Estimated | C20: 0 | D20: 0 | E20: 0 | F20: 0 | G20: 0 | H20: 0 | I20: 0 | J20: 0 | K20: 0 | L20: 0 | M20: 0 | N20: 0 | O20: =SUM(C20:N20) -> 0
B21: Budget | O21: =SUM(C21:N21) -> 0
B22: Actual | O22: =SUM(C22:N22) -> 0
B23: Actual 2024 | O23: =SUM(C23:N23) -> 0
B24: Estimated | C24: 0 | D24: 0 | E24: 0 | F24: 0 | G24: 0 | H24: 0 | I24: 0 | J24: 0 | K24: 0 | L24: 0 | M24: 0 | N24: 0 | O24: =SUM(C24:N24) -> 0
B25: Budget | O25: =SUM(C25:N25) -> 0
B26: Actual | O26: =SUM(C26:N26) -> 0
B27: Actual 2024 | O27: =SUM(C27:N27) -> 0
B28: Estimated | C28: 0 | D28: 0 | E28: 0 | F28: 0 | G28: 0 | H28: 0 | I28: 0 | J28: 0 | K28: 0 | L28: 0 | M28: 0 | N28: 0 | O28: =SUM(C28:N28) -> 0
B29: Budget | O29: =SUM(C29:N29) -> 0
B30: Actual | O30: =SUM(C30:N30) -> 0
B31: Actual 2024 | O31: =SUM(C31:N31) -> 0
B32: Estimated | C32: 0 | D32: 0 | E32: 0 | F32: 0 | G32: 0 | H32: 0 | I32: 0 | J32: 0 | K32: 0 | L32: 0 | M32: 0 | N32: 0 | O32: =SUM(C32:N32) -> 0
B33: Budget | O33: =SUM(C33:N33) -> 0
B34: Actual | O34: =SUM(C34:N34) -> 0
B35: Actual 2024 | O35: =SUM(C35:N35) -> 0
B36: Estimated | C36: 0 | D36: 0 | E36: 0 | F36: 0 | G36: 0 | H36: 0 | I36: 0 | J36: 0 | K36: 0 | L36: 0 | M36: 0 | N36: 0 | O36: =SUM(C36:N36) -> 0
B37: Budget | O37: =SUM(C37:N37) -> 0
B38: Actual | O38: =SUM(C38:N38) -> 0
B39: Actual 2024 | O39: =SUM(C39:N39) -> 0
B40: Estimated | C40: 0 | D40: 0 | E40: 0 | F40: 0 | G40: 0 | H40: 0 | I40: 0 | J40: 0 | K40: 0 | L40: 0 | M40: 0 | N40: 0 | O40: =SUM(C40:N40) -> 0
B41: Budget | O41: =SUM(C41:N41) -> 0
B42: Actual | O42: =SUM(C42:N42) -> 0
B43: Actual 2024 | O43: =SUM(C43:N43) -> 0
B44: Estimated | C44: 0 | D44: 0 | E44: 0 | F44: 0 | G44: 0 | H44: 0 | I44: 0 | J44: 0 | K44: 0 | L44: 0 | M44: 0 | N44: 0 | O44: =SUM(C44:N44) -> 0
B45: Budget | O45: =SUM(C45:N45) -> 0
B46: Actual | O46: =SUM(C46:N46) -> 0
B47: Actual 2024 | O47: =SUM(C47:N47) -> 0
B48: Estimated | C48: 0 | D48: 0 | E48: 0 | F48: 0 | G48: 0 | H48: 0 | I48: 0 | J48: 0 | K48: 0 | L48: 0 | M48: 0 | N48: 0 | O48: =SUM(C48:N48) -> 0
B49: Budget | O49: =SUM(C49:N49) -> 0
B50: Actual | O50: =SUM(C50:N50) -> 0
B51: Actual 2024 | O51: =SUM(C51:N51) -> 0
B52: Estimated | C52: 0 | D52: 0 | E52: 0 | F52: 0 | G52: 0 | H52: 0 | I52: 0 | J52: 0 | K52: 0 | L52: 0 | M52: 0 | N52: 0 | O52: =SUM(C52:N52) -> 0
B53: Budget | O53: =SUM(C53:N53) -> 0
B54: Actual | O54: =SUM(C54:N54) -> 0
B55: Actual 2024 | O55: =SUM(C55:N55) -> 0
B56: Estimated | C56: 0 | D56: 0 | E56: 0 | F56: 0 | G56: 0 | H56: 0 | I56: 0 | J56: 0 | K56: 0 | L56: 0 | M56: 0 | N56: 0 | O56: =SUM(C56:N56) -> 0
B57: Budget | O57: =SUM(C57:N57) -> 0
B58: Actual | O58: =SUM(C58:N58) -> 0
B59: Actual 2024 | O59: =SUM(C59:N59) -> 0
B60: Estimated | C60: 0 | D60: 0 | E60: 0 | F60: 0 | G60: 0 | H60: 0 | I60: 0 | J60: 0 | K60: 0 | L60: 0 | M60: 0 | N60: 0 | O60: =SUM(C60:N60) -> 0
B61: Budget | O61: =SUM(C61:N61) -> 0
B62: Actual | O62: =SUM(C62:N62) -> 0
B63: Actual 2024 | O63: =SUM(C63:N63) -> 0
B64: Estimated | C64: 0 | D64: 0 | E64: 0 | F64: 0 | G64: 0 | H64: 0 | I64: 0 | J64: 0 | K64: 0 | L64: 0 | M64: 0 | N64: 0 | O64: =SUM(C64:N64) -> 0
B65: Budget | O65: =SUM(C65:N65) -> 0
B66: Actual | O66: =SUM(C66:N66) -> 0
B67: Actual 2024 | O67: =SUM(C67:N67) -> 0
B68: Estimated | C68: 0 | D68: 0 | E68: 0 | F68: 0 | G68: 0 | H68: 0 | I68: 0 | J68: 0 | K68: 0 | L68: 0 | M68: 0 | N68: 0 | O68: =SUM(C68:N68) -> 0
B69: Budget | O69: =SUM(C69:N69) -> 0
B70: Actual | O70: =SUM(C70:N70) -> 0
B71: Actual 2024 | O71: =SUM(C71:N71) -> 0
B72: Estimated | C72: 0 | D72: 0 | E72: 0 | F72: 0 | G72: 0 | H72: 0 | I72: 0 | J72: 0 | K72: 0 | L72: 0 | M72: 0 | N72: 0 | O72: =SUM(C72:N72) -> 0
B73: Budget | O73: =SUM(C73:N73) -> 0
B74: Actual | O74: =SUM(C74:N74) -> 0
B75: Actual 2024 | O75: =SUM(C75:N75) -> 0
B76: Estimated | C76: 0 | D76: 0 | E76: 0 | F76: 0 | G76: 0 | H76: 0 | I76: 0 | J76: 0 | K76: 0 | L76: 0 | M76: 0 | N76: 0 | O76: =SUM(C76:N76) -> 0
B77: Budget | O77: =SUM(C77:N77) -> 0
B78: Actual | O78: =SUM(C78:N78) -> 0
B79: Actual 2024 | O79: =SUM(C79:N79) -> 0
B80: Estimated | C80: 0 | D80: 0 | E80: 0 | F80: 0 | G80: 0 | H80: 0 | I80: 0 | J80: 0 | K80: 0 | L80: 0 | M80: 0 | N80: 0 | O80: =SUM(C80:N80) -> 0
B81: Budget | O81: =SUM(C81:N81) -> 0
B82: Actual | O82: =SUM(C82:N82) -> 0
B83: Actual 2024 | O83: =SUM(C83:N83) -> 0
B84: Estimated | C84: 0 | D84: 0 | E84: 0 | F84: 0 | G84: 0 | H84: 0 | I84: 0 | J84: 0 | K84: 0 | L84: 0 | M84: 0 | N84: 0 | O84: =SUM(C84:N84) -> 0
B85: Budget | O85: =SUM(C85:N85) -> 0
B86: Actual | O86: =SUM(C86:N86) -> 0
B87: Actual 2024 | O87: =SUM(C87:N87) -> 0
B88: Estimated | C88: 0 | D88: 0 | E88: 0 | F88: 0 | G88: 0 | H88: 0 | I88: 0 | J88: 0 | K88: 0 | L88: 0 | M88: 0 | N88: 0 | O88: =SUM(C88:N88) -> 0
B89: Budget | O89: =SUM(C89:N89) -> 0
B90: Actual | O90: =SUM(C90:N90) -> 0

Sheet 5313-510 Telecommunications
A1: 5313-510 Telecommunications
C2: January | D2: February | E2: March | F2: April | G2: May | H2: June | I2: July | J2: August | K2: September | L2: October | M2: November | N2: December | O2: Total
A3: TOTAL | B3: Actual 2024 | C3: =SUMIFS(C$11:C1000,$B$11:$B1000,"Actual 2024") -> 216.67 | D3: =SUMIFS(D$11:D1000,$B$11:$B1000,"Actual 2024") -> 216.67 | E3: =SUMIFS(E$11:E1000,$B$11:$B1000,"Actual 2024") -> 216.67 | F3: =SUMIFS(F$11:F1000,$B$11:$B1000,"Actual 2024") -> 216.67 | G3: =SUMIFS(G$11:G1000,$B$11:$B1000,"Actual 2024") -> 216.67 | H3: =SUMIFS(H$11:H1000,$B$11:$B1000,"Actual 2024") -> 216.67 | I3: =SUMIFS(I$11:I1000,$B$11:$B1000,"Actual 2024") -> 216.67 | J3: =SUMIFS(J$11:J1000,$B$11:$B1000,"Actual 2024") -> 216.67 | ... O3: =SUMIFS(O$11:O1000,$B$11:$B1000,"Actual 2024") -> 2600.04 | P3: 2240.84
B4: Estimated | C4: =SUMIFS(C$11:C1000,$B$11:$B1000,"Estimated") -> 216.67 | D4: =SUMIFS(D$11:D1000,$B$11:$B1000,"Estimated") -> 216.67 | E4: =SUMIFS(E$11:E1000,$B$11:$B1000,"Estimated") -> 216.67 | F4: =SUMIFS(F$11:F1000,$B$11:$B1000,"Estimated") -> 216.67 | G4: =SUMIFS(G$11:G1000,$B$11:$B1000,"Estimated") -> 216.67 | H4: =SUMIFS(H$11:H1000,$B$11:$B1000,"Estimated") -> 216.67 | I4: =SUMIFS(I$11:I1000,$B$11:$B1000,"Estimated") -> 216.67 | J4: =SUMIFS(J$11:J1000,$B$11:$B1000,"Estimated") -> 216.67 | ... O4: =SUMIFS(O$11:O1000,$B$11:$B1000,"Estimated") -> 2600.04
B5: Budget | C5: 216.67 | D5: 216.67 | E5: 216.67 | F5: 216.67 | G5: 216.67 | H5: 216.67 | I5: 216.67 | J5: 216.67 | K5: 216.67 | L5: 216.67 | M5: 216.67 | N5: 216.67 | O5: =SUM(C5:N5) -> 2600.04 | P5: 2600
B6: Actual | C6: =SUMIFS(C$11:C1005,$B$11:$B1005,"Actual") -> 0 | D6: =SUMIFS(D$11:D1005,$B$11:$B1005,"Actual") -> 0 | E6: =SUMIFS(E$11:E1005,$B$11:$B1005,"Actual") -> 0 | F6: =SUMIFS(F$11:F1005,$B$11:$B1005,"Actual") -> 0 | G6: =SUMIFS(G$11:G1005,$B$11:$B1005,"Actual") -> 0 | H6: =SUMIFS(H$11:H1005,$B$11:$B1005,"Actual") -> 0 | I6: =SUMIFS(I$11:I1005,$B$11:$B1005,"Actual") -> 0 | J6: =SUMIFS(J$11:J1005,$B$11:$B1005,"Actual") -> 0 | ... O6: =SUMIFS(O$11:O1005,$B$11:$B1005,"Actual") -> 0
B7: Budget Deficit/ Savings | C7: =C5-C6 -> 216.67 | D7: =D5-D6 -> 216.67 | E7: =E5-E6 -> 216.67 | F7: =F5-F6 -> 216.67 | G7: =G5-G6 -> 216.67 | H7: =H5-H6 -> 216.67 | I7: =I5-I6 -> 216.67 | J7: =J5-J6 -> 216.67 | ... O7: =O5-O6 -> 2600.04
B8: Year to Date Spend | C8: =SUM($C6:C6) -> 0 | D8: =SUM($C6:D6) -> 0 | E8: =SUM($C6:E6) -> 0 | F8: =SUM($C6:F6) -> 0 | G8: =SUM($C6:G6) -> 0 | H8: =SUM($C6:H6) -> 0 | I8: =SUM($C6:I6) -> 0 | J8: =SUM($C6:J6) -> 0 | ... N8: =SUM($C6:N6) -> 0 | O8: =O6 -> 0
B9: YTD Excess From Budget | C9: =SUM($C5:C5)-C8 -> 216.67 | D9: =SUM($C5:D5)-D8 -> 433.34 | E9: =SUM($C5:E5)-E8 -> 650.01 | F9: =SUM($C5:F5)-F8 -> 866.68 | G9: =SUM($C5:G5)-G8 -> 1083.35 | H9: =SUM($C5:H5)-H8 -> 1300.02 | I9: =SUM($C5:I5)-I8 -> 1516.69 | J9: =SUM($C5:J5)-J8 -> 1733.36 | ... N9: =SUM($C5:N5)-N8 -> 2600.04
A11: Cell phone | B11: Actual 2024 | C11: 216.67 | D11: 216.67 | E11: 216.67 | F11: 216.67 | G11: 216.67 | H11: 216.67 | I11: 216.67 | J11: 216.67 | K11: 216.67 | L11: 216.67 | M11: 216.67 | N11: 216.67 | O11: =SUM(C11:N11) -> 2600.04
B12: Estimated | C12: 216.67 | D12: 216.67 | E12: 216.67 | F12: 216.67 | G12: 216.67 | H12: 216.67 | I12: 216.67 | J12: 216.67 | K12: 216.67 | L12: 216.67 | M12: 216.67 | N12: 216.67 | O12: =SUM(C12:N12) -> 2600.04
B13: Budget | O13: =SUM(C13:N13) -> 0
B14: Actual | O14: =SUM(C14:N14) -> 0
B15: Actual 2024 | O15: =SUM(C15:N15) -> 0
B16: Estimated | C16: 0 | D16: 0 | E16: 0 | F16: 0 | G16: 0 | H16: 0 | I16: 0 | J16: 0 | K16: 0 | L16: 0 | M16: 0 | N16: 0 | O16: =SUM(C16:N16) -> 0
B17: Budget | O17: =SUM(C17:N17) -> 0
B18: Actual | O18: =SUM(C18:N18) -> 0
B19: Actual 2024 | O19: =SUM(C19:N19) -> 0
B20: Estimated | C20: 0 | D20: 0 | E20: 0 | F20: 0 | G20: 0 | H20: 0 | I20: 0 | J20: 0 | K20: 0 | L20: 0 | M20: 0 | N20: 0 | O20: =SUM(C20:N20) -> 0
B21: Budget | O21: =SUM(C21:N21) -> 0
B22: Actual | O22: =SUM(C22:N22) -> 0
B23: Actual 2024 | O23: =SUM(C23:N23) -> 0
B24: Estimated | C24: 0 | D24: 0 | E24: 0 | F24: 0 | G24: 0 | H24: 0 | I24: 0 | J24: 0 | K24: 0 | L24: 0 | M24: 0 | N24: 0 | O24: =SUM(C24:N24) -> 0
B25: Budget | O25: =SUM(C25:N25) -> 0
B26: Actual | O26: =SUM(C26:N26) -> 0
B27: Actual 2024 | O27: =SUM(C27:N27) -> 0
B28: Estimated | C28: 0 | D28: 0 | E28: 0 | F28: 0 | G28: 0 | H28: 0 | I28: 0 | J28: 0 | K28: 0 | L28: 0 | M28: 0 | N28: 0 | O28: =SUM(C28:N28) -> 0
B29: Budget | O29: =SUM(C29:N29) -> 0
B30: Actual | O30: =SUM(C30:N30) -> 0
B31: Actual 2024 | O31: =SUM(C31:N31) -> 0
B32: Estimated | C32: 0 | D32: 0 | E32: 0 | F32: 0 | G32: 0 | H32: 0 | I32: 0 | J32: 0 | K32: 0 | L32: 0 | M32: 0 | N32: 0 | O32: =SUM(C32:N32) -> 0
B33: Budget | O33: =SUM(C33:N33) -> 0
B34: Actual | O34: =SUM(C34:N34) -> 0
B35: Actual 2024 | O35: =SUM(C35:N35) -> 0
B36: Estimated | C36: 0 | D36: 0 | E36: 0 | F36: 0 | G36: 0 | H36: 0 | I36: 0 | J36: 0 | K36: 0 | L36: 0 | M36: 0 | N36: 0 | O36: =SUM(C36:N36) -> 0
B37: Budget | O37: =SUM(C37:N37) -> 0
B38: Actual | O38: =SUM(C38:N38) -> 0
B39: Actual 2024 | O39: =SUM(C39:N39) -> 0
B40: Estimated | C40: 0 | D40: 0 | E40: 0 | F40: 0 | G40: 0 | H40: 0 | I40: 0 | J40: 0 | K40: 0 | L40: 0 | M40: 0 | N40: 0 | O40: =SUM(C40:N40) -> 0
B41: Budget | O41: =SUM(C41:N41) -> 0
B42: Actual | O42: =SUM(C42:N42) -> 0
B43: Actual 2024 | O43: =SUM(C43:N43) -> 0
B44: Estimated | C44: 0 | D44: 0 | E44: 0 | F44: 0 | G44: 0 | H44: 0 | I44: 0 | J44: 0 | K44: 0 | L44: 0 | M44: 0 | N44: 0 | O44: =SUM(C44:N44) -> 0
B45: Budget | O45: =SUM(C45:N45) -> 0
B46: Actual | O46: =SUM(C46:N46) -> 0
B47: Actual 2024 | O47: =SUM(C47:N47) -> 0
B48: Estimated | C48: 0 | D48: 0 | E48: 0 | F48: 0 | G48: 0 | H48: 0 | I48: 0 | J48: 0 | K48: 0 | L48: 0 | M48: 0 | N48: 0 | O48: =SUM(C48:N48) -> 0
B49: Budget | O49: =SUM(C49:N49) -> 0
B50: Actual | O50: =SUM(C50:N50) -> 0
B51: Actual 2024 | O51: =SUM(C51:N51) -> 0
B52: Estimated | C52: 0 | D52: 0 | E52: 0 | F52: 0 | G52: 0 | H52: 0 | I52: 0 | J52: 0 | K52: 0 | L52: 0 | M52: 0 | N52: 0 | O52: =SUM(C52:N52) -> 0
B53: Budget | O53: =SUM(C53:N53) -> 0
B54: Actual | O54: =SUM(C54:N54) -> 0
B55: Actual 2024 | O55: =SUM(C55:N55) -> 0
B56: Estimated | C56: 0 | D56: 0 | E56: 0 | F56: 0 | G56: 0 | H56: 0 | I56: 0 | J56: 0 | K56: 0 | L56: 0 | M56: 0 | N56: 0 | O56: =SUM(C56:N56) -> 0
B57: Budget | O57: =SUM(C57:N57) -> 0
B58: Actual | O58: =SUM(C58:N58) -> 0
B59: Actual 2024 | O59: =SUM(C59:N59) -> 0
B60: Estimated | C60: 0 | D60: 0 | E60: 0 | F60: 0 | G60: 0 | H60: 0 | I60: 0 | J60: 0 | K60: 0 | L60: 0 | M60: 0 | N60: 0 | O60: =SUM(C60:N60) -> 0
B61: Budget | O61: =SUM(C61:N61) -> 0
B62: Actual | O62: =SUM(C62:N62) -> 0
B63: Actual 2024 | O63: =SUM(C63:N63) -> 0
B64: Estimated | C64: 0 | D64: 0 | E64: 0 | F64: 0 | G64: 0 | H64: 0 | I64: 0 | J64: 0 | K64: 0 | L64: 0 | M64: 0 | N64: 0 | O64: =SUM(C64:N64) -> 0
B65: Budget | O65: =SUM(C65:N65) -> 0
B66: Actual | O66: =SUM(C66:N66) -> 0
B67: Actual 2024 | O67: =SUM(C67:N67) -> 0
B68: Estimated | C68: 0 | D68: 0 | E68: 0 | F68: 0 | G68: 0 | H68: 0 | I68: 0 | J68: 0 | K68: 0 | L68: 0 | M68: 0 | N68: 0 | O68: =SUM(C68:N68) -> 0
B69: Budget | O69: =SUM(C69:N69) -> 0
B70: Actual | O70: =SUM(C70:N70) -> 0
B71: Actual 2024 | O71: =SUM(C71:N71) -> 0
B72: Estimated | C72: 0 | D72: 0 | E72: 0 | F72: 0 | G72: 0 | H72: 0 | I72: 0 | J72: 0 | K72: 0 | L72: 0 | M72: 0 | N72: 0 | O72: =SUM(C72:N72) -> 0
B73: Budget | O73: =SUM(C73:N73) -> 0
B74: Actual | O74: =SUM(C74:N74) -> 0
B75: Actual 2024 | O75: =SUM(C75:N75) -> 0
B76: Estimated | C76: 0 | D76: 0 | E76: 0 | F76: 0 | G76: 0 | H76: 0 | I76: 0 | J76: 0 | K76: 0 | L76: 0 | M76: 0 | N76: 0 | O76: =SUM(C76:N76) -> 0
B77: Budget | O77: =SUM(C77:N77) -> 0
B78: Actual | O78: =SUM(C78:N78) -> 0
B79: Actual 2024 | O79: =SUM(C79:N79) -> 0
B80: Estimated | C80: 0 | D80: 0 | E80: 0 | F80: 0 | G80: 0 | H80: 0 | I80: 0 | J80: 0 | K80: 0 | L80: 0 | M80: 0 | N80: 0 | O80: =SUM(C80:N80) -> 0
B81: Budget | O81: =SUM(C81:N81) -> 0
B82: Actual | O82: =SUM(C82:N82) -> 0
B83: Actual 2024 | O83: =SUM(C83:N83) -> 0
B84: Estimated | C84: 0 | D84: 0 | E84: 0 | F84: 0 | G84: 0 | H84: 0 | I84: 0 | J84: 0 | K84: 0 | L84: 0 | M84: 0 | N84: 0 | O84: =SUM(C84:N84) -> 0
B85: Budget | O85: =SUM(C85:N85) -> 0
B86: Actual | O86: =SUM(C86:N86) -> 0
B87: Actual 2024 | O87: =SUM(C87:N87) -> 0
B88: Estimated | C88: 0 | D88: 0 | E88: 0 | F88: 0 | G88: 0 | H88: 0 | I88: 0 | J88: 0 | K88: 0 | L88: 0 | M88: 0 | N88: 0 | O88: =SUM(C88:N88) -> 0
B89: Budget | O89: =SUM(C89:N89) -> 0
B90: Actual | O90: =SUM(C90:N90) -> 0
B91: Actual 2024 | O91: =SUM(C91:N91) -> 0
B92: Estimated | C92: 0 | D92: 0 | E92: 0 | F92: 0 | G92: 0 | H92: 0 | I92: 0 | J92: 0 | K92: 0 | L92: 0 | M92: 0 | N92: 0 | O92: =SUM(C92:N92) -> 0
B93: Budget | O93: =SUM(C93:N93) -> 0
B94: Actual | O94: =SUM(C94:N94) -> 0
B95: Actual 2024 | O95: =SUM(C95:N95) -> 0
B96: Estimated | C96: 0 | D96: 0 | E96: 0 | F96: 0 | G96: 0 | H96: 0 | I96: 0 | J96: 0 | K96: 0 | L96: 0 | M96: 0 | N96: 0 | O96: =SUM(C96:N96) -> 0
B97: Budget | O97: =SUM(C97:N97) -> 0
B98: Actual | O98: =SUM(C98:N98) -> 0
B99: Actual 2024 | O99: =SUM(C99:N99) -> 0
B100: Estimated | C100: 0 | D100: 0 | E100: 0 | F100: 0 | G100: 0 | H100: 0 | I100: 0 | J100: 0 | K100: 0 | L100: 0 | M100: 0 | N100: 0 | O100: =SUM(C100:N100) -> 0
B101: Budget | O101: =SUM(C101:N101) -> 0
...

Sheet 5314-510 Postage & Freight
A1: 5314-510 Postage and Freight (Outward)
C2: January | D2: February | E2: March | F2: April | G2: May | H2: June | I2: July | J2: August | K2: September | L2: October | M2: November | N2: December | O2: Total
A3: TOTAL | B3: Actual 2024 | C3: =SUMIFS(C$11:C996,$B$11:$B996,"Actual 2024") -> 0 | D3: =SUMIFS(D$11:D996,$B$11:$B996,"Actual 2024") -> 0 | E3: =SUMIFS(E$11:E996,$B$11:$B996,"Actual 2024") -> 0 | F3: =SUMIFS(F$11:F996,$B$11:$B996,"Actual 2024") -> 0 | G3: =SUMIFS(G$11:G996,$B$11:$B996,"Actual 2024") -> 0 | H3: =SUMIFS(H$11:H996,$B$11:$B996,"Actual 2024") -> 0 | I3: =SUMIFS(I$11:I996,$B$11:$B996,"Actual 2024") -> 0 | J3: =SUMIFS(J$11:J996,$B$11:$B996,"Actual 2024") -> 0 | ... O3: =SUMIFS(O$11:O996,$B$11:$B996,"Actual 2024") -> 734.55 | P3: 5644.26
B4: Estimated | C4: =SUMIFS(C$11:C996,$B$11:$B996,"Estimated") -> 0 | D4: =SUMIFS(D$11:D996,$B$11:$B996,"Estimated") -> 0 | E4: =SUMIFS(E$11:E996,$B$11:$B996,"Estimated") -> 0 | F4: =SUMIFS(F$11:F996,$B$11:$B996,"Estimated") -> 0 | G4: =SUMIFS(G$11:G996,$B$11:$B996,"Estimated") -> 0 | H4: =SUMIFS(H$11:H996,$B$11:$B996,"Estimated") -> 0 | I4: =SUMIFS(I$11:I996,$B$11:$B996,"Estimated") -> 0 | J4: =SUMIFS(J$11:J996,$B$11:$B996,"Estimated") -> 0 | ... O4: =SUMIFS(O$11:O996,$B$11:$B996,"Estimated") -> 734
B5: Budget | C5: 0 | D5: 0 | E5: 0 | F5: 0 | G5: 0 | H5: 0 | I5: 0 | J5: 0 | K5: 0 | L5: 0 | M5: 0 | N5: 0 | O5: =SUM(C5:N5) -> 0 | P5: 0
B6: Actual | C6: =SUMIFS(C$11:C1001,$B$11:$B1001,"Actual") -> 0 | D6: =SUMIFS(D$11:D1001,$B$11:$B1001,"Actual") -> 0 | E6: =SUMIFS(E$11:E1001,$B$11:$B1001,"Actual") -> 33.94 | F6: =SUMIFS(F$11:F1001,$B$11:$B1001,"Actual") -> 0 | G6: =SUMIFS(G$11:G1001,$B$11:$B1001,"Actual") -> 0 | H6: =SUMIFS(H$11:H1001,$B$11:$B1001,"Actual") -> 241.55 | I6: =SUMIFS(I$11:I1001,$B$11:$B1001,"Actual") -> 194.31 | J6: =SUMIFS(J$11:J1001,$B$11:$B1001,"Actual") -> 249.19 | ... O6: =SUMIFS(O$11:O1001,$B$11:$B1001,"Actual") -> 797.09
B7: Budget Deficit/ Savings | C7: =C5-C6 -> 0 | D7: =D5-D6 -> 0 | E7: =E5-E6 -> -33.94 | F7: =F5-F6 -> 0 | G7: =G5-G6 -> 0 | H7: =H5-H6 -> -241.55 | I7: =I5-I6 -> -194.31 | J7: =J5-J6 -> -249.19 | ... O7: =O5-O6 -> -797.09
B8: Year to Date Spend | C8: =SUM($C6:C6) -> 0 | D8: =SUM($C6:D6) -> 0 | E8: =SUM($C6:E6) -> 33.94 | F8: =SUM($C6:F6) -> 33.94 | G8: =SUM($C6:G6) -> 33.94 | H8: =SUM($C6:H6) -> 275.49 | I8: =SUM($C6:I6) -> 469.8 | J8: =SUM($C6:J6) -> 718.99 | ... N8: =SUM($C6:N6) -> 797.09 | O8: =O6 -> 797.09
B9: YTD Excess From Budget | C9: =SUM($C5:C5)-C8 -> 0 | D9: =SUM($C5:D5)-D8 -> 0 | E9: =SUM($C5:E5)-E8 -> -33.94 | F9: =SUM($C5:F5)-F8 -> -33.94 | G9: =SUM($C5:G5)-G8 -> -33.94 | H9: =SUM($C5:H5)-H8 -> -275.49 | I9: =SUM($C5:I5)-I8 -> -469.8 | J9: =SUM($C5:J5)-J8 -> -718.99 | ... N9: =SUM($C5:N5)-N8 -> -797.09
A11: PCC Business Office (Mailing) | B11: Actual 2024 | O11: =SUM(C11:N11) -> 0
B12: Estimated | C12: 0 | D12: 0 | E12: 0 | F12: 0 | G12: 0 | H12: 0 | I12: 0 | J12: 0 | K12: 0 | L12: 0 | M12: 0 | N12: 0 | O12: =SUM(C12:N12) -> 0
B13: Budget | O13: =SUM(C13:N13) -> 0
B14: Actual | O14: =SUM(C14:N14) -> 0
A15: FedEx | B15: Actual 2024 | K15: 157.09 | O15: =SUM(C15:N15) -> 157.09
B16: Estimated | C16: 0 | D16: 0 | E16: 0 | F16: 0 | G16: 0 | H16: 0 | I16: 0 | J16: 0 | K16: 157 | L16: 0 | M16: 0 | N16: 0 | O16: =SUM(C16:N16) -> 157
B17: Budget | O17: =SUM(C17:N17) -> 0
B18: Actual | H18: 241.55 | I18: 194.31 | J18: 249.19 | O18: =SUM(C18:N18) -> 685.05
A19: USPS | B19: Actual 2024 | K19: 577.46 | O19: =SUM(C19:N19) -> 577.46
B20: Estimated | C20: 0 | D20: 0 | E20: 0 | F20: 0 | G20: 0 | H20: 0 | I20: 0 | J20: 0 | K20: 577 | L20: 0 | M20: 0 | N20: 0 | O20: =SUM(C20:N20) -> 577
B21: Budget | O21: =SUM(C21:N21) -> 0
B22: Actual | O22: =SUM(C22:N22) -> 0
A23: UPS | B23: Actual 2024 | O23: =SUM(C23:N23) -> 0
B24: Estimated | C24: 0 | D24: 0 | E24: 0 | F24: 0 | G24: 0 | H24: 0 | I24: 0 | J24: 0 | K24: 0 | L24: 0 | M24: 0 | N24: 0 | O24: =SUM(C24:N24) -> 0
B25: Budget | O25: =SUM(C25:N25) -> 0
B26: Actual | E26: 33.94 | O26: =SUM(C26:N26) -> 33.94
A27: Hotel Keihan | B27: Actual 2024 | O27: =SUM(C27:N27) -> 0
B28: Estimated | C28: 0 | D28: 0 | E28: 0 | F28: 0 | G28: 0 | H28: 0 | I28: 0 | J28: 0 | K28: 0 | L28: 0 | M28: 0 | N28: 0 | O28: =SUM(C28:N28) -> 0
B29: Budget | O29: =SUM(C29:N29) -> 0
B30: Actual | K30: 78.1 | O30: =SUM(C30:N30) -> 78.1
B31: Actual 2024 | O31: =SUM(C31:N31) -> 0
B32: Estimated | C32: 0 | D32: 0 | E32: 0 | F32: 0 | G32: 0 | H32: 0 | I32: 0 | J32: 0 | K32: 0 | L32: 0 | M32: 0 | N32: 0 | O32: =SUM(C32:N32) -> 0
B33: Budget | O33: =SUM(C33:N33) -> 0
B34: Actual | O34: =SUM(C34:N34) -> 0
B35: Actual 2024 | O35: =SUM(C35:N35) -> 0
B36: Estimated | C36: 0 | D36: 0 | E36: 0 | F36: 0 | G36: 0 | H36: 0 | I36: 0 | J36: 0 | K36: 0 | L36: 0 | M36: 0 | N36: 0 | O36: =SUM(C36:N36) -> 0
B37: Budget | O37: =SUM(C37:N37) -> 0
B38: Actual | O38: =SUM(C38:N38) -> 0
B39: Actual 2024 | O39: =SUM(C39:N39) -> 0
B40: Estimated | C40: 0 | D40: 0 | E40: 0 | F40: 0 | G40: 0 | H40: 0 | I40: 0 | J40: 0 | K40: 0 | L40: 0 | M40: 0 | N40: 0 | O40: =SUM(C40:N40) -> 0
B41: Budget | O41: =SUM(C41:N41) -> 0
B42: Actual | O42: =SUM(C42:N42) -> 0
B43: Actual 2024 | O43: =SUM(C43:N43) -> 0
B44: Estimated | C44: 0 | D44: 0 | E44: 0 | F44: 0 | G44: 0 | H44: 0 | I44: 0 | J44: 0 | K44: 0 | L44: 0 | M44: 0 | N44: 0 | O44: =SUM(C44:N44) -> 0
B45: Budget | O45: =SUM(C45:N45) -> 0
B46: Actual | O46: =SUM(C46:N46) -> 0
B47: Actual 2024 | O47: =SUM(C47:N47) -> 0
B48: Estimated | C48: 0 | D48: 0 | E48: 0 | F48: 0 | G48: 0 | H48: 0 | I48: 0 | J48: 0 | K48: 0 | L48: 0 | M48: 0 | N48: 0 | O48: =SUM(C48:N48) -> 0
B49: Budget | O49: =SUM(C49:N49) -> 0
B50: Actual | O50: =SUM(C50:N50) -> 0
B51: Actual 2024 | O51: =SUM(C51:N51) -> 0
B52: Estimated | C52: 0 | D52: 0 | E52: 0 | F52: 0 | G52: 0 | H52: 0 | I52: 0 | J52: 0 | K52: 0 | L52: 0 | M52: 0 | N52: 0 | O52: =SUM(C52:N52) -> 0
B53: Budget | O53: =SUM(C53:N53) -> 0
B54: Actual | O54: =SUM(C54:N54) -> 0
B55: Actual 2024 | O55: =SUM(C55:N55) -> 0
B56: Estimated | C56: 0 | D56: 0 | E56: 0 | F56: 0 | G56: 0 | H56: 0 | I56: 0 | J56: 0 | K56: 0 | L56: 0 | M56: 0 | N56: 0 | O56: =SUM(C56:N56) -> 0
B57: Budget | O57: =SUM(C57:N57) -> 0
B58: Actual | O58: =SUM(C58:N58) -> 0
B59: Actual 2024 | O59: =SUM(C59:N59) -> 0
B60: Estimated | C60: 0 | D60: 0 | E60: 0 | F60: 0 | G60: 0 | H60: 0 | I60: 0 | J60: 0 | K60: 0 | L60: 0 | M60: 0 | N60: 0 | O60: =SUM(C60:N60) -> 0
B61: Budget | O61: =SUM(C61:N61) -> 0
B62: Actual | O62: =SUM(C62:N62) -> 0
B63: Actual 2024 | O63: =SUM(C63:N63) -> 0
B64: Estimated | C64: 0 | D64: 0 | E64: 0 | F64: 0 | G64: 0 | H64: 0 | I64: 0 | J64: 0 | K64: 0 | L64: 0 | M64: 0 | N64: 0 | O64: =SUM(C64:N64) -> 0
B65: Budget | O65: =SUM(C65:N65) -> 0
B66: Actual | O66: =SUM(C66:N66) -> 0
B67: Actual 2024 | O67: =SUM(C67:N67) -> 0
B68: Estimated | C68: 0 | D68: 0 | E68: 0 | F68: 0 | G68: 0 | H68: 0 | I68: 0 | J68: 0 | K68: 0 | L68: 0 | M68: 0 | N68: 0 | O68: =SUM(C68:N68) -> 0
B69: Budget | O69: =SUM(C69:N69) -> 0
B70: Actual | O70: =SUM(C70:N70) -> 0
B71: Actual 2024 | O71: =SUM(C71:N71) -> 0
B72: Estimated | C72: 0 | D72: 0 | E72: 0 | F72: 0 | G72: 0 | H72: 0 | I72: 0 | J72: 0 | K72: 0 | L72: 0 | M72: 0 | N72: 0 | O72: =SUM(C72:N72) -> 0
B73: Budget | O73: =SUM(C73:N73) -> 0
B74: Actual | O74: =SUM(C74:N74) -> 0
B75: Actual 2024 | O75: =SUM(C75:N75) -> 0
B76: Estimated | C76: 0 | D76: 0 | E76: 0 | F76: 0 | G76: 0 | H76: 0 | I76: 0 | J76: 0 | K76: 0 | L76: 0 | M76: 0 | N76: 0 | O76: =SUM(C76:N76) -> 0
B77: Budget | O77: =SUM(C77:N77) -> 0
B78: Actual | O78: =SUM(C78:N78) -> 0
B79: Actual 2024 | O79: =SUM(C79:N79) -> 0
B80: Estimated | C80: 0 | D80: 0 | E80: 0 | F80: 0 | G80: 0 | H80: 0 | I80: 0 | J80: 0 | K80: 0 | L80: 0 | M80: 0 | N80: 0 | O80: =SUM(C80:N80) -> 0
B81: Budget | O81: =SUM(C81:N81) -> 0
B82: Actual | O82: =SUM(C82:N82) -> 0
B83: Actual 2024 | O83: =SUM(C83:N83) -> 0
B84: Estimated | C84: 0 | D84: 0 | E84: 0 | F84: 0 | G84: 0 | H84: 0 | I84: 0 | J84: 0 | K84: 0 | L84: 0 | M84: 0 | N84: 0 | O84: =SUM(C84:N84) -> 0
B85: Budget | O85: =SUM(C85:N85) -> 0
B86: Actual | O86: =SUM(C86:N86) -> 0
B87: Actual 2024 | O87: =SUM(C87:N87) -> 0
B88: Estimated | C88: 0 | D88: 0 | E88: 0 | F88: 0 | G88: 0 | H88: 0 | I88: 0 | J88: 0 | K88: 0 | L88: 0 | M88: 0 | N88: 0 | O88: =SUM(C88:N88) -> 0
B89: Budget | O89: =SUM(C89:N89) -> 0
B90: Actual | O90: =SUM(C90:N90) -> 0
B91: Actual 2024 | O91: =SUM(C91:N91) -> 0
B92: Estimated | C92: 0 | D92: 0 | E92: 0 | F92: 0 | G92: 0 | H92: 0 | I92: 0 | J92: 0 | K92: 0 | L92: 0 | M92: 0 | N92: 0 | O92: =SUM(C92:N92) -> 0
B93: Budget | O93: =SUM(C93:N93) -> 0
B94: Actual | O94: =SUM(C94:N94) -> 0
B95: Actual 2024 | O95: =SUM(C95:N95) -> 0
B96: Estimated | C96: 0 | D96: 0 | E96: 0 | F96: 0 | G96: 0 | H96: 0 | I96: 0 | J96: 0 | K96: 0 | L96: 0 | M96: 0 | N96: 0 | O96: =SUM(C96:N96) -> 0
B97: Budget | O97: =SUM(C97:N97) -> 0
B98: Actual | O98: =SUM(C98:N98) -> 0

Sheet 5315-510 Technology Services
A1: 5315-510 Technology Services
C2: January | D2: February | E2: March | F2: April | G2: May | H2: June | I2: July | J2: August | K2: September | L2: October | M2: November | N2: December | O2: Total
A3: TOTAL | B3: Actual 2024 | C3: =SUMIFS(C$11:C989,$B$11:$B989,"Actual 2024") -> 6906.24 | D3: =SUMIFS(D$11:D989,$B$11:$B989,"Actual 2024") -> 6134.72 | E3: =SUMIFS(E$11:E989,$B$11:$B989,"Actual 2024") -> 5579.61 | F3: =SUMIFS(F$11:F989,$B$11:$B989,"Actual 2024") -> 7145.87 | G3: =SUMIFS(G$11:G989,$B$11:$B989,"Actual 2024") -> 6555.06 | H3: =SUMIFS(H$11:H989,$B$11:$B989,"Actual 2024") -> 6400.36 | I3: =SUMIFS(I$11:I989,$B$11:$B989,"Actual 2024") -> 6958.69 | J3: =SUMIFS(J$11:J989,$B$11:$B989,"Actual 2024") -> 15241.24 | ... O3: =SUMIFS(O$11:O989,$B$11:$B989,"Actual 2024") -> 94790.68 | P3: 63710.26
B4: Estimated | C4: =SUMIFS(C$11:C989,$B$11:$B989,"Estimated") -> 8473.64 | D4: =SUMIFS(D$11:D989,$B$11:$B989,"Estimated") -> 9183.16 | E4: =SUMIFS(E$11:E989,$B$11:$B989,"Estimated") -> 8023.21 | F4: =SUMIFS(F$11:F989,$B$11:$B989,"Estimated") -> 12423.21 | G4: =SUMIFS(G$11:G989,$B$11:$B989,"Estimated") -> 8023.21 | H4: =SUMIFS(H$11:H989,$B$11:$B989,"Estimated") -> 8923.21 | I4: =SUMIFS(I$11:I989,$B$11:$B989,"Estimated") -> 8173.21 | J4: =SUMIFS(J$11:J989,$B$11:$B989,"Estimated") -> 18462.83 | ... O4: =SUMIFS(O$11:O989,$B$11:$B989,"Estimated") -> 127633.11 | Q4: =O4-O3 -> 32842.43
B5: Budget | C5: 500 | D5: 500 | E5: 500 | F5: 500 | G5: 500 | H5: 500 | I5: 500 | J5: 500 | K5: 500 | L5: 500 | M5: 500 | N5: 500 | O5: =SUM(C5:N5) -> 6000 | P5: 6000
B6: Actual | C6: =SUMIFS(C$11:C989,$B$11:$B989,"Actual") -> 6731.17 | D6: =SUMIFS(D$11:D989,$B$11:$B989,"Actual") -> 7121.81 | E6: =SUMIFS(E$11:E989,$B$11:$B989,"Actual") -> 7581.94 | F6: =SUMIFS(F$11:F989,$B$11:$B989,"Actual") -> 6799.15 | G6: =SUMIFS(G$11:G989,$B$11:$B989,"Actual") -> 10575.96 | H6: =SUMIFS(H$11:H989,$B$11:$B989,"Actual") -> 9434.81 | I6: =SUMIFS(I$11:I989,$B$11:$B989,"Actual") -> 7708.89 | J6: =SUMIFS(J$11:J989,$B$11:$B989,"Actual") -> 17798.1 | ... O6: =SUMIFS(O$11:O989,$B$11:$B989,"Actual") -> 91817.64
B7: Budget Deficit/ Savings | C7: =C5-C6 -> -6231.17 | D7: =D5-D6 -> -6621.81 | E7: =E5-E6 -> -7081.94 | F7: =F5-F6 -> -6299.15 | G7: =G5-G6 -> -10075.96 | H7: =H5-H6 -> -8934.81 | I7: =I5-I6 -> -7208.89 | J7: =J5-J6 -> -17298.1 | ... O7: =O5-O6 -> -85817.64
B8: Year to Date Spend | C8: =SUM($C6:C6) -> 6731.17 | D8: =SUM($C6:D6) -> 13852.98 | E8: =SUM($C6:E6) -> 21434.92 | F8: =SUM($C6:F6) -> 28234.07 | G8: =SUM($C6:G6) -> 38810.03 | H8: =SUM($C6:H6) -> 48244.84 | I8: =SUM($C6:I6) -> 55953.73 | J8: =SUM($C6:J6) -> 73751.83 | ... N8: =SUM($C6:N6) -> 91817.64 | O8: =O6 -> 91817.64
B9: YTD Excess From Budget | C9: =SUM($C5:C5)-C8 -> -6231.17 | D9: =SUM($C5:D5)-D8 -> -12852.98 | E9: =SUM($C5:E5)-E8 -> -19934.92 | F9: =SUM($C5:F5)-F8 -> -26234.07 | G9: =SUM($C5:G5)-G8 -> -36310.03 | H9: =SUM($C5:H5)-H8 -> -45244.84 | I9: =SUM($C5:I5)-I8 -> -52453.73 | J9: =SUM($C5:J5)-J8 -> -69751.83 | ... N9: =SUM($C5:N5)-N8 -> -85817.64
A11: Performance Horizon Inc (Brand Verity) | B11: Actual 2024 | C11: 1125 | F11: 1125 | I11: 1125 | L11: 1125 | O11: =SUM(C11:N11) -> 4500
B12: Perf | C12: 375 | D12: 375 | E12: 375 | F12: 375 | G12: 375 | H12: 375 | I12: 375 | J12: 375 | K12: 375 | L12: 375 | M12: 375 | N12: 375 | O12: =SUM(C12:N12) -> 4500
B13: Budget | O13: =SUM(C13:N13) -> 0
B14: Actual | G14: 1125 | I14: 1125 | O14: =SUM(C14:N14) -> 2250
A15: REVIEWTRACKERS | B15: Actual 2024 | C15: 93.6 | D15: 93.6 | E15: 93.6 | F15: 93.6 | G15: 93.6 | H15: 93.6 | I15: 93.6 | J15: 93.6 | K15: 93.6 | L15: 93.6 | M15: 93.6 | N15: 93.6 | O15: =SUM(C15:N15) -> 1123.2
B16: Estimated | C16: 94 | D16: 94 | E16: 94 | F16: 94 | G16: 94 | H16: 94 | I16: 94 | J16: 94 | K16: 94 | L16: 94 | M16: 94 | N16: 94 | O16: =SUM(C16:N16) -> 1128
B17: Budget | O17: =SUM(C17:N17) -> 0
B18: Actual | C18: 93.6 | D18: 93.6 | E18: 93.6 | F18: 93.6 | G18: 93.6 | H18: 93.6 | I18: 93.6 | J18: 93.6 | K18: 93.6 | O18: =SUM(C18:N18) -> 842.4
A19: DISTROKID.COM | B19: Actual 2024 | G19: 59.23 | J19: 179.01 | K19: 12.57 | L19: 41.87 | M19: 40.97 | O19: =SUM(C19:N19) -> 333.65
B20: Estimated | C20: 60 | D20: 60 | E20: 60 | F20: 60 | G20: 60 | H20: 60 | I20: 60 | J20: 60 | K20: 60 | L20: 60 | M20: 60 | N20: 60 | O20: =SUM(C20:N20) -> 720
B21: Budget | O21: =SUM(C21:N21) -> 0
B22: Actual | F22: 59.23 | J22: 179.01 | K22: 12.57 | O22: =SUM(C22:N22) -> 250.81
A23: VIA/POSTSCRIPT | B23: Actual 2024 | C23: 400 | D23: 652.82 | E23: 652.82 | F23: 529.87 | G23: 624.75 | H23: 631.58 | I23: 542.2 | J23: 528.79 | K23: 523.37 | L23: 549.61 | M23: 521.1 | N23: 602.84 | O23: =SUM(C23:N23) -> 6759.75
B24: Estimated | C24: 500 | D24: 500 | E24: 500 | F24: 500 | G24: 500 | H24: 500 | I24: 500 | J24: 542.86 | K24: 560.71 | L24: 700 | M24: 700 | N24: 700 | O24: =SUM(C24:N24) -> 6703.57
B25: Budget | O25: =SUM(C25:N25) -> 0
B26: Actual | C26: 510.39 | D26: 509.95 | E26: 887.19 | O26: =SUM(C26:N26) -> 1907.53
A27: VIMEO | B27: Actual 2024 | C27: 51.21 | D27: 51.21 | E27: 51.21 | F27: 51.21 | G27: 51.21 | H27: 51.21 | I27: 51.21 | J27: 51.21 | K27: 51.21 | L27: 51.21 | M27: 51.21 | N27: 625.96 | O27: =SUM(C27:N27) -> 1189.27
B28: Estimated | C28: 51.21 | D28: 51.21 | E28: 51.21 | F28: 51.21 | G28: 51.21 | H28: 51.21 | I28: 51.21 | J28: 51.21 | K28: 51.21 | L28: 51.21 | M28: 51.21 | N28: 51.21 | O28: =SUM(C28:N28) -> 614.52
B29: Budget | O29: =SUM(C29:N29) -> 0
B30: Actual | O30: =SUM(C30:N30) -> 0
A31: WP ROCKET (WP PLUGIN) | B31: Actual 2024 | O31: =SUM(C31:N31) -> 0
B32: Estimated | C32: 0 | D32: 0 | E32: 0 | F32: 0 | G32: 0 | H32: 0 | I32: 150 | J32: 0 | K32: 0 | L32: 0 | M32: 0 | N32: 0 | O32: =SUM(C32:N32) -> 150
B33: Budget | O33: =SUM(C33:N33) -> 0
B34: Actual | O34: =SUM(C34:N34) -> 0
A35: SMUGMUG | B35: Actual 2024 | F35: 257.07 | O35: =SUM(C35:N35) -> 257.07
B36: Estimated | C36: 0 | D36: 0 | E36: 0 | F36: 0 | G36: 0 | H36: 0 | I36: 0 | J36: 0 | K36: 0 | L36: 0 | M36: 0 | N36: 0 | O36: =SUM(C36:N36) -> 0
A37: Storage (Like Dropbox) | B37: Budget | O37: =SUM(C37:N37) -> 0
B38: Actual | O38: =SUM(C38:N38) -> 0
A39: ELEMENTOR - PAGE BUILDER | B39: Actual 2024 | O39: =SUM(C39:N39) -> 0
B40: Estimated | C40: 0 | D40: 0 | E40: 0 | F40: 0 | G40: 0 | H40: 300 | I40: 0 | J40: 0 | K40: 0 | L40: 0 | M40: 99 | N40: 0 | O40: =SUM(C40:N40) -> 399
A41: CMS, Website database | B41: Budget | O41: =SUM(C41:N41) -> 0
A42: Ecommerice | B42: Actual | H42: 207.96 | O42: =SUM(C42:N42) -> 207.96
A43: WP ZOOM (Inspiro Theme) | B43: Actual 2024 | K43: 79 | O43: =SUM(C43:N43) -> 79
B44: Estimated | C44: 0 | D44: 0 | E44: 0 | F44: 0 | G44: 0 | H44: 0 | I44: 0 | J44: 0 | K44: 90 | L44: 0 | M44: 0 | N44: 0 | O44: =SUM(C44:N44) -> 90
B45: Budget | O45: =SUM(C45:N45) -> 0
B46: Actual | K46: 79 | O46: =SUM(C46:N46) -> 79
A47: LUCID CHART (For managing our Hubspot workflows and Org Chart) | B47: Actual 2024 | G47: 778.53 | M47: 4895.3 | O47: =SUM(C47:N47) -> 5673.83
B48: Estimated | C48: 0 | D48: 0 | E48: 0 | F48: 0 | G48: 0 | H48: 0 | I48: 0 | J48: 0 | K48: 0 | L48: 6000 | M48: 0 | N48: 0 | O48: =SUM(C48:N48) -> 6000
B49: Budget | O49: =SUM(C49:N49) -> 0
B50: Actual | K50: 271.7 | M50: 6854.37 | O50: =SUM(C50:N50) -> 7126.07
A51: Music Bed | B51: Actual 2024 | K51: 1199.88 | O51: =SUM(C51:N51) -> 1199.88
B52: Estimated | C52: 0 | D52: 0 | E52: 0 | F52: 0 | G52: 0 | H52: 0 | I52: 0 | J52: 0 | K52: 1079.88 | L52: 0 | M52: 0 | N52: 0 | O52: =SUM(C52:N52) -> 1079.88
B53: Budget | O53: =SUM(C53:N53) -> 0
B54: Actual | K54: 1199.88 | L54: 3150 | O54: =SUM(C54:N54) -> 4349.88
A55: MINT CRO | B55: Actual 2024 | C55: 79 | D55: 79 | E55: 79 | F55: 79 | G55: 79 | H55: 79 | I55: 79 | J55: 79 | K55: 79 | L55: 79 | M55: 79 | N55: 79 | O55: =SUM(C55:N55) -> 948
B56: Estimated | C56: 79 | D56: 79 | E56: 79 | F56: 79 | G56: 79 | H56: 79 | I56: 79 | J56: 79 | K56: 79 | L56: 79 | M56: 79 | N56: 79 | O56: =SUM(C56:N56) -> 948
B57: Budget | O57: =SUM(C57:N57) -> 0
B58: Actual | C58: 79 | D58: 79 | E58: 79 | F58: 79 | G58: 79 | H58: 79 | I58: 79 | J58: 79 | K58: 79 | O58: =SUM(C58:N58) -> 711
A59: Hat Rack (Bret Grow) | B59: Actual 2024 | C59: 50 | D59: 50 | E59: 50 | G59: 40 | H59: 40 | I59: 40 | J59: 40 | K59: 40 | L59: 40 | M59: 40 | N59: 40 | O59: =SUM(C59:N59) -> 470
B60: Estimated | C60: 100 | D60: 100 | E60: 100 | F60: 100 | G60: 100 | H60: 100 | I60: 100 | J60: 100 | K60: 100 | L60: 100 | M60: 100 | N60: 100 | O60: =SUM(C60:N60) -> 1200
B61: Budget | O61: =SUM(C61:N61) -> 0
B62: Actual | E62: 500 | O62: =SUM(C62:N62) -> 500
A63: Figma-monthly | B63: Actual 2024 | C63: 62.7 | D63: 62.7 | E63: 62.7 | F63: 62.7 | G63: 62.7 | H63: 62.7 | I63: 62.7 | J63: 62.7 | K63: 62.7 | L63: 62.7 | M63: 62.7 | N63: 62.7 | O63: =SUM(C63:N63) -> 752.4
B64: Estimated | C64: 63 | D64: 63 | E64: 63 | F64: 63 | G64: 63 | H64: 63 | I64: 63 | J64: 63 | K64: 63 | L64: 63 | M64: 63 | N64: 63 | O64: =SUM(C64:N64) -> 756
B65: Budget | O65: =SUM(C65:N65) -> 0
B66: Actual | C66: 62.7 | D66: 62.7 | E66: 62.7 | F66: 62.7 | G66: 62.7 | H66: 62.7 | I66: 62.7 | J66: 62.7 | K66: 62.7 | O66: =SUM(C66:N66) -> 564.3
A67: Figma (Annual Renewal) | B67: Actual 2024 | C67: 150.48 | O67: =SUM(C67:N67) -> 150.48
B68: Estimated | C68: 150.48 | D68: 0 | E68: 0 | F68: 0 | G68: 0 | H68: 0 | I68: 0 | J68: 0 | K68: 0 | L68: 0 | M68: 0 | N68: 0 | O68: =SUM(C68:N68) -> 150.48
B69: Budget | O69: =SUM(C69:N69) -> 0
B70: Actual | C70: 150.48 | O70: =SUM(C70:N70) -> 150.48
A71: Pixel Film S | B71: Actual 2024 | O71: =SUM(C71:N71) -> 0
B72: Estimated | C72: 99.95 | D72: 29.95 | E72: 0 | F72: 0 | G72: 0 | H72: 0 | I72: 0 | J72: 0 | K72: 0 | L72: 0 | M72: 0 | N72: 0 | O72: =SUM(C72:N72) -> 129.9
B73: Budget | O73: =SUM(C73:N73) -> 0
B74: Actual | O74: =SUM(C74:N74) -> 0
A75: Sales Message--automated text Hubspot plugin | B75: Actual 2024 | C75: 11.34 | D75: 72.89 | E75: 29.84 | F75: 62.54 | G75: 64.5 | H75: 62.7 | I75: 69.01 | J75: 9266.21 | K75: 40.26 | L75: 52.46 | M75: 59.44 | N75: 55.32 | O75: =SUM(C75:N75) -> 9846.51
B76: Estimated | C76: 190 | D76: 190 | E76: 190 | F76: 190 | G76: 190 | H76: 190 | I76: 190 | J76: 9172 | K76: 190 | L76: 190 | M76: 190 | N76: 190 | O76: =SUM(C76:N76) -> 11262
B77: Budget | O77: =SUM(C77:N77) -> 0
B78: Actual | C78: 61.22 | D78: 60.73 | E78: 30.87 | F78: 31.29 | G78: =95.58+100.4 -> 195.98 | H78: =11.47+101.29 -> 112.76 | I78: 103.04 | J78: =32.53+43.06+9604.18 -> 9679.77 | K78: 174.91 | O78: =SUM(C78:N78) -> 10450.57
A79: REGISTER@FAA 347EPXH | B79: Actual 2024 | O79: =SUM(C79:N79) -> 0
B80: Estimated | C80: 0 | D80: 5 | E80: 0 | F80: 0 | G80: 0 | H80: 0 | I80: 0 | J80: 0 | K80: 0 | L80: 0 | M80: 0 | N80: 0 | O80: =SUM(C80:N80) -> 5
B81: Budget | O81: =SUM(C81:N81) -> 0
B82: Actual | O82: =SUM(C82:N82) -> 0
A83: Referral Rock--affiliate marketing system fee (not variable incentive) | B83: Actual 2024 | H83: 800 | I83: 400 | J83: 400 | K83: 400 | L83: 400 | M83: 400 | N83: 400 | O83: =SUM(C83:N83) -> 3200
B84: Estimated | C84: 400 | D84: 400 | E84: 400 | F84: 4800 | G84: 400 | H84: 400 | I84: 400 | J84: 400 | K84: 400 | L84: 400 | M84: 400 | N84: 400 | O84: =SUM(C84:N84) -> 9200
B85: Budget | O85: =SUM(C85:N85) -> 0
B86: Actual | C86: 400 | D86: 400 | E86: 400 | F86: 400 | G86: 400 | H86: 400 | I86: 400 | J86: 400 | K86: 400 | O86: =SUM(C86:N86) -> 3600
A87: Genie AI Chatbot | B87: Actual 2024 | O87: =SUM(C87:N87) -> 0
B88: Estimated | C88: 0 | D88: 0 | E88: 0 | F88: 0 | G88: 0 | H88: 0 | I88: 0 | J88: 0 | K88: 0 | L88: 0 | M88: 0 | N88: 0 | O88: =SUM(C88:N88) -> 0
B89: Budget | O89: =SUM(C89:N89) -> 0
B90: Actual | O90: =SUM(C90:N90) -> 0
A91: AddShoppers | B91: Actual 2024 | O91: =SUM(C91:N91) -> 0
B92: Estimated | C92: 0 | D92: 0 | E92: 0 | F92: 0 | G92: 0 | H92: 0 | I92: 0 | J92: 0 | K92: 0 | L92: 0 | M92: 0 | N92: 0 | O92: =SUM(C92:N92) -> 0
B93: Budget | O93: =SUM(C93:N93) -> 0
B94: Actual | O94: =SUM(C94:N94) -> 0
A95: MVP Media Network | B95: Actual 2024 | O95: =SUM(C95:N95) -> 0
B96: Estimated | C96: 0 | D96: 0 | E96: 0 | F96: 0 | G96: 0 | H96: 0 | I96: 0 | J96: 747 | K96: 0 | L96: 0 | M96: 0 | N96: 0 | O96: =SUM(C96:N96) -> 747
B97: Budget | O97: =SUM(C97:N97) -> 0
B98: Actual | O98: =SUM(C98:N98) -> 0
A99: The Events Cal Plugins | B99: Actual 2024 | O99: =SUM(C99:N99) -> 0
B100: Estimated | C100: 0 | D100: 0 | E100: 0 | F100: 0 | G100: 0 | H100: 0 | I100: 0 | J100: 103.46 | K100: 0 | L100: 0 | M100: 0 | N100: 0 | O100: =SUM(C100:N100) -> 103.46
B101: Budget | O101: =SUM(C101:N101) -> 0
...

Sheet 5315-630 Technology (MIS)
A1: 5315-630 Technology Services (Cost Center MIS)
C2: January | D2: February | E2: March | F2: April | G2: May | H2: June | I2: July | J2: August | K2: September | L2: October | M2: November | N2: December | O2: Total
A3: TOTAL | B3: Actual 2024 | C3: =SUMIFS(C$11:C972,$B$11:$B972,"Actual 2024") -> 2933.06 | D3: =SUMIFS(D$11:D972,$B$11:$B972,"Actual 2024") -> 4322.33 | E3: =SUMIFS(E$11:E972,$B$11:$B972,"Actual 2024") -> 43334.07 | F3: =SUMIFS(F$11:F972,$B$11:$B972,"Actual 2024") -> 7210.86 | G3: =SUMIFS(G$11:G972,$B$11:$B972,"Actual 2024") -> 4411.65 | H3: =SUMIFS(H$11:H972,$B$11:$B972,"Actual 2024") -> 4692.31 | I3: =SUMIFS(I$11:I972,$B$11:$B972,"Actual 2024") -> 5262.45 | J3: =SUMIFS(J$11:J972,$B$11:$B972,"Actual 2024") -> 4715.69 | ... O3: =SUMIFS(O$11:O972,$B$11:$B972,"Actual 2024") -> 100353.52 | P3: ??
B4: Estimated | C4: =SUMIFS(C$11:C972,$B$11:$B972,"Estimated") -> 2984.8 | D4: =SUMIFS(D$11:D972,$B$11:$B972,"Estimated") -> 38680 | E4: =SUMIFS(E$11:E972,$B$11:$B972,"Estimated") -> 60292.81 | F4: =SUMIFS(F$11:F972,$B$11:$B972,"Estimated") -> 2544.31 | G4: =SUMIFS(G$11:G972,$B$11:$B972,"Estimated") -> 1612.94 | H4: =SUMIFS(H$11:H972,$B$11:$B972,"Estimated") -> 1605.61 | I4: =SUMIFS(I$11:I972,$B$11:$B972,"Estimated") -> 11339.4 | J4: =SUMIFS(J$11:J972,$B$11:$B972,"Estimated") -> 4205.61 | ... O4: =SUMIFS(O$11:O972,$B$11:$B972,"Estimated") -> 131044.42 | P4: ?? | Q4: =O4-O3 -> 30690.9
B5: Budget | C5: 0 | D5: 0 | E5: 0 | F5: 0 | G5: 0 | H5: 0 | I5: 0 | J5: 0 | K5: 0 | L5: 0 | M5: 0 | N5: 0 | O5: =SUM(C5:N5) -> 0 | P5: ??
B6: Actual | C6: =SUMIFS(C$11:C977,$B$11:$B977,"Actual") -> 3692.29 | D6: =SUMIFS(D$11:D977,$B$11:$B977,"Actual") -> 38805.87 | E6: =SUMIFS(E$11:E977,$B$11:$B977,"Actual") -> 61092.63 | F6: =SUMIFS(F$11:F977,$B$11:$B977,"Actual") -> 21354.83 | G6: =SUMIFS(G$11:G977,$B$11:$B977,"Actual") -> 2325.79 | H6: =SUMIFS(H$11:H977,$B$11:$B977,"Actual") -> 1536.36 | I6: =SUMIFS(I$11:I977,$B$11:$B977,"Actual") -> 1381.84 | J6: =SUMIFS(J$11:J977,$B$11:$B977,"Actual") -> 1381.69 | ... O6: =SUMIFS(O$11:O977,$B$11:$B977,"Actual") -> 131571.3
B7: Budget Deficit/ Savings | C7: =C5-C6 -> -3692.29 | D7: =D5-D6 -> -38805.87 | E7: =E5-E6 -> -61092.63 | F7: =F5-F6 -> -21354.83 | G7: =G5-G6 -> -2325.79 | H7: =H5-H6 -> -1536.36 | I7: =I5-I6 -> -1381.84 | J7: =J5-J6 -> -1381.69 | ... O7: =O5-O6 -> -131571.3
B8: Year to Date Spend | C8: =SUM($C6:C6) -> 3692.29 | D8: =SUM($C6:D6) -> 42498.16 | E8: =SUM($C6:E6) -> 103590.79 | F8: =SUM($C6:F6) -> 124945.62 | G8: =SUM($C6:G6) -> 127271.41 | H8: =SUM($C6:H6) -> 128807.77 | I8: =SUM($C6:I6) -> 130189.61 | J8: =SUM($C6:J6) -> 131571.3 | ... N8: =SUM($C6:N6) -> 131571.3 | O8: =O6 -> 131571.3
B9: YTD Excess From Budget | C9: =SUM($C5:C5)-C8 -> -3692.29 | D9: =SUM($C5:D5)-D8 -> -42498.16 | E9: =SUM($C5:E5)-E8 -> -103590.79 | F9: =SUM($C5:F5)-F8 -> -124945.62 | G9: =SUM($C5:G5)-G8 -> -127271.41 | H9: =SUM($C5:H5)-H8 -> -128807.77 | I9: =SUM($C5:I5)-I8 -> -130189.61 | J9: =SUM($C5:J5)-J8 -> -131571.3 | ... N9: =SUM($C5:N5)-N8 -> -131571.3
A11: Dropbox | B11: Actual 2024 | C11: 1805.76 | F11: 1805.76 | K11: 1865.95 | L11: 1865.95 | O11: =SUM(C11:N11) -> 7343.42
B12: Estimated | C12: 1504.8 | D12: 0 | E12: 0 | F12: 0 | G12: 0 | H12: 0 | I12: 9028 | J12: 0 | K12: 250 | L12: 0 | M12: 0 | N12: 0 | O12: =SUM(C12:N12) -> 10782.8
B13: Budget | O13: =SUM(C13:N13) -> 0
B14: Actual | C14: 1865.95 | F14: 1865.95 | O14: =SUM(C14:N14) -> 3731.9
A15: Hubspot | B15: Actual 2024 | E15: 38975.08 | F15: 805.65 | I15: 608.45 | K15: 466.56 | L15: 392.02 | O15: =SUM(C15:N15) -> 41247.76
B16: Estimated | C16: 0 | D16: 0 | E16: 58687.2 | F16: 926.5 | H16: 0 | I16: 699.72 | J16: 0 | K16: 536.54 | L16: 450.82 | M16: 0 | N16: 0 | O16: =SUM(C16:N16) -> 61300.78
B17: Budget | O17: =SUM(C17:N17) -> 0
B18: Actual | C18: 158.73 | E18: 59565 | F18: =17100.1+719.42 -> 17819.52 | G18: 716.42 | O18: =SUM(C18:N18) -> 78259.67
A19: Adobe | B19: Actual 2024 | O19: =SUM(C19:N19) -> 0
B20: Estimated | C20: 0 | D20: 0 | E20: 0 | F20: 12.2 | G20: 7.33 | H20: 0 | I20: 6.07 | J20: 0 | K20: 0 | L20: 0 | M20: 0 | N20: 0 | O20: =SUM(C20:N20) -> 25.6
B21: Budget | O21: =SUM(C21:N21) -> 0
B22: Actual | E22: 4.56 | F22: 31.41 | O22: =SUM(C22:N22) -> 35.97
A23: Heinsen - Mobile App | B23: Actual 2024 | O23: =SUM(C23:N23) -> 0
B24: Estimated | C24: 0 | D24: 0 | E24: 0 | F24: 0 | G24: 0 | H24: 0 | I24: 0 | J24: 0 | K24: 0 | L24: 0 | M24: 0 | N24: 0 | O24: =SUM(C24:N24) -> 0
B25: Budget | O25: =SUM(C25:N25) -> 0
B26: Actual | O26: =SUM(C26:N26) -> 0
A27: Map Tiler - Mobile App | B27: Actual 2024 | O27: =SUM(C27:N27) -> 0
B28: Estimated | C28: 0 | D28: 0 | E28: 0 | F28: 0 | G28: 0 | H28: 0 | I28: 0 | J28: 0 | K28: 119.14 | L28: 0 | M28: 0 | N28: 0 | O28: =SUM(C28:N28) -> 119.14
B29: Budget | O29: =SUM(C29:N29) -> 0
B30: Actual | O30: =SUM(C30:N30) -> 0
A31: Conductor | B31: Actual 2024 | D31: 3100 | E31: 3100 | F31: 3100 | G31: 3100 | H31: 3100 | I31: 3100 | J31: 3100 | K31: 3100 | L31: 3100 | M31: 3100 | N31: 3100 | O31: =SUM(C31:N31) -> 34100
B32: Estimated | C32: 0 | D32: 37200 | E32: 0 | F32: 0 | G32: 0 | H32: 0 | I32: 0 | J32: 0 | K32: 0 | L32: 0 | M32: 0 | N32: 0 | O32: =SUM(C32:N32) -> 37200
B33: Budget | O33: =SUM(C33:N33) -> 0
B34: Actual | D34: 37200 | O34: =SUM(C34:N34) -> 37200
A35: Adobe Creative Cloud (Nephi) | B35: Actual 2024 | C35: 176.68 | D35: 266.89 | E35: 266.89 | F35: 266.89 | G35: 266.89 | H35: 266.89 | I35: 282.59 | J35: 282.59 | K35: 282.59 | L35: 282.59 | M35: 298.29 | N35: 298.29 | O35: =SUM(C35:N35) -> 3238.07
B36: Estimated | C36: 380 | D36: 380 | E36: 380 | F36: 380 | G36: 380 | H36: 380 | I36: 380 | J36: 380 | K36: 380 | L36: 380 | M36: 380 | N36: 380 | O36: =SUM(C36:N36) -> 4560
B37: Budget | O37: =SUM(C37:N37) -> 0
B38: Actual | C38: 298.29 | D38: 298.29 | E38: 298.29 | F38: 298.29 | G38: 324.25 | H38: 324.45 | O38: =SUM(C38:N38) -> 1841.86
A39: Adobe Creative Cloud (Seth + Virginia) | B39: Actual 2024 | G39: -21.55 | H39: 94.2 | I39: 94.2 | J39: 94.2 | K39: 94.2 | L39: 94.2 | M39: 94.2 | N39: 94.2 | O39: =SUM(C39:N39) -> 637.85
B40: Estimated | C40: 0 | D40: 0 | E40: 94.2 | F40: 94.2 | G40: 94.2 | H40: 94.2 | I40: 94.2 | J40: 94.2 | K40: 94.2 | L40: 94.2 | M40: 94.2 | N40: 94.2 | O40: =SUM(C40:N40) -> 942
B41: Budget | O41: =SUM(C41:N41) -> 0
B42: Actual | C42: 94.2 | D42: 94.2 | E42: 94.2 | F42: 94.2 | G42: 94.2 | I42: 188.46 | J42: =62.82+62.82+62.82 -> 188.46 | O42: =SUM(C42:N42) -> 847.92
A43: Adobe Creative Cloud (Mia) | B43: Actual 2024 | G43: -21.55 | H43: 94.2 | I43: 94.2 | J43: 94.2 | K43: 94.2 | L43: 94.2 | M43: 94.2 | N43: 94.2 | O43: =SUM(C43:N43) -> 637.85
B44: Estimated | C44: 0 | D44: 0 | E44: 31.41 | F44: 31.41 | G44: 31.41 | H44: 31.41 | I44: 31.41 | J44: 31.41 | K44: 31.41 | L44: 31.41 | M44: 31.41 | N44: 31.41 | O44: =SUM(C44:N44) -> 314.1
B45: Budget | O45: =SUM(C45:N45) -> 0
B46: Actual | C46: 31.41 | D46: 31.41 | E46: 31.41 | F46: 31.41 | G46: 31.41 | H46: 31.41 | I46: 31.41 | O46: =SUM(C46:N46) -> 219.87
A47: Cloudflare--host flattened pages (Japan) | B47: Actual 2024 | O47: =SUM(C47:N47) -> 0
B48: Estimated | C48: 0 | D48: 0 | E48: 0 | F48: 0 | G48: 0 | H48: 0 | I48: 0 | J48: 2600 | K48: 0 | L48: 0 | M48: 0 | N48: 0 | O48: =SUM(C48:N48) -> 2600
B49: Budget | O49: =SUM(C49:N49) -> 0
B50: Actual | O50: =SUM(C50:N50) -> 0
A51: Amazon Web Services (AWS) | B51: Actual 2024 | C51: 950.62 | D51: 955.44 | E51: 992.1 | F51: 1232.56 | G51: 1087.86 | H51: 1137.02 | I51: 1083.01 | J51: 1144.7 | K51: 1160.66 | L51: 1111.02 | M51: 1158.55 | N51: 1135.03 | O51: =SUM(C51:N51) -> 13148.57
B52: Estimated | C52: 1100 | D52: 1100 | E52: 1100 | F52: 1100 | G52: 1100 | H52: 1100 | I52: 1100 | J52: 1100 | K52: 1100 | L52: 1100 | M52: 1100 | N52: 1100 | O52: =SUM(C52:N52) -> 13200
B53: Budget | O53: =SUM(C53:N53) -> 0
B54: Actual | C54: 1243.71 | D54: 1181.97 | E54: 1099.17 | F54: 1214.05 | G54: 1159.51 | H54: 1180.5 | I54: 1161.97 | J54: 1193.23 | O54: =SUM(C54:N54) -> 9434.11
B55: Actual 2024 | O55: =SUM(C55:N55) -> 0
B56: Estimated | C56: 0 | D56: 0 | E56: 0 | F56: 0 | G56: 0 | H56: 0 | I56: 0 | J56: 0 | K56: 0 | L56: 0 | M56: 0 | N56: 0 | O56: =SUM(C56:N56) -> 0
B57: Budget | O57: =SUM(C57:N57) -> 0
B58: Actual | O58: =SUM(C58:N58) -> 0
B59: Actual 2024 | O59: =SUM(C59:N59) -> 0
B60: Estimated | C60: 0 | D60: 0 | E60: 0 | F60: 0 | G60: 0 | H60: 0 | I60: 0 | J60: 0 | K60: 0 | L60: 0 | M60: 0 | N60: 0 | O60: =SUM(C60:N60) -> 0
B61: Budget | O61: =SUM(C61:N61) -> 0
B62: Actual | O62: =SUM(C62:N62) -> 0
B63: Actual 2024 | O63: =SUM(C63:N63) -> 0
B64: Estimated | C64: 0 | D64: 0 | E64: 0 | F64: 0 | G64: 0 | H64: 0 | I64: 0 | J64: 0 | K64: 0 | L64: 0 | M64: 0 | N64: 0 | O64: =SUM(C64:N64) -> 0
B65: Budget | O65: =SUM(C65:N65) -> 0
B66: Actual | O66: =SUM(C66:N66) -> 0
B67: Actual 2024 | O67: =SUM(C67:N67) -> 0
B68: Estimated | C68: 0 | D68: 0 | E68: 0 | F68: 0 | G68: 0 | H68: 0 | I68: 0 | J68: 0 | K68: 0 | L68: 0 | M68: 0 | N68: 0 | O68: =SUM(C68:N68) -> 0
B69: Budget | O69: =SUM(C69:N69) -> 0
B70: Actual | O70: =SUM(C70:N70) -> 0
B71: Actual 2024 | O71: =SUM(C71:N71) -> 0
B72: Estimated | C72: 0 | D72: 0 | E72: 0 | F72: 0 | G72: 0 | H72: 0 | I72: 0 | J72: 0 | K72: 0 | L72: 0 | M72: 0 | N72: 0 | O72: =SUM(C72:N72) -> 0
B73: Budget | O73: =SUM(C73:N73) -> 0
B74: Actual | O74: =SUM(C74:N74) -> 0

Sheet 5322-510 Gifts
A1: 5322-510 Gifts
C2: January | D2: February | E2: March | F2: April | G2: May | H2: June | I2: July | J2: August | K2: September | L2: October | M2: November | N2: December | O2: Total
